Workbook

Sheet OPTIONAL
A1: OPTIONAL
A3: GRADE 1
A4: Graphs | B4: Unit 1A: Lists and Tables | C4: 1.1 Making, reading and interpreting lists and tables | D4: PINE_G1_C14_P1.1.1 | E4: Ch 14 Practice 1.1.1: Making lists | F4: To present data in lists and tables
D5: PINE_G1_C14_P1.1.2 | E5: Ch 14 Practice 1.1.2: Reading and interpreting lists | F5: To read and interpret lists and tables
D6: PINE_G1_C14_P1.1.3 | E6: Ch 14 Practice 1.1.3: Making tables | F6: To present data in lists and tables
D7: PINE_G1_C14_P1.1.4 | E7: Ch 14 Practice 1.1.4: Reading and interpreting tables | F7: To read and interpret lists and tables
A8: Mental Strategies | B8: Unit 1: Number Bonds | C8: 1.1 Pairing 1-digit numbers | D8: PINE_G2_C09_P1.1.1 | E8: Ch 9 Practice 1.1.1: Pairing 1-digit numbers | F8: To find pairs of 1-digit numbers with a total up to 18 and write the addition and subtraction facts for each number pair | G8: M1AL-IIIh-8 | H8: Patterns and Algebra | I8: constructs equivalent number expression using addition and subtraction.
D9: PINE_G2_C09_P1.1.2 | E9: Ch 9 Practice 1.1.2: Finding the missing part in an addition sentence | F9: To find the missing part in an addition sentence | G9: M1AL-IIIh-8 | H9: Patterns and Algebra | I9: constructs equivalent number expression using addition and subtraction.
D10: PINE_G2_C09_P1.1.3 | E10: Ch 9 Practice 1.1.3: Finding the missing part or whole in a subtraction sentence | F10: To find the missing part or whole in a subtraction sentence | G10: M1AL-IIIh-8 | H10: Patterns and Algebra | I10: constructs equivalent number expression using addition and subtraction.
D11: PINE_G2_C09_P1.1.4 | E11: Ch 9 Practice 1.1.4: Representing equality | F11: To use the = sign to represent equality, e.g. 16 + 4 = 17 + 3 | G11: M1AL-IIIh-8 | H11: Patterns and Algebra | I11: constructs equivalent number expression using addition and subtraction.
A12: Multiplication | B12: Unit 1: Adding Equal Groups | C12: 1.1 Adding the same number | F12: To recognize equal groups and find the total number in the groups by repeated addition To add equal groups using number lines | G12: M1NS-IIIa-37 | H12: Numbers and Number sense | I12: counts groups of equal quantity using concrete objects up to 50 and writes an equivalent expression. e.g. 2 groups of 5
D13: PINE_G2_C06_P1.1.2 | E13: Ch 6 Practice 1.1.2: Describing equal groups | F13: To use mathematical language such as ‘4 threes’ to describe equal groups | G13: M1NS-IIIa-37 | H13: Numbers and Number sense | I13: counts groups of equal quantity using concrete objects up to 50 and writes an equivalent expression. e.g. 2 groups of 5
C14: 1.2 Telling number stories | D14: PINE_G2_C06_P1.2.1 | E14: Ch 6 Practice 1.2.1: Telling number stories | F14: To tell a number story by finding the total number in the groups using repeated addition | G14: M1NS-IIIa-37 | H14: Numbers and Number sense | I14: counts groups of equal quantity using concrete objects up to 50 and writes an equivalent expression. e.g. 2 groups of 5
D15: PINE_G2_C06_P1.2.2 | E15: Ch 6 Practice 1.2.2: Describing equal groups | F15: To use mathematical language such as ‘2 groups of 5’ to describe equal groups | G15: M1NS-IIIa-37 | H15: Numbers and Number sense | I15: counts groups of equal quantity using concrete objects up to 50 and writes an equivalent expression. e.g. 2 groups of 5
B16: Unit 2: Making Multiplication Stories | C16: 2.1 Making multiplication stories | D16: PINE_G2_C06_P2.1.1 | E16: Ch 6 Practice 2.1.1: Illustrating the meaning of multiplication | F16: To use manipulatives to illustrate the meaning of multiplication | G16: M1NS-IIIa-37 | H16: Numbers and Number sense | I16: counts groups of equal quantity using concrete objects up to 50 and writes an equivalent expression. e.g. 2 groups of 5
D17: PINE_G2_C06_P2.1.2 | E17: Ch 6 Practice 2.1.2: Making multiplication stories | F17: To make a number story for a given multiplication sentence | G17: M1NS-IIIa-37 | H17: Numbers and Number sense | I17: counts groups of equal quantity using concrete objects up to 50 and writes an equivalent expression. e.g. 2 groups of 5
D18: PINE_G2_C06_P2.1.3 | E18: Ch 6 Practice 2.1.3: Writing multiplication sentences | F18: To write a number sentence for a given situation involving multiplication | G18: M1NS-IIIa-37 | H18: Numbers and Number sense | I18: counts groups of equal quantity using concrete objects up to 50 and writes an equivalent expression. e.g. 2 groups of 5
D19: PINE_G2_C06_P2.1.4 | E19: Ch 6 Practice 2.1.4: Using array to show multiplication sentences | F19: To understand multiplication as describing an array | G19: M1NS-IIIa-37 | H19: Numbers and Number sense | I19: counts groups of equal quantity using concrete objects up to 50 and writes an equivalent expression. e.g. 2 groups of 5
D20: PINE_G2_C06_P2.1.5 | E20: Ch 6 Practice 2.1.5: Understanding the meaning of product | G20: M1NS-IIIa-37 | H20: Numbers and Number sense | I20: counts groups of equal quantity using concrete objects up to 50 and writes an equivalent expression. e.g. 2 groups of 5
A21: Division | B21: Unit 1: Sharing and Grouping | C21: 1.1 Finding the number of objects in each group | D21: PINE_G2_C07_P1.1.1 | E21: Ch 7 Practice 1.1.1: Finding the number of objects in each group | F21: To use objects and manipulatives to illustrate the sharing concept of division | G21: M1NS-IIIa-48 | H21: Numbers and Number sense | I21: visualizes, represents, and separates objects into groups of equal quantity using concrete objects up to 50. e.g. 10 grouped by 5s
D22: PINE_G2_C07_P1.1.2 | E22: Ch 7 Practice 1.1.2: Understanding that division can leave some left over | F22: To understand that division can leave some left over | G22: M1NS-IIIa-48 | H22: Numbers and Number sense | I22: visualizes, represents, and separates objects into groups of equal quantity using concrete objects up to 50. e.g. 10 grouped by 5s
C23: 1.2 Finding the number of equal groups | D23: PINE_G2_C07_P1.2.1 | E23: Ch 7 Practice 1.2.1: Finding the number of equal groups | F23: To use objects and manipulatives to illustrate the grouping concept of division To find the number of equal groups using a number line | G23: M1NS-IIIa-48 | H23: Numbers and Number sense | I23: visualizes, represents, and separates objects into groups of equal quantity using concrete objects up to 50. e.g. 10 grouped by 5s
D24: PINE_G2_C07_P1.2.2 | E24: Ch 7 Practice 1.2.2: Understanding that division can leave some left over | F24: To understand that division can leave some left over | G24: M1NS-IIIa-48 | H24: Numbers and Number sense | I24: visualizes, represents, and separates objects into groups of equal quantity using concrete objects up to 50. e.g. 10 grouped by 5s
C25: 1.3 Telling division stories | D25: PINE_G2_C07_P1.3.1 | E25: Ch 7 Practice 1.3.1: Telling division stories | F25: To make number stories for a given division sentence | G25: M1NS-IIIa-48 | H25: Numbers and Number sense | I25: visualizes, represents, and separates objects into groups of equal quantity using concrete objects up to 50. e.g. 10 grouped by 5s
A27: GRADE 2
A28: Graphs | B28: Unit 2: Block Graphs | C28: 2.1 Making, reading and interpreting block graphs | D28: PINE_G2_C15_P2.1.1 | E28: Ch 15 Practice 2.1.1: Making block graphs | F28: To present data given in lists and tables as block graphs
D29: PINE_G2_C15_P2.1.2 | E29: Ch 15 Practice 2.1.2: Reading and interpreting block graphs | F29: To read and interpret block graphs
B30: Unit 2A: Line Plots | C30: 2A.1 Making, reading and interpreting line plots | D30: PINE_G2_C15_P2A.1.1 | E30: Ch 15 Practice 2A.1.1: Making, reading and interpreting line plots | F30: To make, read and interpret a line plot
B31: Unit 3: Carroll Diagrams | C31: 3.1 Sorting data in Carroll diagrams | D31: PINE_G2_C15_P3.1.1 | E31: Ch 15 Practice 3.1.1: Grouping objects in Carroll diagrams | F31: To group objects in Carroll diagrams using different criteria
D32: PINE_G2_C15_P3.1.2 | E32: Ch 15 Practice 3.1.2: Sorting data in Carroll diagrams | F32: To sort data in Carroll diagrams with 1 criterion and read the Caroll diagrams
A33: Symmetry | B33: Unit 4: Symmetry | C33: 3.1 Identifying and making symmetric figures | D33: PINE_G2_C16_P3.1.1 | E33: Ch 16 Practice 3.1.1: Identifying symmetric figures | F33: To identify a symmetric figure | G33: M2GE-IIIh-7.1 | H33: Geometry | I33: identifies shapes/figures that show symmetry in a line
D34: PINE_G2_C16_P3.1.2 | E34: Ch 16 Practice 3.1.2: Making symmetric figures | F34: To cut out a symmetric figure from a piece of folded paper | G34: M2GE-IIIh-7.2 | H34: Geometry | I34: creates figures that show symmetry in a line.
D35: PINE_G2_C16_P3.1.3 | E35: Ch 16 Practice 3.1.3: Identifying symmetry in the environment | F35: To find examples of symmetry in the environment | G35: M2GE-IIIh-7.4a | H35: Geometry | I35: identifies and draws the line of symmetry in a given symmetrical figure
C36: 3.2 Identifying and drawing lines of symmetry | D36: PINE_G2_C16_P3.2.1 | E36: Ch 16 Practice 3.2.1: Identifying and drawing lines of symmetry | F36: To determine whether a straight line is a line of symmetry of a figure or pattern To draw a line of symmetry in figures and patterns | G36: M2GE-IIIh-7.4a | H36: Geometry | I36: identifies and draws the line of symmetry in a given symmetrical figure
A37: Capacity | B37: Unit 1: Capacity in Liters | C37: 1.1 Measuring and comparing capacities in liters | D37: PINE_G2_C05_P1.1.1 | E37: Ch 5 Practice 1.1.1: Measuring and comparing capacities in liters | F37: To understand the need for standardized units of measurement of capacity To estimate and measure capacity in liters To compare capacities of two or more containers in liters | G37: M2ME-IVf-33 | H37: Measurement | I37: measures objects using appropriate measuring tools in mL or L
D38: PINE_G2_C05_P1.1.2 | E38: Ch 5 Practice 1.1.2: Ordering capacities in liters | G38: M2ME-IVf-33 | H38: Measurement | I38: measures objects using appropriate measuring tools in mL or L
B39: Unit 2: Problem Solving | C39: 2.1 Word problems | D39: PINE_G2_C05_P2.1.1 | E39: Ch 5 Practice 2.1.1: Word problems | F39: To solve 1-step word problems involving capacity
C40: 2.2 More word problems | D40: PINE_G2_C05_P2.2.1 | E40: Ch 5 Practice 2.2.1: More word problems | F40: To solve 2-step word problems involving capacity
A41: Customary Units of Length | B41: Unit 1: Length in Inches | C41: 1.1 Measuring and comparing lengths in inches | F41: To estimate and measure length in inches To measure the lengths of two objects to determine how much longer one object is than another, expressing the length difference in terms of inches
C42: 1.2 Measuring lines and curves | D42: PINE_G2_C10A_P1.2.1 | E42: Ch 10A Practice 1.2.1: Measuring lines and curves | F42: To measure the length of a line or curve in inches
C43: 1.3 Drawing lines | D43: PINE_G2_C10A_P1.3.1 | E43: Ch 10A Practice 1.3.1: Drawing lines | F43: To draw a line of a given length in inches
B44: Unit 2: Length in Feet | C44: 2.1 Measuring and comparing lengths in feet | D44: PINE_G2_C10A_P2.1.1 | E44: Ch 10A Practice 2.1.1: Measuring and comparing lengths in feet | F44: To understand that a foot is longer than an inch To estimate and measure length in feet To measure the lengths of two objects to determine how much longer one object is than another, expressing the length difference in terms of feet
B45: Unit 3: Length in Yards | C45: 3.1 Measuring and comparing lengths in yards | D45: PINE_G2_C10A_P3.1.1 | E45: Ch 10A Practice 3.1.1: Measuring and comparing lengths in yards | F45: To understand that a yard is longer than a foot To estimate and measure length in yards To measure the lengths of two objects to determine how much longer one object is than another, expressing the length difference in terms of yards
C46: 3.2 Choosing tools or units of measure | D46: PINE_G2_C10A_P3.2.1 | E46: Ch 10A Practice 3.2.1: Choosing tools or units of measure | F46: To choose an appropriate tool or unit of measure when measuring lengths and distances
B47: Unit 4: Problem Solving | C47: 4.1 Word problems | D47: PINE_G2_C10A_P4.1.1 | E47: Ch 10A Practice 4.1.1: Word problems | F47: To solve 1-step word problems on length
C48: 4.2 More word problems | D48: PINE_G2_C10A_P4.2.1 | E48: Ch 10A Practice 4.2.1: More word problems | F48: To solve 2-step word problems on length
A50: GRADE 3
A51: Graphs | B51: Unit 3: Venn Diagrams | C51: 3.1 Sorting data in Venn diagrams with 1 criterion | D51: PINE_G3_C07_P3.1.1 | E51: Ch 7 Practice 3.1.1: Grouping objects in Venn diagrams | F51: To group objects in Venn diagrams using different criteria
D52: PINE_G3_C07_P3.1.2 | E52: Ch 7 Practice 3.1.2: Sorting data in Venn diagrams with 1 criterion | F52: To sort data in Venn diagrams with 1 criterion and read the Venn diagrams
B53: Unit 4: Carroll Diagrams | C53: 4.1 Sorting data in Carroll diagrams with 2 or 3 criteria | D53: PINE_G3_C07_P4.1.1 | E53: Ch 7 Practice 4.1.1: Sorting data in Carroll diagrams with 2 or 3 criteria | F53: To sort data in Carroll diagrams with 2 criteria To sort data in Carroll diagrams with 3 criteria
B54: Unit 4: Doubles and Halves | C54: 4.1 Finding doubles of 2-digit numbers | D54: PINE_G3_C06_P4.1.1 | E54: Ch 6 Practice 4.1.1: Finding doubles of 2-digit numbers | F54: To find doubles of tens up to 100 mentally To find doubles of 2-digit numbers mentally
C55: 4.2 Finding halves of numbers up to 200 | D55: PINE_G3_C06_P4.2.1 | E55: Ch 6 Practice 4.2.1: Finding halves of numbers up to 200 | F55: To find halves of tens up to 200 mentally To find halves of even numbers up to 200 mentally
A56: Tessellations | B56: Unit 1: Tiling Patterns | C56: 1.1 Recognizing shapes that can tessellate | D56: PINE_G5_C15A_P1.1.1 | E56: Ch 15A Practice 1.1.1: Recognizing shapes that can tessellate | F56: Recognize shapes that can tessellate | G56: M3GE-IIIh-8.3 | H56: Geometry | I56: tessellates the plane using triangles, squares and other shapes that can tessellate.
D57: PINE_G5_C15A_P1.1.2 | E57: Ch 15A Practice 1.1.2: Identifying the unit shape in tessellations | F57: Identify the unit shape in a tessellation | G57: M3GE-IIIh-8.3 | H57: Geometry | I57: tessellates the plane using triangles, squares and other shapes that can tessellate.
D58: PINE_G5_C15A_P1.1.3 | E58: Ch 15A Practice 1.1.3: Drawing tessellations on dot paper | F58: Draw a tessellation on dot paper | G58: M3GE-IIIh-8.3 | H58: Geometry | I58: tessellates the plane using triangles, squares and other shapes that can tessellate.
A59: 2D and 3D Shapes | B59: Unit 1: 2D Shapes | C59: 1.1 Identifying and describing 2D shapes | D59: PINE_G3_C14_P1.1.1 | E59: Ch 14 Practice 1.1.1: Identifying and describing 2D shapes | F59: To identify, describe and draw 2D shapes including pentagons, hexagons, octagons and semi-circles
D60: PINE_G3_C14_P1.1.2 | E60: Ch 14 Practice 1.1.2: Finding 2D shapes in the enviroment | F60: To find 2D shapes in the environment
C61: 1.2 Sorting 2D shapes | D61: PINE_G3_C14_P1.2.1 | E61: Ch 14 Practice 1.2.1: Sorting 2D shapes | F61: To sort 2D shapes according to the number of sides, vertices and right angles
C62: 1.2A Combining and splitting shapes | D62: PINE_G3_C14_P1.2A.1 | E62: Ch 14 Practice 1.2A.1: Combining shapes | F62: To fit cutouts of shapes together to make a new shape
D63: PINE_G3_C14_P1.2A.2 | E63: Ch 14 Practice 1.2A.2: Splitting shapes | F63: To identify and name basic shapes that make up a new shape
B64: Unit 3: Nets of Cubes | C64: 3.1 Making cubes | D64: PINE_G3_C14_P3.1.1 | E64: Ch 14 Practice 3.1.1: Understanding nets | F64: To understand that 3D shapes can be formed by nets
D65: PINE_G3_C14_P3.1.2 | E65: Ch 14 Practice 3.1.2: Nets of cubes | F65: To identify the nets of a cube
A66: Customary Units of Length | B66: Unit 1: Length in Inches | C66: 1.1 Measuring and comparing lengths to the nearest half inch | D66: PINE_G3_C06A_P1.1.1 | E66: Ch 6A Practice 1.1.1: Measuring and comparing lengths to the nearest half inch | F66: To measure and compare lengths to the nearest half of an inch
C67: 1.2 Measuring and comparing lengths to the nearest quarter inch | D67: PINE_G3_C06A_P1.2.1 | E67: Ch 6A Practice 1.2.1: Measuring and comparing lengths to the nearest quarter inch | F67: To measure and compare lengths to the nearest quarter of an inch
A68: Customary Units of Weight | B68: Unit 1: Weight in Pounds | C68: 1.1 Measuring weight in pounds | D68: PINE_G3_C12A_P1.1.1 | E68: Ch 12A Practice 1.1.1: Measuring weight in pounds | F68: To measure weight in pounds
C69: 1.2 Comparing weights in pounds | D69: PINE_G3_C12A_P1.2.1 | E69: Ch 12A Practice 1.2.1: Comparing weights in pounds | F69: To compare weights in pounds
B70: Unit 2: Weight in Ounces | C70: 2.1 Measuring weight in ounces | D70: PINE_G3_C12A_P2.1.1 | E70: Ch 12A Practice 2.1.1: Measuring weight in ounces | F70: To measure weight in ounces
C71: 2.2 Comparing weights in ounces | D71: PINE_G3_C12A_P2.2.1 | E71: Ch 12A Practice 2.2.1: Comparing weights in ounces | F71: To compare weights in ounces
C72: 2.3 Choosing tool or units of measure | D72: PINE_G3_C12A_P2.3.1 | E72: Ch 12A Practice 2.3.1: Choosing tool or units of measure | F72: To choose an appropriate tool or unit of measure when measuring weight
B73: Unit 3: Problem Solving | C73: 3.1 Word problems | D73: PINE_G3_C12A_P3.1.1 | E73: Ch 12A Practice 3.1.1: Word problems | F73: To solve 1-step or 2-step word problems involving weight
A74: Temperature | B74: Unit 1: Measuring Temperature | C74: 1.1 Reading temperature | D74: PINE_G3_C12B_P1.1.1 | E74: Ch 12B Practice 1.1.1: Reading temperature | F74: To use the thermometer to read temperature in Celsius or Fahrenheit
A75: Position and Movement | B75: Unit 1: Turns and Right Angles | C75: 1.1 Relating turns to right angles | D75: PINE_G3_C15_P1.1.1 | E75: Ch 15 Practice 1.1.1: Relating turns to right angles | F75: To recognise that a right angle is a quarter turn, 2 right angles is a half turn, 3 right angles is a three-quarter turn and 4 right angles is a complete turn
D76: PINE_G3_C15_P1.1.2 | E76: Ch 15 Practice 1.1.2: Relating straight lines and right angles | F76: To recognise that a straight line is equivalent to two right angles
B77: Unit 2: Position and Movement on a Grid | C77: 2.1 Interpreting grid references | D77: PINE_G3_C15_P2.1.1 | E77: Ch 15 Practice 2.1.1: Interpreting grid references | F77: To find and describe the position of a square on a grid of squares where the rows and columns are labelled
C78: 2.2 Giving directions | D78: PINE_G3_C15_P2.2.1 | E78: Ch 15 Practice 2.2.1: Giving directions | F78: To give and follow directions to a place on a grid
A80: GRADE 4
A81: Multiplying | B81: Unit 1: Multiplication | C81: 1.1 Multiplying ones, tens and hundreds by a 1-digit number | D81: PINE_G4_C03_P1.1.1 | E81: Ch 3 Practice 1.1.1: Multiplying ones, tens and hundreds by a 1-digit number | F81: To multiply ones, tens and hundreds by a 1-digit number
C82: 1.2 Multiplying 3-digit numbers by 1-digit numbers
C83: 1.3 Multiplying three 1-digit numbers | D83: PINE_G4_C03_P1.3.1 | E83: Ch 3 Practice 1.3.1: Multiplying three 1-digit numbers | F83: To multiply three 1-digit numbers using the commutative and associative properties of multiplication
C84: 1.4 Multiplying whole numbers by 10 | D84: PINE_G4_C03_P1.4.1 | E84: Ch 3 Practice 1.4.1: Multiplying whole numbers by 10 | F84: To multiply a whole number up to 3 digits by 10
C85: 1.5 Estimating products | D85: PINE_G4_C03_P1.5.1 | E85: Ch 3 Practice 1.5.1: Estimating products | F85: To estimate an answer in multiplication
D86: PINE_G4_C03_P1.5.2 | E86: Ch 3 Practice 1.5.2: Checking reasonableness | F86: To check the reasonableness of an answer in multiplication
C87: 1.6 Solving word problems | D87: PINE_G4_C03_P1.6.1 | E87: Ch 3 Practice 1.6.1: Solving word problems | F87: To solve 1-step word problems on multiplication
B88: Unit 3: Fractions and Division | C88: 3.1 Associating fractions with division | D88: PINE_G4_C04_P3.1.1 | E88: Ch 4 Practice 3.1.1: Associating fractions with division | F88: To associate a fraction with division
D89: PINE_G4_C04_P3.1.2 | E89: Ch 4 Practice 3.1.2: Expressing whole numbers as fractions | F89: To express whole numbers as fractions and recognise fractions that are equivalent to whole numbers
D90: PINE_G4_C04_P3.1.3 | E90: Ch 4 Practice 3.1.3: Dividing whole numbers to get mixed numbers | F90: To divide a whole number by another whole number and write the quotient as a mixed number
C91: 3.2 Expressing improper fractions as whole numbers or mixed numbers | D91: PINE_G4_C04_P3.2.1 | E91: Ch 4 Practice 3.2.1: Expressing improper fractions as whole numbers or mixed numbers | F91: To express an improper fraction as a whole number or a mixed number
C92: 3.3 Solving word problems | D92: PINE_G4_C04_P3.3.1 | E92: Ch 4 Practice 3.3.1: Solving word problems | F92: To solve 1-step word problems involving fractions and division
A93: Graphs | D93: PINE_G4_C07_P1.1.3 | E93: Ch 7 Practice 1.1.3: Scales with different intervals | F93: To compare the impact of representations where scales have different intervals
B94: Unit 1A: Line Plots | C94: 1A.1 Making, reading and interpreting line plots | D94: PINE_G4_C07_P1A.1.1 | E94: Ch 7 Practice 1A.1.1: Making, reading and interpreting line plots | F94: To make, read and interpret a line plot with a scale marked in whole numbers, halves, quarters or eighths
B95: Unit 2: Venn Diagrams | C95: 2.1 Sorting data in Venn diagrams with 2 criteria | D95: PINE_G4_C07_P2.1.1 | E95: Ch 7 Practice 2.1.1: Sorting data in Venn diagrams with 2 criteria | F95: To sort data in Venn diagrams with 2 criteria
C96: 2.2 Sorting data in Venn diagrams with 3 criteria | D96: PINE_G4_C07_P2.2.1 | E96: Ch 7 Practice 2.2.1: Sorting data in Venn diagrams with 3 criteria | F96: To sort data in Venn diagrams with 3 criteria
A97: Area and Volume of Triangles and Quadrilaterals | B97: Unit 1: Area of Triangles | C97: 1.3 Finding area of triangles | D97: PINE_G6_C14A_P1.3.1 | E97: Ch 14A Practice 1.3.1: Finding area of triangles | F97: To understand that every triangle has a related rectangle To find the area of a triangle using formula | G97: M4GE-IIId-18.1 | H97: Geometry | I97: relates triangles to quadrilaterals
B98: Unit 2: Area of Quadrilaterals | C98: 2.1 Finding area of parallelograms | D98: PINE_G6_C14A_P2.1.1 | E98: Ch 14A Practice 2.1.1: Finding area of parallelograms | F98: To understand that every parallelogram has a related rectangle To find the area of a parallelogram using formula | G98: M4ME-IVb-58 | H98: Measurement | I98: finds the area of triangles, parallelograms and trapezoids using sq. cm and sq. m.
C99: 2.2 Finding area of rhombuses | D99: PINE_G6_C14A_P2.2.1 | E99: Ch 14A Practice 2.2.1: Finding area of rhombuses | F99: To understand the relationship between a rhombus and a parallelogram To find the area of a rhombus using formula | G99: M4ME-IVb-58 | H99: Measurement | I99: finds the area of triangles, parallelograms and trapezoids using sq. cm and sq. m.
C100: 2.3 Finding area of trapezoids | D100: PINE_G6_C14A_P2.3.1 | E100: Ch 14A Practice 2.3.1: Finding area of trapezoids | F100: To find the area of a trapezoid using formula | G100: M4ME-IVb-58 | H100: Measurement | I100: finds the area of triangles, parallelograms and trapezoids using sq. cm and sq. m.
G101: M4ME-IVb-57 | H101: Measurement | I101: derives the formulas for the area of triangles, parallelograms, and trapezoids.
G102: M4ME-IVc-59 | H102: Measurement | I102: estimates the area of triangles, parallelograms, and trapezoids
G103: M4ME-IVd-61 | H103: Measurement | I103: creates problems(with reasonable answers) involving perimeter and area involving squares, rectangles,triangles, parallelograms, and trapezoids.
G104: M4ME-IVe-63 | H104: Measurement | I104: derives the formula for the volume of rectangular prisms.
...

Sheet Grade 1
A1: Chapter (1A: 1-10 1B: 11 - 23) | B1: Unit | C1: Lesson | D1: Digital Practices and Assessments (DPA) | G1: Assessments | J1: PH Tags at item level | P1: Reference ID | Q1: Activity Title | R1: PH Tags at activity level | AK1: MS ready for review | AL1: Cleared by Evonne | AM1: Status update | AP1: Status Update | AQ1: Next course of action | AR1: Comments
D2: Activity Reference (revised) | E2: Activity Title (revised) | F2: Objective | G2: Chpt Assessment | H2: Review | I2: Mid-Year / EOY | J2: PR1ME PH Curriculum Learning Objective Summary | K2: PH Curriculum Learning Objective (Name and Long Name) | N2: PH Curriculum Learning Objective Summary | O2: Question Category | R2: Curriculum | S2: PINE Activity Type | T2: Product Code | U2: PR1ME PH Grade | V2: PR1ME PH Chapter | W2: PR1ME PH ISBN | X2: PR1ME PH Page Number | Y2: PR1ME PH Curriculum Strand | Z2: PR1ME PH Curriculum Substrand | AA2: PR1ME PH National Curriculum Unit | AB2: PR1ME PH Curriculum Learning Objective Summary | AC2: PH Curriculum Strand | AD2: PH Curriculum Substrand | AE2: PH Curriculum Learning Objective (Name and Long Name) | AG2: PH Curriculum Learning Objective Summary | AH2: Chapter Number | AI2: PH Pre-requisite
A3: Chapter 1: Numbers 0 to 10 | B3: Unit 1: Counting and Comparing | C3: 1.1 Counting, reading and writing numbers | D3: PINE_G1_C01_P1.1.1 | E3: Ch 1 Practice 1.1.1: Counting | F3: To count within 10 (including the use of zero to denote an empty set) | G3: 1 | I3: A_01 | J3: 1.001 To count within 10 M1NS-Ia-1.1 | K3: M1NS-Ia-1.1 | L3: Visualizes and represents numbers from 0 to 100 using a variety of materials | M3: M1NS-Ia-1.1: Visualizes and represents numbers from 0 - 100 using a variety of materials. | N3: 1.001 Visualizes and represents numbers from 0 - 100 M1NS-Ia-1.1 | O3: P1/P2/A1/A2 | P3: PH_G1_C01_P1.1.1 | Q3: =E3 -> Ch 1 Practice 1.1.1: Counting | R3: PH, PR1MEPH | S3: Practice | T3: MATHPRO | U3: Grade 1 | V3: Chapter 1 Numbers 0 to 10 | W3: 9789814969369 | X3: 5 | Y3: 1. Numbers and Number Sense | Z3: G1.1.01 Whole Numbers / Place Value | AA3: Counting and Comparing | AB3: =J3 -> 1.001 To count within 10 M1NS-Ia-1.1 | AC3: =Y3 -> 1. Numbers and Number Sense | AD3: =Z3 -> G1.1.01 Whole Numbers / Place Value | AE3: =K3 -> M1NS-Ia-1.1 | AF3: =M3 -> M1NS-Ia-1.1: Visualizes and represents numbers from 0 - 100 using a variety of materials. | AG3: =N3 -> 1.001 Visualizes and represents numbers from 0 - 100 M1NS-Ia-1.1 | AH3: 1 | AI3: n.a. | AJ3: n.a. | AP3: Published | AQ3: =IF($AP3="Raw Manuscript created","Editor to review",IF($AP3="Manuscript reviewed by Editor","Author to revise",IF($AP3="Manuscript revised by Author","Editor to review",IF($AP3="Manuscript finalised by Editor","Evonne to PFP",IF($AP3="Manuscript approved by Evonne","Evelyn to upload to Learnosity",IF($AP3="Manuscript uploaded to Learnosity","Prepress to create Activity",IF($AP3="Ready practice on Learnosity","Prepress to create Activity",IF($AP3="Activity created","Editor to conduct Learnosity review",IF($AP3="Published","Completed",""))))))))) -> Completed
D4: PINE_G1_C01_P1.1.2 | E4: Ch 1 Practice 1.1.2: Reading and writing numbers | F4: To read and write a number from 0 to 10 — the numeral and the corresponding number word | G4: 2 | H4: 1 (Rev1) | I4: B_01 | J4: 1.002 To read and write a number from 0 to 10 — the numeral and the corresponding number word M1NS-Ia-1.1 | K4: M1NS-Ia-1.1 | L4: Visualizes and represents numbers from 0 to 100 using a variety of materials | M4: M1NS-Ia-1.1: Visualizes and represents numbers from 0 - 100 using a variety of materials. | N4: 1.001 Visualizes and represents numbers from 0 - 100 M1NS-Ia-1.1 | O4: P1/P2/A1/A2 | P4: PH_G1_C01_P1.1.2 | Q4: =E4 -> Ch 1 Practice 1.1.2: Reading and writing numbers | R4: PH, PR1MEPH | S4: Practice | T4: MATHPRO | U4: Grade 1 | V4: Chapter 1 Numbers 0 to 10 | W4: 9789814969369 | X4: 5 | Y4: 1. Numbers and Number Sense | Z4: G1.1.01 Whole Numbers / Place Value | AA4: Counting and Comparing | AB4: =J4 -> 1.002 To read and write a number from 0 to 10 — the numeral and the corresponding number word M1NS-Ia-1.1 | AC4: =Y4 -> 1. Numbers and Number Sense | AD4: =Z4 -> G1.1.01 Whole Numbers / Place Value | AE4: =K4 -> M1NS-Ia-1.1 | AF4: =M4 -> M1NS-Ia-1.1: Visualizes and represents numbers from 0 - 100 using a variety of materials. | AG4: =N4 -> 1.001 Visualizes and represents numbers from 0 - 100 M1NS-Ia-1.1 | AH4: 1 | AI4: PH_G1_C01_P1.1.1 | AJ4: To count within 10 (including the use of zero to denote an empty set) | AP4: Published | AQ4: =IF($AP4="Raw Manuscript created","Editor to review",IF($AP4="Manuscript reviewed by Editor","Author to revise",IF($AP4="Manuscript revised by Author","Editor to review",IF($AP4="Manuscript finalised by Editor","Evonne to PFP",IF($AP4="Manuscript approved by Evonne","Evelyn to upload to Learnosity",IF($AP4="Manuscript uploaded to Learnosity","Prepress to create Activity",IF($AP4="Ready practice on Learnosity","Prepress to create Activity",IF($AP4="Activity created","Editor to conduct Learnosity review",IF($AP4="Published","Completed",""))))))))) -> Completed
D5: PINE_G1_C01_P1.1.3 | E5: Ch 1 Practice 1.1.3: Recognizing conservation of numbers | F5: To recognise conservation of number | G5: 3 | J5: 1.003 To recognise conservation of number M1NS-Ia-1.1 | K5: M1NS-Ia-1.1 | L5: Visualizes and represents numbers from 0 to 100 using a variety of materials | M5: M1NS-Ia-1.1: Visualizes and represents numbers from 0 - 100 using a variety of materials. | N5: 1.001 Visualizes and represents numbers from 0 - 100 M1NS-Ia-1.1 | O5: P1/P2/A1/A2 | P5: PH_G1_C01_P1.1.3 | Q5: =E5 -> Ch 1 Practice 1.1.3: Recognizing conservation of numbers | R5: PH, PR1MEPH | S5: Practice | T5: MATHPRO | U5: Grade 1 | V5: Chapter 1 Numbers 0 to 10 | W5: 9789814969369 | X5: 5 | Y5: 1. Numbers and Number Sense | Z5: G1.1.01 Whole Numbers / Place Value | AA5: Counting and Comparing | AB5: =J5 -> 1.003 To recognise conservation of number M1NS-Ia-1.1 | AC5: =Y5 -> 1. Numbers and Number Sense | AD5: =Z5 -> G1.1.01 Whole Numbers / Place Value | AE5: =K5 -> M1NS-Ia-1.1 | AF5: =M5 -> M1NS-Ia-1.1: Visualizes and represents numbers from 0 - 100 using a variety of materials. | AG5: =N5 -> 1.001 Visualizes and represents numbers from 0 - 100 M1NS-Ia-1.1 | AH5: 1 | AI5: PH_G1_C01_P1.1.1 | AJ5: To count within 10 (including the use of zero to denote an empty set) | AP5: Published | AQ5: =IF($AP5="Raw Manuscript created","Editor to review",IF($AP5="Manuscript reviewed by Editor","Author to revise",IF($AP5="Manuscript revised by Author","Editor to review",IF($AP5="Manuscript finalised by Editor","Evonne to PFP",IF($AP5="Manuscript approved by Evonne","Evelyn to upload to Learnosity",IF($AP5="Manuscript uploaded to Learnosity","Prepress to create Activity",IF($AP5="Ready practice on Learnosity","Prepress to create Activity",IF($AP5="Activity created","Editor to conduct Learnosity review",IF($AP5="Published","Completed",""))))))))) -> Completed | AR5: remove row as objective is not in SOW
C6: 1.2 Comparing numbers of objects by matching | D6: PINE_G1_C01_P1.3.1 | E6: Ch 1 Practice 1.2.1: Comparing number of objects by matching | F6: To compare number of objects in two groups within 10 | G6: 4 | H6: 1 (Rev3) | J6: 1.004 To compare number of objects in two groups within 10 M1NS-Id-6 | K6: M1NS-Id-6 | L6: Visualizes, represents, and compares two sets using the expressions “less than,” “more than,” and “as many as” | M6: M1NS-Id-6: Visualizes, represents, and compares two sets using the expressions “less than”, “more than”, and “as many as”. | N6: 1.006 Visualizes, represents, and compares two sets M1NS-Id-6 | O6: P1/P2/A1/A2 | P6: PH_G1_C01_P1.2.1 | Q6: =E6 -> Ch 1 Practice 1.2.1: Comparing number of objects by matching | R6: PH, PR1MEPH | S6: Practice | T6: MATHPRO | U6: Grade 1 | V6: Chapter 1 Numbers 0 to 10 | W6: 9789814969369 | X6: 11 | Y6: 1. Numbers and Number Sense | Z6: G1.1.01 Whole Numbers / Place Value | AA6: Counting and Comparing | AB6: =J6 -> 1.004 To compare number of objects in two groups within 10 M1NS-Id-6 | AC6: =Y6 -> 1. Numbers and Number Sense | AD6: =Z6 -> G1.1.01 Whole Numbers / Place Value | AE6: =K6 -> M1NS-Id-6 | AF6: =M6 -> M1NS-Id-6: Visualizes, represents, and compares two sets using the expressions “less than”, “more than”, and “as many as”. | AG6: =N6 -> 1.006 Visualizes, represents, and compares two sets M1NS-Id-6 | AH6: 1 | AI6: PH_G1_C01_P1.1.1 | AJ6: To count within 10 (including the use of zero to denote an empty set) | AP6: Published | AQ6: =IF($AP6="Raw Manuscript created","Editor to review",IF($AP6="Manuscript reviewed by Editor","Author to revise",IF($AP6="Manuscript revised by Author","Editor to review",IF($AP6="Manuscript finalised by Editor","Evonne to PFP",IF($AP6="Manuscript approved by Evonne","Evelyn to upload to Learnosity",IF($AP6="Manuscript uploaded to Learnosity","Prepress to create Activity",IF($AP6="Ready practice on Learnosity","Prepress to create Activity",IF($AP6="Activity created","Editor to conduct Learnosity review",IF($AP6="Published","Completed",""))))))))) -> Completed
C7: 1.3 Comparing numbers | D7: PINE_G1_C01_P1.4.1 | E7: Ch 1 Practice 1.3.1: Comparing number of objects by counting | F7: To compare number of objects in two groups within 10 | G7: 5 | H7: 2 (Rev1) | J7: 1.005 To compare number of objects in two groups within 10 M1NS-Id-6 | K7: M1NS-Id-6 | L7: Visualizes, represents, and compares two sets using the expressions “less than,” “more than,” and “as many as” | M7: M1NS-Id-6: Visualizes, represents, and compares two sets using the expressions “less than”, “more than”, and “as many as”. | N7: 1.006 Visualizes, represents, and compares two sets M1NS-Id-6 | O7: P1/P2/A1/A2 | P7: PH_G1_C01_P1.3.1 | Q7: =E7 -> Ch 1 Practice 1.3.1: Comparing number of objects by counting | R7: PH, PR1MEPH | S7: Practice | T7: MATHPRO | U7: Grade 1 | V7: Chapter 1 Numbers 0 to 10 | W7: 9789814969369 | X7: 11 | Y7: 1. Numbers and Number Sense | Z7: G1.1.01 Whole Numbers / Place Value | AA7: Counting and Comparing | AB7: =J7 -> 1.005 To compare number of objects in two groups within 10 M1NS-Id-6 | AC7: =Y7 -> 1. Numbers and Number Sense | AD7: =Z7 -> G1.1.01 Whole Numbers / Place Value | AE7: =K7 -> M1NS-Id-6 | AF7: =M7 -> M1NS-Id-6: Visualizes, represents, and compares two sets using the expressions “less than”, “more than”, and “as many as”. | AG7: =N7 -> 1.006 Visualizes, represents, and compares two sets M1NS-Id-6 | AH7: 1 | AI7: PH_G1_C01_P1.1.1 | AJ7: To count within 10 (including the use of zero to denote an empty set) | AP7: Published | AQ7: =IF($AP7="Raw Manuscript created","Editor to review",IF($AP7="Manuscript reviewed by Editor","Author to revise",IF($AP7="Manuscript revised by Author","Editor to review",IF($AP7="Manuscript finalised by Editor","Evonne to PFP",IF($AP7="Manuscript approved by Evonne","Evelyn to upload to Learnosity",IF($AP7="Manuscript uploaded to Learnosity","Prepress to create Activity",IF($AP7="Ready practice on Learnosity","Prepress to create Activity",IF($AP7="Activity created","Editor to conduct Learnosity review",IF($AP7="Published","Completed",""))))))))) -> Completed
D8: PINE_G1_C01_P1.4.2 | E8: Ch 1 Practice 1.3.2: Comparing two numbers | F8: To compare two numbers within 10 | G8: 6 | J8: 1.006 To compare two numbers within 10 M1NS-Id-6 | K8: M1NS-Id-6 | L8: Visualizes, represents, and compares two sets using the expressions “less than,” “more than,” and “as many as” | M8: M1NS-Id-6: Visualizes, represents, and compares two sets using the expressions “less than”, “more than”, and “as many as”. | N8: 1.006 Visualizes, represents, and compares two sets M1NS-Id-6 | O8: P1/P2/A1/A2 | P8: PH_G1_C01_P1.3.2 | Q8: =E8 -> Ch 1 Practice 1.3.2: Comparing two numbers | R8: PH, PR1MEPH | S8: Practice | T8: MATHPRO | U8: Grade 1 | V8: Chapter 1 Numbers 0 to 10 | W8: 9789814969369 | X8: 11 | Y8: 1. Numbers and Number Sense | Z8: G1.1.01 Whole Numbers / Place Value | AA8: Counting and Comparing | AB8: =J8 -> 1.006 To compare two numbers within 10 M1NS-Id-6 | AC8: =Y8 -> 1. Numbers and Number Sense | AD8: =Z8 -> G1.1.01 Whole Numbers / Place Value | AE8: =K8 -> M1NS-Id-6 | AF8: =M8 -> M1NS-Id-6: Visualizes, represents, and compares two sets using the expressions “less than”, “more than”, and “as many as”. | AG8: =N8 -> 1.006 Visualizes, represents, and compares two sets M1NS-Id-6 | AH8: 1 | AI8: PH_G1_C01_P1.3.1 | AJ8: To compare number of objects in two groups within 10 | AP8: Published | AQ8: =IF($AP8="Raw Manuscript created","Editor to review",IF($AP8="Manuscript reviewed by Editor","Author to revise",IF($AP8="Manuscript revised by Author","Editor to review",IF($AP8="Manuscript finalised by Editor","Evonne to PFP",IF($AP8="Manuscript approved by Evonne","Evelyn to upload to Learnosity",IF($AP8="Manuscript uploaded to Learnosity","Prepress to create Activity",IF($AP8="Ready practice on Learnosity","Prepress to create Activity",IF($AP8="Activity created","Editor to conduct Learnosity review",IF($AP8="Published","Completed",""))))))))) -> Completed | AR8: remove row as objective is not in SOW
D9: PINE_G1_C01_P1.4.3 | E9: Ch 1 Practice 1.3.3: Using the = sign | F9: To use the = sign to represent equality | G9: 7 | I9: EOY_1 | J9: 1.007 To use the = sign to represent equality M1NS-Ih-12.1 | K9: M1NS-Ih-12.1 | L9: Visualizes, represents, and compares numbers up to 100 using relation symbols | M9: M1NS-Ih-12.1: Visualizes, represents, and compares numbers up to 100 using relation symbols. | N9: 1.012 Visualizes, represents, and compares numbers up to 100 M1NS-Ih-12.1 | O9: P1/P2/A1/A2 | P9: PH_G1_C01_P1.3.3 | Q9: =E9 -> Ch 1 Practice 1.3.3: Using the = sign | R9: PH, PR1MEPH | S9: Practice | T9: MATHPRO | U9: Grade 1 | V9: Chapter 1 Numbers 0 to 10 | W9: 9789814969369 | X9: 11 | Y9: 1. Numbers and Number Sense | Z9: G1.1.01 Whole Numbers / Place Value | AA9: Counting and Comparing | AB9: =J9 -> 1.007 To use the = sign to represent equality M1NS-Ih-12.1 | AC9: =Y9 -> 1. Numbers and Number Sense | AD9: =Z9 -> G1.1.01 Whole Numbers / Place Value | AE9: =K9 -> M1NS-Ih-12.1 | AF9: =M9 -> M1NS-Ih-12.1: Visualizes, represents, and compares numbers up to 100 using relation symbols. | AG9: =N9 -> 1.012 Visualizes, represents, and compares numbers up to 100 M1NS-Ih-12.1 | AH9: 1 | AI9: PH_G1_C01_P1.3.2 | AJ9: To compare two numbers within 10 | AP9: Published | AQ9: =IF($AP9="Raw Manuscript created","Editor to review",IF($AP9="Manuscript reviewed by Editor","Author to revise",IF($AP9="Manuscript revised by Author","Editor to review",IF($AP9="Manuscript finalised by Editor","Evonne to PFP",IF($AP9="Manuscript approved by Evonne","Evelyn to upload to Learnosity",IF($AP9="Manuscript uploaded to Learnosity","Prepress to create Activity",IF($AP9="Ready practice on Learnosity","Prepress to create Activity",IF($AP9="Activity created","Editor to conduct Learnosity review",IF($AP9="Published","Completed",""))))))))) -> Completed | AR9: remove row as objective is not in SOW
C10: 1.4 Counting on and backwards | D10: PINE_G1_C01_P1.2.1 | E10: Ch 1 Practice 1.4.1: Counting on and backwards | F10: To count on and backwards within 10 | G10: 8 | H10: 3 (Rev1) | J10: 1.008 To count on and backwards within 10 M1NS-Ib-2.1 | K10: M1NS-Ib-2.1 | L10: Counts the number of objects in a given set by ones and tens | M10: M1NS-Ib-2.1: Counts the number of objects in a given set by ones and tens. | N10: 1.002 Counts the number of objects in a given set by ones and tens M1NS-Ib-2.1 | O10: P1/P2/A1/A2 | P10: PH_G1_C01_P1.4.1 | Q10: =E10 -> Ch 1 Practice 1.4.1: Counting on and backwards | R10: PH, PR1MEPH | S10: Practice | T10: MATHPRO | U10: Grade 1 | V10: Chapter 1 Numbers 0 to 10 | W10: 9789814969369 | X10: 13 | Y10: 1. Numbers and Number Sense | Z10: G1.1.01 Whole Numbers / Place Value | AA10: Counting and Comparing | AB10: =J10 -> 1.008 To count on and backwards within 10 M1NS-Ib-2.1 | AC10: =Y10 -> 1. Numbers and Number Sense | AD10: =Z10 -> G1.1.01 Whole Numbers / Place Value | AE10: =K10 -> M1NS-Ib-2.1 | AF10: =M10 -> M1NS-Ib-2.1: Counts the number of objects in a given set by ones and tens. | AG10: =N10 -> 1.002 Counts the number of objects in a given set by ones and tens M1NS-Ib-2.1 | AH10: 1 | AI10: PH_G1_C01_P1.1.1 | AJ10: To count within 10 (including the use of zero to denote an empty set) | AP10: Published | AQ10: =IF($AP10="Raw Manuscript created","Editor to review",IF($AP10="Manuscript reviewed by Editor","Author to revise",IF($AP10="Manuscript revised by Author","Editor to review",IF($AP10="Manuscript finalised by Editor","Evonne to PFP",IF($AP10="Manuscript approved by Evonne","Evelyn to upload to Learnosity",IF($AP10="Manuscript uploaded to Learnosity","Prepress to create Activity",IF($AP10="Ready practice on Learnosity","Prepress to create Activity",IF($AP10="Activity created","Editor to conduct Learnosity review",IF($AP10="Published","Completed",""))))))))) -> Completed
D11: PINE_G1_C01_P1.5.1 | E11: Ch 1 Practice 1.4.2: Comparing and ordering numbers | F11: To compare and order numbers within 10 | G11: 9 | I11: B_06 | J11: 1.009 To compare and order numbers within 10 M1NS-Ie-7 | K11: M1NS-Ie-7 | L11: Visualizes, represents, and orders sets from least to greatest and vice versa | M11: M1NS-Ie-7: Visualizes, represents, and orders sets from least to greatest and vice versa. | N11: 1.007 Visualizes, represents, and orders sets from least to greatest and vice versa M1NS-Ie-7 | O11: P1/P2/A1/A2 | P11: PH_G1_C01_P1.4.2 | Q11: =E11 -> Ch 1 Practice 1.4.2: Comparing and ordering numbers | R11: PH, PR1MEPH | S11: Practice | T11: MATHPRO | U11: Grade 1 | V11: Chapter 1 Numbers 0 to 10 | W11: 9789814969369 | X11: 13 | Y11: 1. Numbers and Number Sense | Z11: G1.1.01 Whole Numbers / Place Value | AA11: Counting and Comparing | AB11: =J11 -> 1.009 To compare and order numbers within 10 M1NS-Ie-7 | AC11: =Y11 -> 1. Numbers and Number Sense | AD11: =Z11 -> G1.1.01 Whole Numbers / Place Value | AE11: =K11 -> M1NS-Ie-7 | AF11: =M11 -> M1NS-Ie-7: Visualizes, represents, and orders sets from least to greatest and vice versa. | AG11: =N11 -> 1.007 Visualizes, represents, and orders sets from least to greatest and vice versa M1NS-Ie-7 | AH11: 1 | AI11: PH_G1_C01_P1.4.1 | AJ11: To count on and backwards within 10 | AP11: Published | AQ11: =IF($AP11="Raw Manuscript created","Editor to review",IF($AP11="Manuscript reviewed by Editor","Author to revise",IF($AP11="Manuscript revised by Author","Editor to review",IF($AP11="Manuscript finalised by Editor","Evonne to PFP",IF($AP11="Manuscript approved by Evonne","Evelyn to upload to Learnosity",IF($AP11="Manuscript uploaded to Learnosity","Prepress to create Activity",IF($AP11="Ready practice on Learnosity","Prepress to create Activity",IF($AP11="Activity created","Editor to conduct Learnosity review",IF($AP11="Published","Completed",""))))))))) -> Completed | AR11: remove row as objective is not in SOW
A12: Chapter 2: Number Bonds | B12: Unit 1: Telling Number Stories | C12: 1.1 Making 5 | D12: PINE_G1_C02_P1.1.1 | E12: Ch 2 Practice 1.1.1: Making a number story for 5 | F12: To make a number story to illustrate a number bond for 5 | G12: 1 | J12: 1.010 To make a number story to illustrate a number bond for 5 M1AL-IIIi-9 | K12: M1AL-IIIi-9 | L12: Identifies and creates patterns to compose and decompose using addition eg 7 = 0 + 7, 1 + 6, 2 + 5, 3 + 4, 4 + 3, 5 + 2, 6 + 1, 7 + 0 | M12: M1AL-IIIi-9: Identifies and creates patterns to compose and decompose using addition. | N12: 1.051 Identifies and creates patterns to compose and decompose M1AL-IIIi-9 | O12: P1/P2/A1/A2 | P12: PH_G1_C02_P1.1.1 | Q12: =E12 -> Ch 2 Practice 1.1.1: Making a number story for 5 | R12: PH, PR1MEPH | S12: Practice | T12: MATHPRO | U12: Grade 1 | V12: Chapter 2 Number Bonds | W12: 9789814969369 | X12: 16 | Y12: 1. Numbers and Number Sense | Z12: G1.1.01 Whole Numbers / Place Value | AA12: Telling number stories | AB12: =J12 -> 1.010 To make a number story to illustrate a number bond for 5 M1AL-IIIi-9 | AC12: =Y12 -> 1. Numbers and Number Sense | AD12: =Z12 -> G1.1.01 Whole Numbers / Place Value | AE12: =K12 -> M1AL-IIIi-9 | AF12: =M12 -> M1AL-IIIi-9: Identifies and creates patterns to compose and decompose using addition. | AG12: =N12 -> 1.051 Identifies and creates patterns to compose and decompose M1AL-IIIi-9 | AH12: 2 | AI12: PH_G1_C01_P1.1.1 | AJ12: To count within 10 (including the use of zero to denote an empty set) | AP12: Published | AQ12: =IF($AP12="Raw Manuscript created","Editor to review",IF($AP12="Manuscript reviewed by Editor","Author to revise",IF($AP12="Manuscript revised by Author","Editor to review",IF($AP12="Manuscript finalised by Editor","Evonne to PFP",IF($AP12="Manuscript approved by Evonne","Evelyn to upload to Learnosity",IF($AP12="Manuscript uploaded to Learnosity","Prepress to create Activity",IF($AP12="Ready practice on Learnosity","Prepress to create Activity",IF($AP12="Activity created","Editor to conduct Learnosity review",IF($AP12="Published","Completed",""))))))))) -> Completed
D13: PINE_G1_C02_P1.1.2 | E13: Ch 2 Practice 1.1.2: Making 5 | F13: To break a set of 5 objects into two parts in different ways | G13: 2 | J13: 1.011 To break a set of 5 objects into two parts in different ways M1NS-Ic-4 | K13: M1NS-Ic-4 | L13: Composes and decomposes a given number eg 5 is 5 and 0, 4 and 1, 3 and 2, 2 and 3, 1 and 4, 0 and 5 | M13: M1NS-Ic-4: Composes and decomposes a given number. | N13: 1.004 Composes and decomposes a given number M1NS-Ic-4 | O13: P1/P2/A1/A2 | P13: PH_G1_C02_P1.1.2 | Q13: =E13 -> Ch 2 Practice 1.1.2: Making 5 | R13: PH, PR1MEPH | S13: Practice | T13: MATHPRO | U13: Grade 1 | V13: Chapter 2 Number Bonds | W13: 9789814969369 | X13: 16 | Y13: 1. Numbers and Number Sense | Z13: G1.1.01 Whole Numbers / Place Value | AA13: Telling number stories | AB13: =J13 -> 1.011 To break a set of 5 objects into two parts in different ways M1NS-Ic-4 | AC13: =Y13 -> 1. Numbers and Number Sense | AD13: =Z13 -> G1.1.01 Whole Numbers / Place Value | AE13: =K13 -> M1NS-Ic-4 | AF13: =M13 -> M1NS-Ic-4: Composes and decomposes a given number. | AG13: =N13 -> 1.004 Composes and decomposes a given number M1NS-Ic-4 | AH13: 2 | AI13: PH_G1_C02_P1.1.1 | AJ13: To make a number story to illustrate a number bond for 5 | AP13: Published | AQ13: =IF($AP13="Raw Manuscript created","Editor to review",IF($AP13="Manuscript reviewed by Editor","Author to revise",IF($AP13="Manuscript revised by Author","Editor to review",IF($AP13="Manuscript finalised by Editor","Evonne to PFP",IF($AP13="Manuscript approved by Evonne","Evelyn to upload to Learnosity",IF($AP13="Manuscript uploaded to Learnosity","Prepress to create Activity",IF($AP13="Ready practice on Learnosity","Prepress to create Activity",IF($AP13="Activity created","Editor to conduct Learnosity review",IF($AP13="Published","Completed",""))))))))) -> Completed
D14: PINE_G1_C02_P1.1.3 | E14: Ch 2 Practice 1.1.3: Writing number bonds for 5 | F14: To write a number bond for 5 | G14: 3 | H14: 4 (Rev1) | J14: 1.012 To write a number bond for 5 M1NS-Ic-4 | K14: M1NS-Ic-4 | L14: Composes and decomposes a given number eg 5 is 5 and 0, 4 and 1, 3 and 2, 2 and 3, 1 and 4, 0 and 5 | M14: M1NS-Ic-4: Composes and decomposes a given number. | N14: 1.004 Composes and decomposes a given number M1NS-Ic-4 | O14: P1/P2/A1/A2 | P14: PH_G1_C02_P1.1.3 | Q14: =E14 -> Ch 2 Practice 1.1.3: Writing number bonds for 5 | R14: PH, PR1MEPH | S14: Practice | T14: MATHPRO | U14: Grade 1 | V14: Chapter 2 Number Bonds | W14: 9789814969369 | X14: 16 | Y14: 1. Numbers and Number Sense | Z14: G1.1.01 Whole Numbers / Place Value | AA14: Telling number stories | AB14: =J14 -> 1.012 To write a number bond for 5 M1NS-Ic-4 | AC14: =Y14 -> 1. Numbers and Number Sense | AD14: =Z14 -> G1.1.01 Whole Numbers / Place Value | AE14: =K14 -> M1NS-Ic-4 | AF14: =M14 -> M1NS-Ic-4: Composes and decomposes a given number. | AG14: =N14 -> 1.004 Composes and decomposes a given number M1NS-Ic-4 | AH14: 2 | AI14: PH_G1_C02_P1.1.2 | AJ14: To break a set of 5 objects into two parts in different ways | AP14: Published | AQ14: =IF($AP14="Raw Manuscript created","Editor to review",IF($AP14="Manuscript reviewed by Editor","Author to revise",IF($AP14="Manuscript revised by Author","Editor to review",IF($AP14="Manuscript finalised by Editor","Evonne to PFP",IF($AP14="Manuscript approved by Evonne","Evelyn to upload to Learnosity",IF($AP14="Manuscript uploaded to Learnosity","Prepress to create Activity",IF($AP14="Ready practice on Learnosity","Prepress to create Activity",IF($AP14="Activity created","Editor to conduct Learnosity review",IF($AP14="Published","Completed",""))))))))) -> Completed
C15: 1.2 Making 6 | D15: PINE_G1_C02_P1.2.1 | E15: Ch 2 Practice 1.2.1: Making a number story for 6 | F15: To make a number story to illustrate a number bond for 6 | G15: 4 | J15: 1.013 To make a number story to illustrate a number bond for 6 M1AL-IIIi-9 | K15: M1AL-IIIi-9 | L15: Identifies and creates patterns to compose and decompose using addition eg 7 = 0 + 7, 1 + 6, 2 + 5, 3 + 4, 4 + 3, 5 + 2, 6 + 1, 7 + 0 | M15: M1AL-IIIi-9: Identifies and creates patterns to compose and decompose using addition. | N15: 1.051 Identifies and creates patterns to compose and decompose M1AL-IIIi-9 | O15: P1/P2/A1/A2 | P15: PH_G1_C02_P1.2.1 | Q15: =E15 -> Ch 2 Practice 1.2.1: Making a number story for 6 | R15: PH, PR1MEPH | S15: Practice | T15: MATHPRO | U15: Grade 1 | V15: Chapter 2 Number Bonds | W15: 9789814969369 | X15: 16 | Y15: 1. Numbers and Number Sense | Z15: G1.1.01 Whole Numbers / Place Value | AA15: Telling number stories | AB15: =J15 -> 1.013 To make a number story to illustrate a number bond for 6 M1AL-IIIi-9 | AC15: =Y15 -> 1. Numbers and Number Sense | AD15: =Z15 -> G1.1.01 Whole Numbers / Place Value | AE15: =K15 -> M1AL-IIIi-9 | AF15: =M15 -> M1AL-IIIi-9: Identifies and creates patterns to compose and decompose using addition. | AG15: =N15 -> 1.051 Identifies and creates patterns to compose and decompose M1AL-IIIi-9 | AH15: 2 | AI15: PH_G1_C01_P1.1.1 | AJ15: To count within 10 (including the use of zero to denote an empty set) | AP15: Published | AQ15: =IF($AP15="Raw Manuscript created","Editor to review",IF($AP15="Manuscript reviewed by Editor","Author to revise",IF($AP15="Manuscript revised by Author","Editor to review",IF($AP15="Manuscript finalised by Editor","Evonne to PFP",IF($AP15="Manuscript approved by Evonne","Evelyn to upload to Learnosity",IF($AP15="Manuscript uploaded to Learnosity","Prepress to create Activity",IF($AP15="Ready practice on Learnosity","Prepress to create Activity",IF($AP15="Activity created","Editor to conduct Learnosity review",IF($AP15="Published","Completed",""))))))))) -> Completed
D16: PINE_G1_C02_P1.2.2 | E16: Ch 2 Practice 1.2.2: Making 6 | F16: To break a set of 6 objects into two parts in different ways | G16: 5 | J16: 1.014 To break a set of 6 objects into two parts in different ways M1NS-Ic-4 | K16: M1NS-Ic-4 | L16: Composes and decomposes a given number eg 5 is 5 and 0, 4 and 1, 3 and 2, 2 and 3, 1 and 4, 0 and 5 | M16: M1NS-Ic-4: Composes and decomposes a given number. | N16: 1.004 Composes and decomposes a given number M1NS-Ic-4 | O16: P1/P2/A1/A2 | P16: PH_G1_C02_P1.2.2 | Q16: =E16 -> Ch 2 Practice 1.2.2: Making 6 | R16: PH, PR1MEPH | S16: Practice | T16: MATHPRO | U16: Grade 1 | V16: Chapter 2 Number Bonds | W16: 9789814969369 | X16: 16 | Y16: 1. Numbers and Number Sense | Z16: G1.1.01 Whole Numbers / Place Value | AA16: Telling number stories | AB16: =J16 -> 1.014 To break a set of 6 objects into two parts in different ways M1NS-Ic-4 | AC16: =Y16 -> 1. Numbers and Number Sense | AD16: =Z16 -> G1.1.01 Whole Numbers / Place Value | AE16: =K16 -> M1NS-Ic-4 | AF16: =M16 -> M1NS-Ic-4: Composes and decomposes a given number. | AG16: =N16 -> 1.004 Composes and decomposes a given number M1NS-Ic-4 | AH16: 2 | AI16: PH_G1_C02_P1.2.1 | AJ16: To make a number story to illustrate a number bond for 6 | AP16: Published | AQ16: =IF($AP16="Raw Manuscript created","Editor to review",IF($AP16="Manuscript reviewed by Editor","Author to revise",IF($AP16="Manuscript revised by Author","Editor to review",IF($AP16="Manuscript finalised by Editor","Evonne to PFP",IF($AP16="Manuscript approved by Evonne","Evelyn to upload to Learnosity",IF($AP16="Manuscript uploaded to Learnosity","Prepress to create Activity",IF($AP16="Ready practice on Learnosity","Prepress to create Activity",IF($AP16="Activity created","Editor to conduct Learnosity review",IF($AP16="Published","Completed",""))))))))) -> Completed
D17: PINE_G1_C02_P1.2.3 | E17: Ch 2 Practice 1.2.3: Writing number bonds for 6 | F17: To write a number bond for 6 | G17: Objective not tested in CA, to be tested in MYE or EOY | I17: EOY_2 | J17: 1.015 To write a number bond for 6 M1NS-Ic-4 | K17: M1NS-Ic-4 | L17: Composes and decomposes a given number eg 5 is 5 and 0, 4 and 1, 3 and 2, 2 and 3, 1 and 4, 0 and 5 | M17: M1NS-Ic-4: Composes and decomposes a given number. | N17: 1.004 Composes and decomposes a given number M1NS-Ic-4 | O17: P1/P2/A1/A2 | P17: PH_G1_C02_P1.2.3 | Q17: =E17 -> Ch 2 Practice 1.2.3: Writing number bonds for 6 | R17: PH, PR1MEPH | S17: Practice | T17: MATHPRO | U17: Grade 1 | V17: Chapter 2 Number Bonds | W17: 9789814969369 | X17: 16 | Y17: 1. Numbers and Number Sense | Z17: G1.1.01 Whole Numbers / Place Value | AA17: Telling number stories | AB17: =J17 -> 1.015 To write a number bond for 6 M1NS-Ic-4 | AC17: =Y17 -> 1. Numbers and Number Sense | AD17: =Z17 -> G1.1.01 Whole Numbers / Place Value | AE17: =K17 -> M1NS-Ic-4 | AF17: =M17 -> M1NS-Ic-4: Composes and decomposes a given number. | AG17: =N17 -> 1.004 Composes and decomposes a given number M1NS-Ic-4 | AH17: 2 | AI17: PH_G1_C02_P1.2.2 | AJ17: To break a set of 6 objects into two parts in different ways | AP17: Published | AQ17: =IF($AP17="Raw Manuscript created","Editor to review",IF($AP17="Manuscript reviewed by Editor","Author to revise",IF($AP17="Manuscript revised by Author","Editor to review",IF($AP17="Manuscript finalised by Editor","Evonne to PFP",IF($AP17="Manuscript approved by Evonne","Evelyn to upload to Learnosity",IF($AP17="Manuscript uploaded to Learnosity","Prepress to create Activity",IF($AP17="Ready practice on Learnosity","Prepress to create Activity",IF($AP17="Activity created","Editor to conduct Learnosity review",IF($AP17="Published","Completed",""))))))))) -> Completed
C18: 1.3 Making 7 | D18: PINE_G1_C02_P1.3.1 | E18: Ch 2 Practice 1.3.1: Making a number story for 7 | F18: To make a number story to illustrate a number bond for 7 | J18: 1.016 To make a number story to illustrate a number bond for 7 M1AL-IIIi-9 | K18: M1AL-IIIi-9 | L18: Identifies and creates patterns to compose and decompose using addition | M18: M1AL-IIIi-9: Identifies and creates patterns to compose and decompose using addition. | N18: 1.051 Identifies and creates patterns to compose and decompose M1AL-IIIi-9 | O18: P1/P2/A1/A2 | P18: PH_G1_C02_P1.3.1 | Q18: =E18 -> Ch 2 Practice 1.3.1: Making a number story for 7 | R18: PH, PR1MEPH | S18: Practice | T18: MATHPRO | U18: Grade 1 | V18: Chapter 2 Number Bonds | W18: 9789814969369 | X18: 18 | Y18: 1. Numbers and Number Sense | Z18: G1.1.01 Whole Numbers / Place Value | AA18: Telling number stories | AB18: =J18 -> 1.016 To make a number story to illustrate a number bond for 7 M1AL-IIIi-9 | AC18: =Y18 -> 1. Numbers and Number Sense | AD18: =Z18 -> G1.1.01 Whole Numbers / Place Value | AE18: =K18 -> M1AL-IIIi-9 | AF18: =M18 -> M1AL-IIIi-9: Identifies and creates patterns to compose and decompose using addition. | AG18: =N18 -> 1.051 Identifies and creates patterns to compose and decompose M1AL-IIIi-9 | AH18: 2 | AI18: PH_G1_C01_P1.1.1 | AJ18: To count within 10 (including the use of zero to denote an empty set) | AP18: Published | AQ18: =IF($AP18="Raw Manuscript created","Editor to review",IF($AP18="Manuscript reviewed by Editor","Author to revise",IF($AP18="Manuscript revised by Author","Editor to review",IF($AP18="Manuscript finalised by Editor","Evonne to PFP",IF($AP18="Manuscript approved by Evonne","Evelyn to upload to Learnosity",IF($AP18="Manuscript uploaded to Learnosity","Prepress to create Activity",IF($AP18="Ready practice on Learnosity","Prepress to create Activity",IF($AP18="Activity created","Editor to conduct Learnosity review",IF($AP18="Published","Completed",""))))))))) -> Completed
D19: PINE_G1_C02_P1.3.2 | E19: Ch 2 Practice 1.3.2: Making 7 | F19: To break a set of 7 objects into two parts in different ways | G19: 6 | J19: 1.017 To break a set of 7 objects into two parts in different ways M1NS-Ic-4 | K19: M1NS-Ic-4 | L19: Composes and decomposes a given number eg 5 is 5 and 0, 4 and 1, 3 and 2, 2 and 3, 1 and 4, 0 and 5 | M19: M1NS-Ic-4: Composes and decomposes a given number. | N19: 1.004 Composes and decomposes a given number M1NS-Ic-4 | O19: P1/P2/A1/A2 | P19: PH_G1_C02_P1.3.2 | Q19: =E19 -> Ch 2 Practice 1.3.2: Making 7 | R19: PH, PR1MEPH | S19: Practice | T19: MATHPRO | U19: Grade 1 | V19: Chapter 2 Number Bonds | W19: 9789814969369 | X19: 18 | Y19: 1. Numbers and Number Sense | Z19: G1.1.01 Whole Numbers / Place Value | AA19: Telling number stories | AB19: =J19 -> 1.017 To break a set of 7 objects into two parts in different ways M1NS-Ic-4 | AC19: =Y19 -> 1. Numbers and Number Sense | AD19: =Z19 -> G1.1.01 Whole Numbers / Place Value | AE19: =K19 -> M1NS-Ic-4 | AF19: =M19 -> M1NS-Ic-4: Composes and decomposes a given number. | AG19: =N19 -> 1.004 Composes and decomposes a given number M1NS-Ic-4 | AH19: 2 | AI19: PH_G1_C02_P1.3.1 | AJ19: To make a number story to illustrate a number bond for 7 | AP19: Published | AQ19: =IF($AP19="Raw Manuscript created","Editor to review",IF($AP19="Manuscript reviewed by Editor","Author to revise",IF($AP19="Manuscript revised by Author","Editor to review",IF($AP19="Manuscript finalised by Editor","Evonne to PFP",IF($AP19="Manuscript approved by Evonne","Evelyn to upload to Learnosity",IF($AP19="Manuscript uploaded to Learnosity","Prepress to create Activity",IF($AP19="Ready practice on Learnosity","Prepress to create Activity",IF($AP19="Activity created","Editor to conduct Learnosity review",IF($AP19="Published","Completed",""))))))))) -> Completed
D20: PINE_G1_C02_P1.3.3 | E20: Ch 2 Practice 1.3.3: Writing number bonds for 7 | F20: To write a number bond for 7 | G20: 7 | H20: 1 (Rev 4) | J20: 1.018 To write a number bond for 7 M1NS-Ic-4 | K20: M1NS-Ic-4 | L20: Composes and decomposes a given number eg 5 is 5 and 0, 4 and 1, 3 and 2, 2 and 3, 1 and 4, 0 and 5 | M20: M1NS-Ic-4: Composes and decomposes a given number. | N20: 1.004 Composes and decomposes a given number M1NS-Ic-4 | O20: P1/P2/A1/A2 | P20: PH_G1_C02_P1.3.3 | Q20: =E20 -> Ch 2 Practice 1.3.3: Writing number bonds for 7 | R20: PH, PR1MEPH | S20: Practice | T20: MATHPRO | U20: Grade 1 | V20: Chapter 2 Number Bonds | W20: 9789814969369 | X20: 18 | Y20: 1. Numbers and Number Sense | Z20: G1.1.01 Whole Numbers / Place Value | AA20: Telling number stories | AB20: =J20 -> 1.018 To write a number bond for 7 M1NS-Ic-4 | AC20: =Y20 -> 1. Numbers and Number Sense | AD20: =Z20 -> G1.1.01 Whole Numbers / Place Value | AE20: =K20 -> M1NS-Ic-4 | AF20: =M20 -> M1NS-Ic-4: Composes and decomposes a given number. | AG20: =N20 -> 1.004 Composes and decomposes a given number M1NS-Ic-4 | AH20: 2 | AI20: PH_G1_C02_P1.3.2 | AJ20: To break a set of 7 objects into two parts in different ways | AP20: Published | AQ20: =IF($AP20="Raw Manuscript created","Editor to review",IF($AP20="Manuscript reviewed by Editor","Author to revise",IF($AP20="Manuscript revised by Author","Editor to review",IF($AP20="Manuscript finalised by Editor","Evonne to PFP",IF($AP20="Manuscript approved by Evonne","Evelyn to upload to Learnosity",IF($AP20="Manuscript uploaded to Learnosity","Prepress to create Activity",IF($AP20="Ready practice on Learnosity","Prepress to create Activity",IF($AP20="Activity created","Editor to conduct Learnosity review",IF($AP20="Published","Completed",""))))))))) -> Completed
C21: 1.4 Making 8 | D21: PINE_G1_C02_P1.4.1 | E21: Ch 2 Practice 1.4.1: Making a number story for 8 | F21: To make a number story to illustrate a number bond for 8 | G21: 8 | H21: 5 (Rev1) | J21: 1.019 To make a number story to illustrate a number bond for 8 M1AL-IIIi-9 | K21: M1AL-IIIi-9 | L21: Identifies and creates patterns to compose and decompose using addition eg 7 = 0 + 7, 1 + 6, 2 + 5, 3 + 4, 4 + 3, 5 + 2, 6 + 1, 7 + 0 | M21: M1AL-IIIi-9: Identifies and creates patterns to compose and decompose using addition. | N21: 1.051 Identifies and creates patterns to compose and decompose M1AL-IIIi-9 | O21: P1/P2/A1/A2 | P21: PH_G1_C02_P1.4.1 | Q21: =E21 -> Ch 2 Practice 1.4.1: Making a number story for 8 | R21: PH, PR1MEPH | S21: Practice | T21: MATHPRO | U21: Grade 1 | V21: Chapter 2 Number Bonds | W21: 9789814969369 | X21: 19 | Y21: 1. Numbers and Number Sense | Z21: G1.1.01 Whole Numbers / Place Value | AA21: Telling number stories | AB21: =J21 -> 1.019 To make a number story to illustrate a number bond for 8 M1AL-IIIi-9 | AC21: =Y21 -> 1. Numbers and Number Sense | AD21: =Z21 -> G1.1.01 Whole Numbers / Place Value | AE21: =K21 -> M1AL-IIIi-9 | AF21: =M21 -> M1AL-IIIi-9: Identifies and creates patterns to compose and decompose using addition. | AG21: =N21 -> 1.051 Identifies and creates patterns to compose and decompose M1AL-IIIi-9 | AH21: 2 | AI21: PH_G1_C01_P1.1.1 | AJ21: To count within 10 (including the use of zero to denote an empty set) | AP21: Published | AQ21: =IF($AP21="Raw Manuscript created","Editor to review",IF($AP21="Manuscript reviewed by Editor","Author to revise",IF($AP21="Manuscript revised by Author","Editor to review",IF($AP21="Manuscript finalised by Editor","Evonne to PFP",IF($AP21="Manuscript approved by Evonne","Evelyn to upload to Learnosity",IF($AP21="Manuscript uploaded to Learnosity","Prepress to create Activity",IF($AP21="Ready practice on Learnosity","Prepress to create Activity",IF($AP21="Activity created","Editor to conduct Learnosity review",IF($AP21="Published","Completed",""))))))))) -> Completed
D22: PINE_G1_C02_P1.4.2 | E22: Ch 2 Practice 1.4.2: Making 8 | F22: To break a set of 8 objects into two parts in different ways | J22: 1.020 To break a set of 8 objects into two parts in different ways M1NS-Ic-4 | K22: M1NS-Ic-4 | L22: Composes and decomposes a given number eg 5 is 5 and 0, 4 and 1, 3 and 2, 2 and 3, 1 and 4, 0 and 5 | M22: M1NS-Ic-4: Composes and decomposes a given number. | N22: 1.004 Composes and decomposes a given number M1NS-Ic-4 | O22: P1/P2/A1/A2 | P22: PH_G1_C02_P1.4.2 | Q22: =E22 -> Ch 2 Practice 1.4.2: Making 8 | R22: PH, PR1MEPH | S22: Practice | T22: MATHPRO | U22: Grade 1 | V22: Chapter 2 Number Bonds | W22: 9789814969369 | X22: 19 | Y22: 1. Numbers and Number Sense | Z22: G1.1.01 Whole Numbers / Place Value | AA22: Telling number stories | AB22: =J22 -> 1.020 To break a set of 8 objects into two parts in different ways M1NS-Ic-4 | AC22: =Y22 -> 1. Numbers and Number Sense | AD22: =Z22 -> G1.1.01 Whole Numbers / Place Value | AE22: =K22 -> M1NS-Ic-4 | AF22: =M22 -> M1NS-Ic-4: Composes and decomposes a given number. | AG22: =N22 -> 1.004 Composes and decomposes a given number M1NS-Ic-4 | AH22: 2 | AI22: PH_G1_C02_P1.4.1 | AJ22: To make a number story to illustrate a number bond for 8 | AP22: Published | AQ22: =IF($AP22="Raw Manuscript created","Editor to review",IF($AP22="Manuscript reviewed by Editor","Author to revise",IF($AP22="Manuscript revised by Author","Editor to review",IF($AP22="Manuscript finalised by Editor","Evonne to PFP",IF($AP22="Manuscript approved by Evonne","Evelyn to upload to Learnosity",IF($AP22="Manuscript uploaded to Learnosity","Prepress to create Activity",IF($AP22="Ready practice on Learnosity","Prepress to create Activity",IF($AP22="Activity created","Editor to conduct Learnosity review",IF($AP22="Published","Completed",""))))))))) -> Completed
D23: PINE_G1_C02_P1.4.3 | E23: Ch 2 Practice 1.4.3: Writing number bonds for 8 | F23: To write a number bond for 8 | G23: 9 | J23: 1.021 To write a number bond for 8 M1NS-Ic-4 | K23: M1NS-Ic-4 | L23: Composes and decomposes a given number eg 5 is 5 and 0, 4 and 1, 3 and 2, 2 and 3, 1 and 4, 0 and 5 | M23: M1NS-Ic-4: Composes and decomposes a given number. | N23: 1.004 Composes and decomposes a given number M1NS-Ic-4 | O23: P1/P2/A1/A2 | P23: PH_G1_C02_P1.4.3 | Q23: =E23 -> Ch 2 Practice 1.4.3: Writing number bonds for 8 | R23: PH, PR1MEPH | S23: Practice | T23: MATHPRO | U23: Grade 1 | V23: Chapter 2 Number Bonds | W23: 9789814969369 | X23: 19 | Y23: 1. Numbers and Number Sense | Z23: G1.1.01 Whole Numbers / Place Value | AA23: Telling number stories | AB23: =J23 -> 1.021 To write a number bond for 8 M1NS-Ic-4 | AC23: =Y23 -> 1. Numbers and Number Sense | AD23: =Z23 -> G1.1.01 Whole Numbers / Place Value | AE23: =K23 -> M1NS-Ic-4 | AF23: =M23 -> M1NS-Ic-4: Composes and decomposes a given number. | AG23: =N23 -> 1.004 Composes and decomposes a given number M1NS-Ic-4 | AH23: 2 | AI23: PH_G1_C02_P1.4.2 | AJ23: To break a set of 8 objects into two parts in different ways | AP23: Published | AQ23: =IF($AP23="Raw Manuscript created","Editor to review",IF($AP23="Manuscript reviewed by Editor","Author to revise",IF($AP23="Manuscript revised by Author","Editor to review",IF($AP23="Manuscript finalised by Editor","Evonne to PFP",IF($AP23="Manuscript approved by Evonne","Evelyn to upload to Learnosity",IF($AP23="Manuscript uploaded to Learnosity","Prepress to create Activity",IF($AP23="Ready practice on Learnosity","Prepress to create Activity",IF($AP23="Activity created","Editor to conduct Learnosity review",IF($AP23="Published","Completed",""))))))))) -> Completed
C24: 1.5 Making 9 | D24: PINE_G1_C02_P1.5.1 | E24: Ch 2 Practice 1.5.1: Making a number story for 9 | F24: To make a number story to illustrate a number bond for 9 | G24: 10 | J24: 1.022 To make a number story to illustrate a number bond for 9 M1AL-IIIi-9 | K24: M1AL-IIIi-9 | L24: Identifies and creates patterns to compose and decompose using addition eg 7 = 0 + 7, 1 + 6, 2 + 5, 3 + 4, 4 + 3, 5 + 2, 6 + 1, 7 + 0 | M24: M1AL-IIIi-9: Identifies and creates patterns to compose and decompose using addition. | N24: 1.051 Identifies and creates patterns to compose and decompose M1AL-IIIi-9 | O24: P1/P2/A1/A2 | P24: PH_G1_C02_P1.5.1 | Q24: =E24 -> Ch 2 Practice 1.5.1: Making a number story for 9 | R24: PH, PR1MEPH | S24: Practice | T24: MATHPRO | U24: Grade 1 | V24: Chapter 2 Number Bonds | W24: 9789814969369 | X24: 21 | Y24: 1. Numbers and Number Sense | Z24: G1.1.01 Whole Numbers / Place Value | AA24: Telling number stories | AB24: =J24 -> 1.022 To make a number story to illustrate a number bond for 9 M1AL-IIIi-9 | AC24: =Y24 -> 1. Numbers and Number Sense | AD24: =Z24 -> G1.1.01 Whole Numbers / Place Value | AE24: =K24 -> M1AL-IIIi-9 | AF24: =M24 -> M1AL-IIIi-9: Identifies and creates patterns to compose and decompose using addition. | AG24: =N24 -> 1.051 Identifies and creates patterns to compose and decompose M1AL-IIIi-9 | AH24: 2 | AI24: PH_G1_C01_P1.1.1 | AJ24: To count within 10 (including the use of zero to denote an empty set) | AP24: Published | AQ24: =IF($AP24="Raw Manuscript created","Editor to review",IF($AP24="Manuscript reviewed by Editor","Author to revise",IF($AP24="Manuscript revised by Author","Editor to review",IF($AP24="Manuscript finalised by Editor","Evonne to PFP",IF($AP24="Manuscript approved by Evonne","Evelyn to upload to Learnosity",IF($AP24="Manuscript uploaded to Learnosity","Prepress to create Activity",IF($AP24="Ready practice on Learnosity","Prepress to create Activity",IF($AP24="Activity created","Editor to conduct Learnosity review",IF($AP24="Published","Completed",""))))))))) -> Completed
D25: PINE_G1_C02_P1.5.2 | E25: Ch 2 Practice 1.5.2: Making 9 | F25: To break a set of 9 objects into two parts in different ways | G25: 11 | H25: 6 (Rev1) | J25: 1.023 To break a set of 9 objects into two parts in different ways M1NS-Ic-4 | K25: M1NS-Ic-4 | L25: Composes and decomposes a given number eg 5 is 5 and 0, 4 and 1, 3 and 2, 2 and 3, 1 and 4, 0 and 5 | M25: M1NS-Ic-4: Composes and decomposes a given number. | N25: 1.004 Composes and decomposes a given number M1NS-Ic-4 | O25: P1/P2/A1/A2 | P25: PH_G1_C02_P1.5.2 | Q25: =E25 -> Ch 2 Practice 1.5.2: Making 9 | R25: PH, PR1MEPH | S25: Practice | T25: MATHPRO | U25: Grade 1 | V25: Chapter 2 Number Bonds | W25: 9789814969369 | X25: 21 | Y25: 1. Numbers and Number Sense | Z25: G1.1.01 Whole Numbers / Place Value | AA25: Telling number stories | AB25: =J25 -> 1.023 To break a set of 9 objects into two parts in different ways M1NS-Ic-4 | AC25: =Y25 -> 1. Numbers and Number Sense | AD25: =Z25 -> G1.1.01 Whole Numbers / Place Value | AE25: =K25 -> M1NS-Ic-4 | AF25: =M25 -> M1NS-Ic-4: Composes and decomposes a given number. | AG25: =N25 -> 1.004 Composes and decomposes a given number M1NS-Ic-4 | AH25: 2 | AI25: PH_G1_C02_P1.5.1 | AJ25: To make a number story to illustrate a number bond for 9 | AP25: Published | AQ25: =IF($AP25="Raw Manuscript created","Editor to review",IF($AP25="Manuscript reviewed by Editor","Author to revise",IF($AP25="Manuscript revised by Author","Editor to review",IF($AP25="Manuscript finalised by Editor","Evonne to PFP",IF($AP25="Manuscript approved by Evonne","Evelyn to upload to Learnosity",IF($AP25="Manuscript uploaded to Learnosity","Prepress to create Activity",IF($AP25="Ready practice on Learnosity","Prepress to create Activity",IF($AP25="Activity created","Editor to conduct Learnosity review",IF($AP25="Published","Completed",""))))))))) -> Completed
D26: PINE_G1_C02_P1.5.3 | E26: Ch 2 Practice 1.5.3: Writing number bonds for 9 | F26: To write a number bond for 9 | J26: 1.024 To write a number bond for 9 M1NS-Ic-4 | K26: M1NS-Ic-4 | L26: Composes and decomposes a given number eg 5 is 5 and 0, 4 and 1, 3 and 2, 2 and 3, 1 and 4, 0 and 5 | M26: M1NS-Ic-4: Composes and decomposes a given number. | N26: 1.004 Composes and decomposes a given number M1NS-Ic-4 | O26: P1/P2/A1/A2 | P26: PH_G1_C02_P1.5.3 | Q26: =E26 -> Ch 2 Practice 1.5.3: Writing number bonds for 9 | R26: PH, PR1MEPH | S26: Practice | T26: MATHPRO | U26: Grade 1 | V26: Chapter 2 Number Bonds | W26: 9789814969369 | X26: 21 | Y26: 1. Numbers and Number Sense | Z26: G1.1.01 Whole Numbers / Place Value | AA26: Telling number stories | AB26: =J26 -> 1.024 To write a number bond for 9 M1NS-Ic-4 | AC26: =Y26 -> 1. Numbers and Number Sense | AD26: =Z26 -> G1.1.01 Whole Numbers / Place Value | AE26: =K26 -> M1NS-Ic-4 | AF26: =M26 -> M1NS-Ic-4: Composes and decomposes a given number. | AG26: =N26 -> 1.004 Composes and decomposes a given number M1NS-Ic-4 | AH26: 2 | AI26: PH_G1_C02_P1.5.2 | AJ26: To break a set of 9 objects into two parts in different ways | AP26: Published | AQ26: =IF($AP26="Raw Manuscript created","Editor to review",IF($AP26="Manuscript reviewed by Editor","Author to revise",IF($AP26="Manuscript revised by Author","Editor to review",IF($AP26="Manuscript finalised by Editor","Evonne to PFP",IF($AP26="Manuscript approved by Evonne","Evelyn to upload to Learnosity",IF($AP26="Manuscript uploaded to Learnosity","Prepress to create Activity",IF($AP26="Ready practice on Learnosity","Prepress to create Activity",IF($AP26="Activity created","Editor to conduct Learnosity review",IF($AP26="Published","Completed",""))))))))) -> Completed
C27: 1.6 Making 10 | D27: PINE_G1_C02_P1.6.1 | E27: Ch 2 Practice 1.6.1: Making a number story for 10 | F27: To make a number story to illustrate a number bond for 10 | G27: 12 | J27: 1.025 To make a number story to illustrate a number bond for 10 M1AL-IIIi-9 | K27: M1AL-IIIi-9 | L27: Identifies and creates patterns to compose and decompose using addition eg 7 = 0 + 7, 1 + 6, 2 + 5, 3 + 4, 4 + 3, 5 + 2, 6 + 1, 7 + 0 | M27: M1AL-IIIi-9: Identifies and creates patterns to compose and decompose using addition. | N27: 1.051 Identifies and creates patterns to compose and decompose M1AL-IIIi-9 | O27: P1/P2/A1/A2 | P27: PH_G1_C02_P1.6.1 | Q27: =E27 -> Ch 2 Practice 1.6.1: Making a number story for 10 | R27: PH, PR1MEPH | S27: Practice | T27: MATHPRO | U27: Grade 1 | V27: Chapter 2 Number Bonds | W27: 9789814969369 | X27: 23 | Y27: 1. Numbers and Number Sense | Z27: G1.1.01 Whole Numbers / Place Value | AA27: Telling number stories | AB27: =J27 -> 1.025 To make a number story to illustrate a number bond for 10 M1AL-IIIi-9 | AC27: =Y27 -> 1. Numbers and Number Sense | AD27: =Z27 -> G1.1.01 Whole Numbers / Place Value | AE27: =K27 -> M1AL-IIIi-9 | AF27: =M27 -> M1AL-IIIi-9: Identifies and creates patterns to compose and decompose using addition. | AG27: =N27 -> 1.051 Identifies and creates patterns to compose and decompose M1AL-IIIi-9 | AH27: 2 | AI27: PH_G1_C01_P1.1.1 | AJ27: To count within 10 (including the use of zero to denote an empty set) | AP27: Published | AQ27: =IF($AP27="Raw Manuscript created","Editor to review",IF($AP27="Manuscript reviewed by Editor","Author to revise",IF($AP27="Manuscript revised by Author","Editor to review",IF($AP27="Manuscript finalised by Editor","Evonne to PFP",IF($AP27="Manuscript approved by Evonne","Evelyn to upload to Learnosity",IF($AP27="Manuscript uploaded to Learnosity","Prepress to create Activity",IF($AP27="Ready practice on Learnosity","Prepress to create Activity",IF($AP27="Activity created","Editor to conduct Learnosity review",IF($AP27="Published","Completed",""))))))))) -> Completed
D28: PINE_G1_C02_P1.6.2 | E28: Ch 2 Practice 1.6.2: Making 10 | F28: To break a set of 10 objects into two parts in different ways | G28: 13 | J28: 1.026 To break a set of 10 objects into two parts in different ways M1NS-Ic-4 | K28: M1NS-Ic-4 | L28: Composes and decomposes a given number eg 5 is 5 and 0, 4 and 1, 3 and 2, 2 and 3, 1 and 4, 0 and 5 | M28: M1NS-Ic-4: Composes and decomposes a given number. | N28: 1.004 Composes and decomposes a given number M1NS-Ic-4 | O28: P1/P2/A1/A2 | P28: PH_G1_C02_P1.6.2 | Q28: =E28 -> Ch 2 Practice 1.6.2: Making 10 | R28: PH, PR1MEPH | S28: Practice | T28: MATHPRO | U28: Grade 1 | V28: Chapter 2 Number Bonds | W28: 9789814969369 | X28: 23 | Y28: 1. Numbers and Number Sense | Z28: G1.1.01 Whole Numbers / Place Value | AA28: Telling number stories | AB28: =J28 -> 1.026 To break a set of 10 objects into two parts in different ways M1NS-Ic-4 | AC28: =Y28 -> 1. Numbers and Number Sense | AD28: =Z28 -> G1.1.01 Whole Numbers / Place Value | AE28: =K28 -> M1NS-Ic-4 | AF28: =M28 -> M1NS-Ic-4: Composes and decomposes a given number. | AG28: =N28 -> 1.004 Composes and decomposes a given number M1NS-Ic-4 | AH28: 2 | AI28: PH_G1_C02_P1.6.1 | AJ28: To make a number story to illustrate a number bond for 10 | AP28: Published | AQ28: =IF($AP28="Raw Manuscript created","Editor to review",IF($AP28="Manuscript reviewed by Editor","Author to revise",IF($AP28="Manuscript revised by Author","Editor to review",IF($AP28="Manuscript finalised by Editor","Evonne to PFP",IF($AP28="Manuscript approved by Evonne","Evelyn to upload to Learnosity",IF($AP28="Manuscript uploaded to Learnosity","Prepress to create Activity",IF($AP28="Ready practice on Learnosity","Prepress to create Activity",IF($AP28="Activity created","Editor to conduct Learnosity review",IF($AP28="Published","Completed",""))))))))) -> Completed
D29: PINE_G1_C02_P1.6.3 | E29: Ch 2 Practice 1.6.3: Writing number bonds for 10 | F29: To write a number bond for 10 | G29: 14 | J29: 1.027 To write a number bond for 10 M1NS-Ic-4 | K29: M1NS-Ic-4 | L29: Composes and decomposes a given number eg 5 is 5 and 0, 4 and 1, 3 and 2, 2 and 3, 1 and 4, 0 and 5 | M29: M1NS-Ic-4: Composes and decomposes a given number. | N29: 1.004 Composes and decomposes a given number M1NS-Ic-4 | O29: P1/P2/A1/A2 | P29: PH_G1_C02_P1.6.3 | Q29: =E29 -> Ch 2 Practice 1.6.3: Writing number bonds for 10 | R29: PH, PR1MEPH | S29: Practice | T29: MATHPRO | U29: Grade 1 | V29: Chapter 2 Number Bonds | W29: 9789814969369 | X29: 23 | Y29: 1. Numbers and Number Sense | Z29: G1.1.01 Whole Numbers / Place Value | AA29: Telling number stories | AB29: =J29 -> 1.027 To write a number bond for 10 M1NS-Ic-4 | AC29: =Y29 -> 1. Numbers and Number Sense | AD29: =Z29 -> G1.1.01 Whole Numbers / Place Value | AE29: =K29 -> M1NS-Ic-4 | AF29: =M29 -> M1NS-Ic-4: Composes and decomposes a given number. | AG29: =N29 -> 1.004 Composes and decomposes a given number M1NS-Ic-4 | AH29: 2 | AI29: PH_G1_C02_P1.6.2 | AJ29: To break a set of 10 objects into two parts in different ways | AP29: Published | AQ29: =IF($AP29="Raw Manuscript created","Editor to review",IF($AP29="Manuscript reviewed by Editor","Author to revise",IF($AP29="Manuscript revised by Author","Editor to review",IF($AP29="Manuscript finalised by Editor","Evonne to PFP",IF($AP29="Manuscript approved by Evonne","Evelyn to upload to Learnosity",IF($AP29="Manuscript uploaded to Learnosity","Prepress to create Activity",IF($AP29="Ready practice on Learnosity","Prepress to create Activity",IF($AP29="Activity created","Editor to conduct Learnosity review",IF($AP29="Published","Completed",""))))))))) -> Completed
C30: 1.7 Completing number bonds | D30: PINE_G1_C02_P1.7.1 | E30: Ch 2 Practice 1.7.1: Completing number bonds | F30: To name the missing part or whole in a number bond | G30: 15 | H30: 1 (Rev2) | I30: A_02 | J30: 1.028 To name the missing part or whole in a number bond M1NS-Ic-4 | K30: M1NS-Ic-4 | L30: Composes and decomposes a given number eg 5 is 5 and 0, 4 and 1, 3 and 2, 2 and 3, 1 and 4, 0 and 5 | M30: M1NS-Ic-4: Composes and decomposes a given number. | N30: 1.004 Composes and decomposes a given number M1NS-Ic-4 | O30: P1/P2/A1/A2 | P30: PH_G1_C02_P1.7.1 | Q30: =E30 -> Ch 2 Practice 1.7.1: Completing number bonds | R30: PH, PR1MEPH | S30: Practice | T30: MATHPRO | U30: Grade 1 | V30: Chapter 2 Number Bonds | W30: 9789814969369 | X30: 26 | Y30: 1. Numbers and Number Sense | Z30: G1.1.01 Whole Numbers / Place Value | AA30: Telling number stories | AB30: =J30 -> 1.028 To name the missing part or whole in a number bond M1NS-Ic-4 | AC30: =Y30 -> 1. Numbers and Number Sense | AD30: =Z30 -> G1.1.01 Whole Numbers / Place Value | AE30: =K30 -> M1NS-Ic-4 | AF30: =M30 -> M1NS-Ic-4: Composes and decomposes a given number. | AG30: =N30 -> 1.004 Composes and decomposes a given number M1NS-Ic-4 | AH30: 2 | AI30: PH_G1_C02_P1.6.3 | AJ30: To write a number bond for 10 | AP30: Published | AQ30: =IF($AP30="Raw Manuscript created","Editor to review",IF($AP30="Manuscript reviewed by Editor","Author to revise",IF($AP30="Manuscript revised by Author","Editor to review",IF($AP30="Manuscript finalised by Editor","Evonne to PFP",IF($AP30="Manuscript approved by Evonne","Evelyn to upload to Learnosity",IF($AP30="Manuscript uploaded to Learnosity","Prepress to create Activity",IF($AP30="Ready practice on Learnosity","Prepress to create Activity",IF($AP30="Activity created","Editor to conduct Learnosity review",IF($AP30="Published","Completed",""))))))))) -> Completed
A31: Chapter 3: Addition | B31: Unit 1: Making Addition Stories | C31: 1.1 Understanding the meaning of addition | D31: PINE_G1_C03_P1.1.1 | E31: Ch 3 Practice 1.1.1: Understanding the meaning of addition | F31: To use picture cutouts (or other manipulatives) to illustrate the meaning of addition | G31: 1 | H31: 2 (Rev 4) | J31: 1.029 To use picture cutouts to illustrate the meaning of addition M1NS-IIa-23 | K31: M1NS-IIa-23 | L31: Illustrates addition as “putting together or combining or joining sets” | M31: M1NS-IIa-23: Illustrates addition as “putting together or combining or joining sets”. | N31: 1.017 Illustrates addition as “putting together or combining or joining sets” M1NS-IIa-23 | O31: P1/P2/A1/A2 | P31: PH_G1_C03_P1.1.1 | Q31: =E31 -> Ch 3 Practice 1.1.1: Understanding the meaning of addition | R31: PH, PR1MEPH | S31: Practice | T31: MATHPRO | U31: Grade 1 | V31: Chapter 3 Addition | W31: 9789814969369 | X31: 30 | Y31: 1. Numbers and Number Sense | Z31: G1.1.02 Addition / Subtraction | AA31: Making Addition Stories | AB31: =J31 -> 1.029 To use picture cutouts to illustrate the meaning of addition M1NS-IIa-23 | AC31: =Y31 -> 1. Numbers and Number Sense | AD31: =Z31 -> G1.1.02 Addition / Subtraction | AE31: =K31 -> M1NS-IIa-23 | AF31: =M31 -> M1NS-IIa-23: Illustrates addition as “putting together or combining or joining sets”. | AG31: =N31 -> 1.017 Illustrates addition as “putting together or combining or joining sets” M1NS-IIa-23 | AH31: 3 | AI31: PH_G1_C01_P1.1.1 | AJ31: To count within 10 (including the use of zero to denote an empty set) | AP31: Published | AQ31: =IF($AP31="Raw Manuscript created","Editor to review",IF($AP31="Manuscript reviewed by Editor","Author to revise",IF($AP31="Manuscript revised by Author","Editor to review",IF($AP31="Manuscript finalised by Editor","Evonne to PFP",IF($AP31="Manuscript approved by Evonne","Evelyn to upload to Learnosity",IF($AP31="Manuscript uploaded to Learnosity","Prepress to create Activity",IF($AP31="Ready practice on Learnosity","Prepress to create Activity",IF($AP31="Activity created","Editor to conduct Learnosity review",IF($AP31="Published","Completed",""))))))))) -> Completed
D32: PINE_G1_C03_P1.1.2 | E32: Ch 3 Practice 1.1.2: Making an addition story | F32: To make a number story for a given addition sentence | G32: 2 | J32: 1.030 To make a number story for a given addition sentence M1NS-IIa-23 | K32: M1NS-IIa-23 | L32: Illustrates addition as “putting together or combining or joining sets” | M32: M1NS-IIa-23: Illustrates addition as “putting together or combining or joining sets”. | N32: 1.017 Illustrates addition as “putting together or combining or joining sets” M1NS-IIa-23 | O32: P1/P2/A1/A2 | P32: PH_G1_C03_P1.1.2 | Q32: =E32 -> Ch 3 Practice 1.1.2: Making an addition story | R32: PH, PR1MEPH | S32: Practice | T32: MATHPRO | U32: Grade 1 | V32: Chapter 3 Addition | W32: 9789814969369 | X32: 30 | Y32: 1. Numbers and Number Sense | Z32: G1.1.02 Addition / Subtraction | AA32: Making Addition Stories | AB32: =J32 -> 1.030 To make a number story for a given addition sentence M1NS-IIa-23 | AC32: =Y32 -> 1. Numbers and Number Sense | AD32: =Z32 -> G1.1.02 Addition / Subtraction | AE32: =K32 -> M1NS-IIa-23 | AF32: =M32 -> M1NS-IIa-23: Illustrates addition as “putting together or combining or joining sets”. | AG32: =N32 -> 1.017 Illustrates addition as “putting together or combining or joining sets” M1NS-IIa-23 | AH32: 3 | AI32: PH_G1_C03_P1.1.1 | AJ32: To use picture cutouts (or other manipulatives) to illustrate the meaning of addition | AP32: Published | AQ32: =IF($AP32="Raw Manuscript created","Editor to review",IF($AP32="Manuscript reviewed by Editor","Author to revise",IF($AP32="Manuscript revised by Author","Editor to review",IF($AP32="Manuscript finalised by Editor","Evonne to PFP",IF($AP32="Manuscript approved by Evonne","Evelyn to upload to Learnosity",IF($AP32="Manuscript uploaded to Learnosity","Prepress to create Activity",IF($AP32="Ready practice on Learnosity","Prepress to create Activity",IF($AP32="Activity created","Editor to conduct Learnosity review",IF($AP32="Published","Completed",""))))))))) -> Completed
D33: PINE_G1_C03_P1.1.3 | E33: Ch 3 Practice 1.1.3: Writing addition sentences | F33: To write a number sentence for a given situation involving addition | G33: 3 | I33: EOY_3 | J33: 1.031 To write a number sentence for a given situation involving addition M1NS-IIa-23 | K33: M1NS-IIa-23 | L33: Illustrates addition as “putting together or combining or joining sets” | M33: M1NS-IIa-23: Illustrates addition as “putting together or combining or joining sets”. | N33: 1.017 Illustrates addition as “putting together or combining or joining sets” M1NS-IIa-23 | O33: P1/P2/A1/A2 | P33: PH_G1_C03_P1.1.3 | Q33: =E33 -> Ch 3 Practice 1.1.3: Writing addition sentences | R33: PH, PR1MEPH | S33: Practice | T33: MATHPRO | U33: Grade 1 | V33: Chapter 3 Addition | W33: 9789814969369 | X33: 30 | Y33: 1. Numbers and Number Sense | Z33: G1.1.02 Addition / Subtraction | AA33: Making Addition Stories | AB33: =J33 -> 1.031 To write a number sentence for a given situation involving addition M1NS-IIa-23 | AC33: =Y33 -> 1. Numbers and Number Sense | AD33: =Z33 -> G1.1.02 Addition / Subtraction | AE33: =K33 -> M1NS-IIa-23 | AF33: =M33 -> M1NS-IIa-23: Illustrates addition as “putting together or combining or joining sets”. | AG33: =N33 -> 1.017 Illustrates addition as “putting together or combining or joining sets” M1NS-IIa-23 | AH33: 3 | AI33: PH_G1_C03_P1.1.2 | AJ33: To make a number story for a given addition sentence | AP33: Published | AQ33: =IF($AP33="Raw Manuscript created","Editor to review",IF($AP33="Manuscript reviewed by Editor","Author to revise",IF($AP33="Manuscript revised by Author","Editor to review",IF($AP33="Manuscript finalised by Editor","Evonne to PFP",IF($AP33="Manuscript approved by Evonne","Evelyn to upload to Learnosity",IF($AP33="Manuscript uploaded to Learnosity","Prepress to create Activity",IF($AP33="Ready practice on Learnosity","Prepress to create Activity",IF($AP33="Activity created","Editor to conduct Learnosity review",IF($AP33="Published","Completed",""))))))))) -> Completed
D34: PINE_G1_C03_P1.1.4 | E34: Ch 3 Practice 1.1.4: Adding 0 | F34: To observe the identity property of addition | G34: 4 | H34: 7 (Rev1) | J34: 1.032 To observe the identity property of addition M1NS-IIa-23 | K34: M1NS-IIa-23 | L34: Illustrates addition as “putting together or combining or joining sets” | M34: M1NS-IIa-23: Illustrates addition as “putting together or combining or joining sets”. | N34: 1.017 Illustrates addition as “putting together or combining or joining sets” M1NS-IIa-23 | O34: P1/P2/A1/A2 | P34: PH_G1_C03_P1.1.4 | Q34: =E34 -> Ch 3 Practice 1.1.4: Adding 0 | R34: PH, PR1MEPH | S34: Practice | T34: MATHPRO | U34: Grade 1 | V34: Chapter 3 Addition | W34: 9789814969369 | X34: 30 | Y34: 1. Numbers and Number Sense | Z34: G1.1.02 Addition / Subtraction | AA34: Making Addition Stories | AB34: =J34 -> 1.032 To observe the identity property of addition M1NS-IIa-23 | AC34: =Y34 -> 1. Numbers and Number Sense | AD34: =Z34 -> G1.1.02 Addition / Subtraction | AE34: =K34 -> M1NS-IIa-23 | AF34: =M34 -> M1NS-IIa-23: Illustrates addition as “putting together or combining or joining sets”. | AG34: =N34 -> 1.017 Illustrates addition as “putting together or combining or joining sets” M1NS-IIa-23 | AH34: 3 | AI34: PH_G1_C03_P1.1.3 | AJ34: To write a number sentence for a given situation involving addition | AP34: Published | AQ34: =IF($AP34="Raw Manuscript created","Editor to review",IF($AP34="Manuscript reviewed by Editor","Author to revise",IF($AP34="Manuscript revised by Author","Editor to review",IF($AP34="Manuscript finalised by Editor","Evonne to PFP",IF($AP34="Manuscript approved by Evonne","Evelyn to upload to Learnosity",IF($AP34="Manuscript uploaded to Learnosity","Prepress to create Activity",IF($AP34="Ready practice on Learnosity","Prepress to create Activity",IF($AP34="Activity created","Editor to conduct Learnosity review",IF($AP34="Published","Completed",""))))))))) -> Completed
B35: Unit 2: Addition With Number Bonds | C35: 2.1 Adding using number bonds | D35: PINE_G1_C03_P2.1.1 | E35: Ch 3 Practice 2.1.1: Writing addition sentences for number bonds | F35: To relate an addition fact within 10 to a number bond To write two addition facts for a given number bond | G35: 5 | J35: 1.033 To relate an addition fact within 10 to a number bond M1NS-IIa-26.1 | K35: M1NS-IIa-26.1 | L35: Visualizes and adds two one-digit numbers with sums up to 18 using the order and zero properties of addition | M35: M1NS-IIa-26.1: Visualizes and adds two one-digit numbers with sums up to 18 using the order and zero properties of addition. | N35: 1.018 Visualizes and adds two one-digit numbers with sums up to 18 M1NS-IIa-26.1 | O35: P1/P2/A1/A2 | P35: PH_G1_C03_P2.1.1 | Q35: =E35 -> Ch 3 Practice 2.1.1: Writing addition sentences for number bonds | R35: PH, PR1MEPH | S35: Practice | T35: MATHPRO | U35: Grade 1 | V35: Chapter 3 Addition | W35: 9789814969369 | X35: 36 | Y35: 1. Numbers and Number Sense | Z35: G1.1.02 Addition / Subtraction | AA35: Addition With Number Bonds | AB35: =J35 -> 1.033 To relate an addition fact within 10 to a number bond M1NS-IIa-26.1 | AC35: =Y35 -> 1. Numbers and Number Sense | AD35: =Z35 -> G1.1.02 Addition / Subtraction | AE35: =K35 -> M1NS-IIa-26.1 | AF35: =M35 -> M1NS-IIa-26.1: Visualizes and adds two one-digit numbers with sums up to 18 using the order and zero properties of addition. | AG35: =N35 -> 1.018 Visualizes and adds two one-digit numbers with sums up to 18 M1NS-IIa-26.1 | AH35: 3 | AI35: PH_G1_C02_P1.7.1 | AJ35: To name the missing part or whole in a number bond | AP35: Published | AQ35: =IF($AP35="Raw Manuscript created","Editor to review",IF($AP35="Manuscript reviewed by Editor","Author to revise",IF($AP35="Manuscript revised by Author","Editor to review",IF($AP35="Manuscript finalised by Editor","Evonne to PFP",IF($AP35="Manuscript approved by Evonne","Evelyn to upload to Learnosity",IF($AP35="Manuscript uploaded to Learnosity","Prepress to create Activity",IF($AP35="Ready practice on Learnosity","Prepress to create Activity",IF($AP35="Activity created","Editor to conduct Learnosity review",IF($AP35="Published","Completed",""))))))))) -> Completed
D36: PINE_G1_C03_P2.1.2 | E36: Ch 3 Practice 2.1.2: Adding using number bonds | F36: To work out an addition fact within 10 by recalling the related number bond | G36: 6 | H36: 8 (Rev1) | J36: 1.034 To work out an addition fact within 10 by recalling the related number bond M1NS-IIa-26.1 | K36: M1NS-IIa-26.1 | L36: Visualizes and adds two one-digit numbers with sums up to 18 using the order and zero properties of addition | M36: M1NS-IIa-26.1: Visualizes and adds two one-digit numbers with sums up to 18 using the order and zero properties of addition. | N36: 1.018 Visualizes and adds two one-digit numbers with sums up to 18 M1NS-IIa-26.1 | O36: P1/P2/A1/A2 | P36: PH_G1_C03_P2.1.2 | Q36: =E36 -> Ch 3 Practice 2.1.2: Adding using number bonds | R36: PH, PR1MEPH | S36: Practice | T36: MATHPRO | U36: Grade 1 | V36: Chapter 3 Addition | W36: 9789814969369 | X36: 36 | Y36: 1. Numbers and Number Sense | Z36: G1.1.02 Addition / Subtraction | AA36: Addition With Number Bonds | AB36: =J36 -> 1.034 To work out an addition fact within 10 by recalling the related number bond M1NS-IIa-26.1 | AC36: =Y36 -> 1. Numbers and Number Sense | AD36: =Z36 -> G1.1.02 Addition / Subtraction | AE36: =K36 -> M1NS-IIa-26.1 | AF36: =M36 -> M1NS-IIa-26.1: Visualizes and adds two one-digit numbers with sums up to 18 using the order and zero properties of addition. | AG36: =N36 -> 1.018 Visualizes and adds two one-digit numbers with sums up to 18 M1NS-IIa-26.1 | AH36: 3 | AI36: PH_G1_C03_P2.1.1 | AJ36: To relate an addition fact within 10 to a number bond | AP36: Published | AQ36: =IF($AP36="Raw Manuscript created","Editor to review",IF($AP36="Manuscript reviewed by Editor","Author to revise",IF($AP36="Manuscript revised by Author","Editor to review",IF($AP36="Manuscript finalised by Editor","Evonne to PFP",IF($AP36="Manuscript approved by Evonne","Evelyn to upload to Learnosity",IF($AP36="Manuscript uploaded to Learnosity","Prepress to create Activity",IF($AP36="Ready practice on Learnosity","Prepress to create Activity",IF($AP36="Activity created","Editor to conduct Learnosity review",IF($AP36="Published","Completed",""))))))))) -> Completed
D37: PINE_G1_C03_P2.1.3 | E37: Ch 3 Practice 2.1.3: Adding numbers in any order | F37: To observe the commutative property of addition using number bonds | G37: 7 | J37: 1.035 To observe the commutative property of addition using number bonds M1NS-IIa-23 | K37: M1NS-IIa-23 | L37: Illustrates addition as “putting together or combining or joining sets” | M37: M1NS-IIa-23: Illustrates addition as “putting together or combining or joining sets”. | N37: 1.017 Illustrates addition as “putting together or combining or joining sets” M1NS-IIa-23 | O37: P1/P2/A1/A2 | P37: PH_G1_C03_P2.1.3 | Q37: =E37 -> Ch 3 Practice 2.1.3: Adding numbers in any order | R37: PH, PR1MEPH | S37: Practice | T37: MATHPRO | U37: Grade 1 | V37: Chapter 3 Addition | W37: 9789814969369 | X37: 36 | Y37: 1. Numbers and Number Sense | Z37: G1.1.02 Addition / Subtraction | AA37: Addition With Number Bonds | AB37: =J37 -> 1.035 To observe the commutative property of addition using number bonds M1NS-IIa-23 | AC37: =Y37 -> 1. Numbers and Number Sense | AD37: =Z37 -> G1.1.02 Addition / Subtraction | AE37: =K37 -> M1NS-IIa-23 | AF37: =M37 -> M1NS-IIa-23: Illustrates addition as “putting together or combining or joining sets”. | AG37: =N37 -> 1.017 Illustrates addition as “putting together or combining or joining sets” M1NS-IIa-23 | AH37: 3 | AI37: PH_G1_C03_P2.1.2 | AJ37: To work out an addition fact within 10 by recalling the related number bond | AP37: Published | AQ37: =IF($AP37="Raw Manuscript created","Editor to review",IF($AP37="Manuscript reviewed by Editor","Author to revise",IF($AP37="Manuscript revised by Author","Editor to review",IF($AP37="Manuscript finalised by Editor","Evonne to PFP",IF($AP37="Manuscript approved by Evonne","Evelyn to upload to Learnosity",IF($AP37="Manuscript uploaded to Learnosity","Prepress to create Activity",IF($AP37="Ready practice on Learnosity","Prepress to create Activity",IF($AP37="Activity created","Editor to conduct Learnosity review",IF($AP37="Published","Completed",""))))))))) -> Completed
B38: Unit 3: Other Methods of Addition | C38: 3.1 Understanding ‘more’ | D38: PINE_G1_C03_P3.1.1 | E38: Ch 3 Practice 3.1.1: Understanding ‘more’ | F38: To relate ‘more’ to adding on To solve 1-step picture problems by addition | G38: 8 | I38: B_02 | J38: 1.036 To relate ‘more’ to adding on M1NS-Id-6 | K38: M1NS-Id-6 | L38: Visualizes, represents, and compares two sets using the expressions “less than,” “more than,” and “as many as” | M38: M1NS-Id-6: Visualizes, represents, and compares two sets using the expressions “less than”, “more than”, and “as many as”. | N38: 1.006 Visualizes, represents, and compares two sets M1NS-Id-6 | O38: P1/P2/A1/A2 | P38: PH_G1_C03_P3.1.1 | Q38: =E38 -> Ch 3 Practice 3.1.1: Understanding ‘more’ | R38: PH, PR1MEPH | S38: Practice | T38: MATHPRO | U38: Grade 1 | V38: Chapter 3 Addition | W38: 9789814969369 | X38: 38 | Y38: 1. Numbers and Number Sense | Z38: G1.1.02 Addition / Subtraction | AA38: Other Methods of Addition | AB38: =J38 -> 1.036 To relate ‘more’ to adding on M1NS-Id-6 | AC38: =Y38 -> 1. Numbers and Number Sense | AD38: =Z38 -> G1.1.02 Addition / Subtraction | AE38: =K38 -> M1NS-Id-6 | AF38: =M38 -> M1NS-Id-6: Visualizes, represents, and compares two sets using the expressions “less than”, “more than”, and “as many as”. | AG38: =N38 -> 1.006 Visualizes, represents, and compares two sets M1NS-Id-6 | AH38: 3 | AI38: PH_G1_C01_P1.4.1 | AJ38: To count on and backwards within 10 | AP38: Published | AQ38: =IF($AP38="Raw Manuscript created","Editor to review",IF($AP38="Manuscript reviewed by Editor","Author to revise",IF($AP38="Manuscript revised by Author","Editor to review",IF($AP38="Manuscript finalised by Editor","Evonne to PFP",IF($AP38="Manuscript approved by Evonne","Evelyn to upload to Learnosity",IF($AP38="Manuscript uploaded to Learnosity","Prepress to create Activity",IF($AP38="Ready practice on Learnosity","Prepress to create Activity",IF($AP38="Activity created","Editor to conduct Learnosity review",IF($AP38="Published","Completed",""))))))))) -> Completed
C39: 3.2 Adding by counting on | D39: PINE_G1_C03_P3.2.1 | E39: Ch 3 Practice 3.2.1: Adding by counting on | F39: To use the ‘counting on’ method to add two numbers within 10, one of which is 1, 2 or 3 | G39: 9 | H39: 9 (Rev1) | J39: 1.037 To use the ‘counting on’ method to add two numbers within 10, one of which is 1, 2 or 3 M1NS-IIa-26.1 | K39: M1NS-IIa-26.1 | L39: Visualizes and adds two one-digit numbers with sums up to 18 using the order and zero properties of addition | M39: M1NS-IIa-26.1: Visualizes and adds two one-digit numbers with sums up to 18 using the order and zero properties of addition. | N39: 1.018 Visualizes and adds two one-digit numbers with sums up to 18 M1NS-IIa-26.1 | O39: P1/P2/A1/A2 | P39: PH_G1_C03_P3.2.1 | Q39: =E39 -> Ch 3 Practice 3.2.1: Adding by counting on | R39: PH, PR1MEPH | S39: Practice | T39: MATHPRO | U39: Grade 1 | V39: Chapter 3 Addition | W39: 9789814969369 | X39: 40 | Y39: 1. Numbers and Number Sense | Z39: G1.1.02 Addition / Subtraction | AA39: Other Methods of Addition | AB39: =J39 -> 1.037 To use the ‘counting on’ method to add two numbers within 10, one of which is 1, 2 or 3 M1NS-IIa-26.1 | AC39: =Y39 -> 1. Numbers and Number Sense | AD39: =Z39 -> G1.1.02 Addition / Subtraction | AE39: =K39 -> M1NS-IIa-26.1 | AF39: =M39 -> M1NS-IIa-26.1: Visualizes and adds two one-digit numbers with sums up to 18 using the order and zero properties of addition. | AG39: =N39 -> 1.018 Visualizes and adds two one-digit numbers with sums up to 18 M1NS-IIa-26.1 | AH39: 3 | AI39: PH_G1_C03_P3.1.1 | AJ39: To relate ‘more’ to adding on | AP39: Published | AQ39: =IF($AP39="Raw Manuscript created","Editor to review",IF($AP39="Manuscript reviewed by Editor","Author to revise",IF($AP39="Manuscript revised by Author","Editor to review",IF($AP39="Manuscript finalised by Editor","Evonne to PFP",IF($AP39="Manuscript approved by Evonne","Evelyn to upload to Learnosity",IF($AP39="Manuscript uploaded to Learnosity","Prepress to create Activity",IF($AP39="Ready practice on Learnosity","Prepress to create Activity",IF($AP39="Activity created","Editor to conduct Learnosity review",IF($AP39="Published","Completed",""))))))))) -> Completed
C40: 3.3 Doubles facts to 10 | D40: PINE_G1_C03_P3.3.1 | E40: Ch 3 Practice 3.3.1: Identifying doubles facts to 10 | F40: To recall an addition fact within 10 | G40: 10 | J40: 1.038 To recall an addition fact within 10 M1NS-IIa-26.1 | K40: M1NS-IIa-26.1 | L40: Visualizes and adds two one-digit numbers with sums up to 18 using the order and zero properties of addition | M40: M1NS-IIa-26.1: Visualizes and adds two one-digit numbers with sums up to 18 using the order and zero properties of addition. | N40: 1.018 Visualizes and adds two one-digit numbers with sums up to 18 M1NS-IIa-26.1 | O40: P1/P2/A1/A2 | P40: PH_G1_C03_P3.3.1 | Q40: =E40 -> Ch 3 Practice 3.3.1: Identifying doubles facts to 10 | R40: PH, PR1MEPH | S40: Practice | T40: MATHPRO | U40: Grade 1 | V40: Chapter 3 Addition | W40: 9789814969369 | X40: 42 | Y40: 1. Numbers and Number Sense | Z40: G1.1.02 Addition / Subtraction | AA40: Other Methods of Addition | AB40: =J40 -> 1.038 To recall an addition fact within 10 M1NS-IIa-26.1 | AC40: =Y40 -> 1. Numbers and Number Sense | AD40: =Z40 -> G1.1.02 Addition / Subtraction | AE40: =K40 -> M1NS-IIa-26.1 | AF40: =M40 -> M1NS-IIa-26.1: Visualizes and adds two one-digit numbers with sums up to 18 using the order and zero properties of addition. | AG40: =N40 -> 1.018 Visualizes and adds two one-digit numbers with sums up to 18 M1NS-IIa-26.1 | AH40: 3 | AI40: PH_G1_C03_P2.1.1 | AJ40: To relate an addition fact within 10 to a number bond | AP40: Published | AQ40: =IF($AP40="Raw Manuscript created","Editor to review",IF($AP40="Manuscript reviewed by Editor","Author to revise",IF($AP40="Manuscript revised by Author","Editor to review",IF($AP40="Manuscript finalised by Editor","Evonne to PFP",IF($AP40="Manuscript approved by Evonne","Evelyn to upload to Learnosity",IF($AP40="Manuscript uploaded to Learnosity","Prepress to create Activity",IF($AP40="Ready practice on Learnosity","Prepress to create Activity",IF($AP40="Activity created","Editor to conduct Learnosity review",IF($AP40="Published","Completed",""))))))))) -> Completed
D41: PINE_G1_C03_P3.3.2 | E41: Ch 3 Practice 3.3.2: Adding a number to itself | F41: To add two numbers which are the same | G41: 11 | H41: 10 (Rev1) | J41: 1.039 To add two numbers which are the same M1NS-IIa-28.1a | K41: M1NS-IIa-28.1a | L41: Adds two one-digit numbers using appropriate mental techniques eg adding doubles and/or near-doubles | M41: M1NS-IIa-28.1a: Adds two one-digit numbers using appropriate mental techniques. | N41: 1.019 Adds two one-digit numbers M1NS-IIa-28.1a | O41: P1/P2/A1/A2 | P41: PH_G1_C03_P3.3.2 | Q41: =E41 -> Ch 3 Practice 3.3.2: Adding a number to itself | R41: PH, PR1MEPH | S41: Practice | T41: MATHPRO | U41: Grade 1 | V41: Chapter 3 Addition | W41: 9789814969369 | X41: 42 | Y41: 1. Numbers and Number Sense | Z41: G1.1.02 Addition / Subtraction | AA41: Other Methods of Addition | AB41: =J41 -> 1.039 To add two numbers which are the same M1NS-IIa-28.1a | AC41: =Y41 -> 1. Numbers and Number Sense | AD41: =Z41 -> G1.1.02 Addition / Subtraction | AE41: =K41 -> M1NS-IIa-28.1a | AF41: =M41 -> M1NS-IIa-28.1a: Adds two one-digit numbers using appropriate mental techniques. | AG41: =N41 -> 1.019 Adds two one-digit numbers M1NS-IIa-28.1a | AH41: 3 | AI41: PH_G1_C03_P3.3.1 | AJ41: To recall an addition fact within 10 | AP41: Published | AQ41: =IF($AP41="Raw Manuscript created","Editor to review",IF($AP41="Manuscript reviewed by Editor","Author to revise",IF($AP41="Manuscript revised by Author","Editor to review",IF($AP41="Manuscript finalised by Editor","Evonne to PFP",IF($AP41="Manuscript approved by Evonne","Evelyn to upload to Learnosity",IF($AP41="Manuscript uploaded to Learnosity","Prepress to create Activity",IF($AP41="Ready practice on Learnosity","Prepress to create Activity",IF($AP41="Activity created","Editor to conduct Learnosity review",IF($AP41="Published","Completed",""))))))))) -> Completed
C42: 3.4 Making 10 | D42: PINE_G1_C03_P3.4.1 | E42: Ch 3 Practice 3.4.1: Making 10 | F42: To make 10 | G42: 12 | H42: 11 (Rev1) | I42: A_03 | J42: 1.040 To make 10 M1NS-IIa-26.1 | K42: M1NS-IIa-26.1 | L42: Visualizes and adds two one-digit numbers with sums up to 18 using the order and zero properties of addition | M42: M1NS-IIa-26.1: Visualizes and adds two one-digit numbers with sums up to 18 using the order and zero properties of addition. | N42: 1.018 Visualizes and adds two one-digit numbers with sums up to 18 M1NS-IIa-26.1 | O42: P1/P2/A1/A2 | P42: PH_G1_C03_P3.4.1 | Q42: =E42 -> Ch 3 Practice 3.4.1: Making 10 | R42: PH, PR1MEPH | S42: Practice | T42: MATHPRO | U42: Grade 1 | V42: Chapter 3 Addition | W42: 9789814969369 | X42: 43 | Y42: 1. Numbers and Number Sense | Z42: G1.1.02 Addition / Subtraction | AA42: Other Methods of Addition | AB42: =J42 -> 1.040 To make 10 M1NS-IIa-26.1 | AC42: =Y42 -> 1. Numbers and Number Sense | AD42: =Z42 -> G1.1.02 Addition / Subtraction | AE42: =K42 -> M1NS-IIa-26.1 | AF42: =M42 -> M1NS-IIa-26.1: Visualizes and adds two one-digit numbers with sums up to 18 using the order and zero properties of addition. | AG42: =N42 -> 1.018 Visualizes and adds two one-digit numbers with sums up to 18 M1NS-IIa-26.1 | AH42: 3 | AI42: PH_G1_C02_P1.6.3 | AJ42: To write a number bond for 10 | AP42: Published | AQ42: =IF($AP42="Raw Manuscript created","Editor to review",IF($AP42="Manuscript reviewed by Editor","Author to revise",IF($AP42="Manuscript revised by Author","Editor to review",IF($AP42="Manuscript finalised by Editor","Evonne to PFP",IF($AP42="Manuscript approved by Evonne","Evelyn to upload to Learnosity",IF($AP42="Manuscript uploaded to Learnosity","Prepress to create Activity",IF($AP42="Ready practice on Learnosity","Prepress to create Activity",IF($AP42="Activity created","Editor to conduct Learnosity review",IF($AP42="Published","Completed",""))))))))) -> Completed
A43: Chapter 4: Subtraction | B43: Unit 1: Making Subtraction Stories | C43: 1.1 Understanding the meaning of subtraction | D43: PINE_G1_C04_P1.1.1 | E43: Ch 4 Practice 1.1.1: Understanding the meaning of subtraction | F43: To use picture cutouts (or other manipulatives) to illustrate the meaning of subtraction | G43: 1 | J43: 1.041 To use picture cutouts to illustrate the meaning of subtraction M1NS-IIf-24 | K43: M1NS-IIf-24 | L43: Illustrates subtraction as “taking away” or “comparing” elements of sets | M43: M1NS-IIf-24: Illustrates subtraction as “taking away” or “comparing” elements of sets. | N43: 1.028 Illustrates subtraction as “taking away” or “comparing” elements of sets M1NS-IIf-24 | O43: P1/P2/A1/A2 | P43: PH_G1_C04_P1.1.1 | Q43: =E43 -> Ch 4 Practice 1.1.1: Understanding the meaning of subtraction | R43: PH, PR1MEPH | S43: Practice | T43: MATHPRO | U43: Grade 1 | V43: Chapter 4 Subtraction | W43: 9789814969369 | X43: 49 | Y43: 1. Numbers and Number Sense | Z43: G1.1.02 Addition / Subtraction | AA43: Making Subtraction Stories | AB43: =J43 -> 1.041 To use picture cutouts to illustrate the meaning of subtraction M1NS-IIf-24 | AC43: =Y43 -> 1. Numbers and Number Sense | AD43: =Z43 -> G1.1.02 Addition / Subtraction | AE43: =K43 -> M1NS-IIf-24 | AF43: =M43 -> M1NS-IIf-24: Illustrates subtraction as “taking away” or “comparing” elements of sets. | AG43: =N43 -> 1.028 Illustrates subtraction as “taking away” or “comparing” elements of sets M1NS-IIf-24 | AH43: 4 | AI43: PH_G1_C01_P1.1.1 | AJ43: To count within 10 (including the use of zero to denote an empty set) | AP43: Published | AQ43: =IF($AP43="Raw Manuscript created","Editor to review",IF($AP43="Manuscript reviewed by Editor","Author to revise",IF($AP43="Manuscript revised by Author","Editor to review",IF($AP43="Manuscript finalised by Editor","Evonne to PFP",IF($AP43="Manuscript approved by Evonne","Evelyn to upload to Learnosity",IF($AP43="Manuscript uploaded to Learnosity","Prepress to create Activity",IF($AP43="Ready practice on Learnosity","Prepress to create Activity",IF($AP43="Activity created","Editor to conduct Learnosity review",IF($AP43="Published","Completed",""))))))))) -> Completed
D44: PINE_G1_C04_P1.1.2 | E44: Ch 4 Practice 1.1.2: Making a subtraction story | F44: To make a number story for a given subtraction sentence | G44: 2 | H44: 3 (Rev 4) | J44: 1.042 To make a number story for a given subtraction sentence M1NS-IIf-24 | K44: M1NS-IIf-24 | L44: Illustrates subtraction as “taking away” or “comparing” elements of sets | M44: M1NS-IIf-24: Illustrates subtraction as “taking away” or “comparing” elements of sets. | N44: 1.028 Illustrates subtraction as “taking away” or “comparing” elements of sets M1NS-IIf-24 | O44: P1/P2/A1/A2 | P44: PH_G1_C04_P1.1.2 | Q44: =E44 -> Ch 4 Practice 1.1.2: Making a subtraction story | R44: PH, PR1MEPH | S44: Practice | T44: MATHPRO | U44: Grade 1 | V44: Chapter 4 Subtraction | W44: 9789814969369 | X44: 49 | Y44: 1. Numbers and Number Sense | Z44: G1.1.02 Addition / Subtraction | AA44: Making Subtraction Stories | AB44: =J44 -> 1.042 To make a number story for a given subtraction sentence M1NS-IIf-24 | AC44: =Y44 -> 1. Numbers and Number Sense | AD44: =Z44 -> G1.1.02 Addition / Subtraction | AE44: =K44 -> M1NS-IIf-24 | AF44: =M44 -> M1NS-IIf-24: Illustrates subtraction as “taking away” or “comparing” elements of sets. | AG44: =N44 -> 1.028 Illustrates subtraction as “taking away” or “comparing” elements of sets M1NS-IIf-24 | AH44: 4 | AI44: PH_G1_C04_P1.1.1 | AJ44: To use picture cutouts (or other manipulatives) to illustrate the meaning of subtraction | AP44: Published | AQ44: =IF($AP44="Raw Manuscript created","Editor to review",IF($AP44="Manuscript reviewed by Editor","Author to revise",IF($AP44="Manuscript revised by Author","Editor to review",IF($AP44="Manuscript finalised by Editor","Evonne to PFP",IF($AP44="Manuscript approved by Evonne","Evelyn to upload to Learnosity",IF($AP44="Manuscript uploaded to Learnosity","Prepress to create Activity",IF($AP44="Ready practice on Learnosity","Prepress to create Activity",IF($AP44="Activity created","Editor to conduct Learnosity review",IF($AP44="Published","Completed",""))))))))) -> Completed
D45: PINE_G1_C04_P1.1.3 | E45: Ch 4 Practice 1.1.3: Writing subtraction sentences | F45: To write a number sentence for a given situation involving subtraction | G45: 3 | H45: 12 (Rev1) | J45: 1.043 To write a number sentence for a given situation involving subtraction M1NS-IIf-24 | K45: M1NS-IIf-24 | L45: Illustrates subtraction as “taking away” or “comparing” elements of sets | M45: M1NS-IIf-24: Illustrates subtraction as “taking away” or “comparing” elements of sets. | N45: 1.028 Illustrates subtraction as “taking away” or “comparing” elements of sets M1NS-IIf-24 | O45: P1/P2/A1/A2 | P45: PH_G1_C04_P1.1.3 | Q45: =E45 -> Ch 4 Practice 1.1.3: Writing subtraction sentences | R45: PH, PR1MEPH | S45: Practice | T45: MATHPRO | U45: Grade 1 | V45: Chapter 4 Subtraction | W45: 9789814969369 | X45: 49 | Y45: 1. Numbers and Number Sense | Z45: G1.1.02 Addition / Subtraction | AA45: Making Subtraction Stories | AB45: =J45 -> 1.043 To write a number sentence for a given situation involving subtraction M1NS-IIf-24 | AC45: =Y45 -> 1. Numbers and Number Sense | AD45: =Z45 -> G1.1.02 Addition / Subtraction | AE45: =K45 -> M1NS-IIf-24 | AF45: =M45 -> M1NS-IIf-24: Illustrates subtraction as “taking away” or “comparing” elements of sets. | AG45: =N45 -> 1.028 Illustrates subtraction as “taking away” or “comparing” elements of sets M1NS-IIf-24 | AH45: 4 | AI45: PH_G1_C04_P1.1.2 | AJ45: To make a number story for a given subtraction sentence | AP45: Published | AQ45: =IF($AP45="Raw Manuscript created","Editor to review",IF($AP45="Manuscript reviewed by Editor","Author to revise",IF($AP45="Manuscript revised by Author","Editor to review",IF($AP45="Manuscript finalised by Editor","Evonne to PFP",IF($AP45="Manuscript approved by Evonne","Evelyn to upload to Learnosity",IF($AP45="Manuscript uploaded to Learnosity","Prepress to create Activity",IF($AP45="Ready practice on Learnosity","Prepress to create Activity",IF($AP45="Activity created","Editor to conduct Learnosity review",IF($AP45="Published","Completed",""))))))))) -> Completed
D46: PINE_G1_C04_P1.1.4 | E46: Ch 4 Practice 1.1.4: Subtracting 0 | F46: To observe the answer when 0 is subtracted from a number | G46: 4 | H46: 13 (Rev1) | J46: 1.044 To observe the answer when 0 is subtracted from a number M1NS-IIf-24 | K46: M1NS-IIf-24 | L46: Illustrates subtraction as “taking away” or “comparing” elements of sets | M46: M1NS-IIf-24: Illustrates subtraction as “taking away” or “comparing” elements of sets. | N46: 1.028 Illustrates subtraction as “taking away” or “comparing” elements of sets M1NS-IIf-24 | O46: P1/P2/A1/A2 | P46: PH_G1_C04_P1.1.4 | Q46: =E46 -> Ch 4 Practice 1.1.4: Subtracting 0 | R46: PH, PR1MEPH | S46: Practice | T46: MATHPRO | U46: Grade 1 | V46: Chapter 4 Subtraction | W46: 9789814969369 | X46: 49 | Y46: 1. Numbers and Number Sense | Z46: G1.1.02 Addition / Subtraction | AA46: Making Subtraction Stories | AB46: =J46 -> 1.044 To observe the answer when 0 is subtracted from a number M1NS-IIf-24 | AC46: =Y46 -> 1. Numbers and Number Sense | AD46: =Z46 -> G1.1.02 Addition / Subtraction | AE46: =K46 -> M1NS-IIf-24 | AF46: =M46 -> M1NS-IIf-24: Illustrates subtraction as “taking away” or “comparing” elements of sets. | AG46: =N46 -> 1.028 Illustrates subtraction as “taking away” or “comparing” elements of sets M1NS-IIf-24 | AH46: 4 | AI46: PH_G1_C04_P1.1.3 | AJ46: To write a number sentence for a given situation involving subtraction | AP46: Published | AQ46: =IF($AP46="Raw Manuscript created","Editor to review",IF($AP46="Manuscript reviewed by Editor","Author to revise",IF($AP46="Manuscript revised by Author","Editor to review",IF($AP46="Manuscript finalised by Editor","Evonne to PFP",IF($AP46="Manuscript approved by Evonne","Evelyn to upload to Learnosity",IF($AP46="Manuscript uploaded to Learnosity","Prepress to create Activity",IF($AP46="Ready practice on Learnosity","Prepress to create Activity",IF($AP46="Activity created","Editor to conduct Learnosity review",IF($AP46="Published","Completed",""))))))))) -> Completed
B47: Unit 2: Subtraction with Number Bonds | C47: 2.1 Subtracting using number bonds | D47: PINE_G1_C04_P2.1.1 | E47: Ch 4 Practice 2.1.1: Writing subtraction sentences for number bonds | F47: To relate a subtraction fact within 10 to a number bond To write two subtraction facts for a given number bond | G47: 5 | I47: B_07 | J47: 1.045 To relate a subtraction fact within 10 to a number bond M1NS-IIg-32.1 | K47: M1NS-IIg-32.1 | L47: Visualizes, represents, and subtracts one-digit numbers with minuends through 18 (basic facts) | M47: M1NS-IIg-32.1: Visualizes, represents, and subtracts one-digit numbers with minuends through 18 (basic facts). | N47: 1.030 Visualizes, represents, and subtracts one-digit numbers with minuends through 18 M1NS-IIg-32.1 | O47: P1/P2/A1/A2 | P47: PH_G1_C04_P2.1.1 | Q47: =E47 -> Ch 4 Practice 2.1.1: Writing subtraction sentences for number bonds | R47: PH, PR1MEPH | S47: Practice | T47: MATHPRO | U47: Grade 1 | V47: Chapter 4 Subtraction | W47: 9789814969369 | X47: 54 | Y47: 1. Numbers and Number Sense | Z47: G1.1.02 Addition / Subtraction | AA47: Subtraction with Number Bonds | AB47: =J47 -> 1.045 To relate a subtraction fact within 10 to a number bond M1NS-IIg-32.1 | AC47: =Y47 -> 1. Numbers and Number Sense | AD47: =Z47 -> G1.1.02 Addition / Subtraction | AE47: =K47 -> M1NS-IIg-32.1 | AF47: =M47 -> M1NS-IIg-32.1: Visualizes, represents, and subtracts one-digit numbers with minuends through 18 (basic facts). | AG47: =N47 -> 1.030 Visualizes, represents, and subtracts one-digit numbers with minuends through 18 M1NS-IIg-32.1 | AH47: 4 | AI47: PH_G1_C02_P1.7.1 | AJ47: To name the missing part or whole in a number bond | AP47: Published | AQ47: =IF($AP47="Raw Manuscript created","Editor to review",IF($AP47="Manuscript reviewed by Editor","Author to revise",IF($AP47="Manuscript revised by Author","Editor to review",IF($AP47="Manuscript finalised by Editor","Evonne to PFP",IF($AP47="Manuscript approved by Evonne","Evelyn to upload to Learnosity",IF($AP47="Manuscript uploaded to Learnosity","Prepress to create Activity",IF($AP47="Ready practice on Learnosity","Prepress to create Activity",IF($AP47="Activity created","Editor to conduct Learnosity review",IF($AP47="Published","Completed",""))))))))) -> Completed
D48: PINE_G1_C04_P2.1.2 | E48: Ch 4 Practice 2.1.2: Subtracting using number bonds | F48: To work out a subtraction fact within 10 by recalling the related number bond | G48: 6 | H48: 14 (Rev1) | J48: 1.046 To work out a subtraction fact within 10 M1NS-IIi-33.1 | K48: M1NS-IIi-33.1 | L48: Subtracts mentally one-digit numbers from two-digit minuends without regrouping using appropriate strategies | M48: M1NS-IIi-33.1: Subtracts mentally one-digit numbers from two-digit minuends without regrouping using appropriate strategies. | N48: 1.034 Subtracts mentally one-digit numbers from two-digit minuends without regrouping M1NS-IIi-33.1 | O48: P1/P2/A1/A2 | P48: PH_G1_C04_P2.1.2 | Q48: =E48 -> Ch 4 Practice 2.1.2: Subtracting using number bonds | R48: PH, PR1MEPH | S48: Practice | T48: MATHPRO | U48: Grade 1 | V48: Chapter 4 Subtraction | W48: 9789814969369 | X48: 54 | Y48: 1. Numbers and Number Sense | Z48: G1.1.02 Addition / Subtraction | AA48: Subtraction with Number Bonds | AB48: =J48 -> 1.046 To work out a subtraction fact within 10 M1NS-IIi-33.1 | AC48: =Y48 -> 1. Numbers and Number Sense | AD48: =Z48 -> G1.1.02 Addition / Subtraction | AE48: =K48 -> M1NS-IIi-33.1 | AF48: =M48 -> M1NS-IIi-33.1: Subtracts mentally one-digit numbers from two-digit minuends without regrouping using appropriate strategies. | AG48: =N48 -> 1.034 Subtracts mentally one-digit numbers from two-digit minuends without regrouping M1NS-IIi-33.1 | AH48: 4 | AI48: PH_G1_C04_P2.1.1 | AJ48: To relate a subtraction fact within 10 to a number bond | AP48: Published | AQ48: =IF($AP48="Raw Manuscript created","Editor to review",IF($AP48="Manuscript reviewed by Editor","Author to revise",IF($AP48="Manuscript revised by Author","Editor to review",IF($AP48="Manuscript finalised by Editor","Evonne to PFP",IF($AP48="Manuscript approved by Evonne","Evelyn to upload to Learnosity",IF($AP48="Manuscript uploaded to Learnosity","Prepress to create Activity",IF($AP48="Ready practice on Learnosity","Prepress to create Activity",IF($AP48="Activity created","Editor to conduct Learnosity review",IF($AP48="Published","Completed",""))))))))) -> Completed
C49: 2.2 Writing a fact family | D49: PINE_G1_C04_P2.2.1 | E49: Ch 4 Practice 2.2.1: Writing a fact family | F49: To write a family of four addition and subtraction facts for a given number bond | G49: 7 | H49: 15 (Rev1) | I49: B_08 | J49: 1.047 To write a family of four addition and subtraction facts for a given number bond M1NS-IIf-25 | K49: M1NS-IIf-25 | L49: Illustrates that addition and subtraction are inverse operations | M49: M1NS-IIf-25: Illustrates that addition and subtraction are inverse operations. | N49: 1.029 Illustrates that addition and subtraction are inverse operations M1NS-IIf-25 | O49: P1/P2/A1/A2 | P49: PH_G1_C04_P2.2.1 | Q49: =E49 -> Ch 4 Practice 2.2.1: Writing a fact family | R49: PH, PR1MEPH | S49: Practice | T49: MATHPRO | U49: Grade 1 | V49: Chapter 4 Subtraction | W49: 9789814969369 | X49: 58 | Y49: 1. Numbers and Number Sense | Z49: G1.1.02 Addition / Subtraction | AA49: Subtraction with Number Bonds | AB49: =J49 -> 1.047 To write a family of four addition and subtraction facts for a given number bond M1NS-IIf-25 | AC49: =Y49 -> 1. Numbers and Number Sense | AD49: =Z49 -> G1.1.02 Addition / Subtraction | AE49: =K49 -> M1NS-IIf-25 | AF49: =M49 -> M1NS-IIf-25: Illustrates that addition and subtraction are inverse operations. | AG49: =N49 -> 1.029 Illustrates that addition and subtraction are inverse operations M1NS-IIf-25 | AH49: 4 | AI49: PH_G1_C04_P2.1.2 | AJ49: To work out a subtraction fact within 10 by recalling the related number bond | AP49: Published | AQ49: =IF($AP49="Raw Manuscript created","Editor to review",IF($AP49="Manuscript reviewed by Editor","Author to revise",IF($AP49="Manuscript revised by Author","Editor to review",IF($AP49="Manuscript finalised by Editor","Evonne to PFP",IF($AP49="Manuscript approved by Evonne","Evelyn to upload to Learnosity",IF($AP49="Manuscript uploaded to Learnosity","Prepress to create Activity",IF($AP49="Ready practice on Learnosity","Prepress to create Activity",IF($AP49="Activity created","Editor to conduct Learnosity review",IF($AP49="Published","Completed",""))))))))) -> Completed
B50: Unit 3: Other Methods of Subtraction | C50: 3.1 Counting backwards | D50: PINE_G1_C04_P3.1.1 | E50: Ch 4 Practice 3.1.1: Subtracting by counting backwards | F50: To use the ‘counting backwards’ method to subtract 1, 2 or 3 from a number within 10 | G50: 8 | H50: 16 (Rev1) | I50: A_04 | J50: 1.048 To use the ‘counting backwards’ method to subtract within 10 M1NS-IIg-32.1 | K50: M1NS-IIg-32.1 | L50: Visualizes, represents, and subtracts one-digit numbers with minuends through 18 (basic facts) | M50: M1NS-IIg-32.1: Visualizes, represents, and subtracts one-digit numbers with minuends through 18 (basic facts). | N50: 1.030 Visualizes, represents, and subtracts one-digit numbers with minuends through 18 M1NS-IIg-32.1 | O50: P1/P2/A1/A2 | P50: PH_G1_C04_P3.1.1 | Q50: =E50 -> Ch 4 Practice 3.1.1: Subtracting by counting backwards | R50: PH, PR1MEPH | S50: Practice | T50: MATHPRO | U50: Grade 1 | V50: Chapter 4 Subtraction | W50: 9789814969369 | X50: 60 | Y50: 1. Numbers and Number Sense | Z50: G1.1.02 Addition / Subtraction | AA50: Other Methods of Subtraction | AB50: =J50 -> 1.048 To use the ‘counting backwards’ method to subtract within 10 M1NS-IIg-32.1 | AC50: =Y50 -> 1. Numbers and Number Sense | AD50: =Z50 -> G1.1.02 Addition / Subtraction | AE50: =K50 -> M1NS-IIg-32.1 | AF50: =M50 -> M1NS-IIg-32.1: Visualizes, represents, and subtracts one-digit numbers with minuends through 18 (basic facts). | AG50: =N50 -> 1.030 Visualizes, represents, and subtracts one-digit numbers with minuends through 18 M1NS-IIg-32.1 | AH50: 4 | AI50: PH_G1_C01_P1.4.1 | AJ50: To count on and backwards within 10 | AP50: Published | AQ50: =IF($AP50="Raw Manuscript created","Editor to review",IF($AP50="Manuscript reviewed by Editor","Author to revise",IF($AP50="Manuscript revised by Author","Editor to review",IF($AP50="Manuscript finalised by Editor","Evonne to PFP",IF($AP50="Manuscript approved by Evonne","Evelyn to upload to Learnosity",IF($AP50="Manuscript uploaded to Learnosity","Prepress to create Activity",IF($AP50="Ready practice on Learnosity","Prepress to create Activity",IF($AP50="Activity created","Editor to conduct Learnosity review",IF($AP50="Published","Completed",""))))))))) -> Completed
D51: PINE_G1_C04_P3.2.1 | E51: Ch 4 Practice 3.1.2: Subtracting by counting on | F51: To use the 'counting on' method to subtract from a number within 10 | G51: 9 | I51: EOY_4 | J51: 1.049 To use the 'counting on' method to subtract from a number within 10 M1NS-IIg-32.1 | K51: M1NS-IIg-32.1 | L51: Visualizes, represents, and subtracts one-digit numbers with minuends through 18 (basic facts) | M51: M1NS-IIg-32.1: Visualizes, represents, and subtracts one-digit numbers with minuends through 18 (basic facts). | N51: 1.030 Visualizes, represents, and subtracts one-digit numbers with minuends through 18 M1NS-IIg-32.1 | O51: P1/P2/A1/A2 | P51: PH_G1_C04_P3.1.2 | Q51: =E51 -> Ch 4 Practice 3.1.2: Subtracting by counting on | R51: PH, PR1MEPH | S51: Practice | T51: MATHPRO | U51: Grade 1 | V51: Chapter 4 Subtraction | W51: 9789814969369 | X51: 60 | Y51: 1. Numbers and Number Sense | Z51: G1.1.02 Addition / Subtraction | AA51: Other Methods of Subtraction | AB51: =J51 -> 1.049 To use the 'counting on' method to subtract from a number within 10 M1NS-IIg-32.1 | AC51: =Y51 -> 1. Numbers and Number Sense | AD51: =Z51 -> G1.1.02 Addition / Subtraction | AE51: =K51 -> M1NS-IIg-32.1 | AF51: =M51 -> M1NS-IIg-32.1: Visualizes, represents, and subtracts one-digit numbers with minuends through 18 (basic facts). | AG51: =N51 -> 1.030 Visualizes, represents, and subtracts one-digit numbers with minuends through 18 M1NS-IIg-32.1 | AH51: 4 | AI51: PH_G1_C01_P1.4.1 | AJ51: To count on and backwards within 10 | AP51: Published | AQ51: =IF($AP51="Raw Manuscript created","Editor to review",IF($AP51="Manuscript reviewed by Editor","Author to revise",IF($AP51="Manuscript revised by Author","Editor to review",IF($AP51="Manuscript finalised by Editor","Evonne to PFP",IF($AP51="Manuscript approved by Evonne","Evelyn to upload to Learnosity",IF($AP51="Manuscript uploaded to Learnosity","Prepress to create Activity",IF($AP51="Ready practice on Learnosity","Prepress to create Activity",IF($AP51="Activity created","Editor to conduct Learnosity review",IF($AP51="Published","Completed",""))))))))) -> Completed | AR51: remove row as objective is not in SOW
D52: PH_G1_C04_P3.1.3 | E52: Ch 4 Practice 3.1.3: Identify numbers which differ by 1 or 2 | F52: Identify numbers which differ by 1 or 2 | G52: 10 | J52: 1.049a Identify numbers which differ by 1 or 2 M1NS-IIg-32.1 | K52: M1NS-IIg-32.1 | L52: Visualizes, represents, and subtracts one-digit numbers with minuends through 18 (basic facts) | M52: M1NS-IIg-32.1: Visualizes, represents, and subtracts one-digit numbers with minuends through 18 (basic facts). | N52: 1.030 Visualizes, represents, and subtracts one-digit numbers with minuends through 18 M1NS-IIg-32.1 | O52: P1/P2/A1/A2 | P52: PH_G1_C04_P3.1.3 | Q52: =E52 -> Ch 4 Practice 3.1.3: Identify numbers which differ by 1 or 2 | R52: PH, PR1MEPH | S52: Practice | T52: MATHPRO | U52: Grade 1 | V52: Chapter 4 Subtraction | W52: 9789814969369 | X52: 60 | Y52: 1. Numbers and Number Sense | Z52: G1.1.02 Addition / Subtraction | AA52: Other Methods of Subtraction | AB52: =J52 -> 1.049a Identify numbers which differ by 1 or 2 M1NS-IIg-32.1 | AC52: =Y52 -> 1. Numbers and Number Sense | AD52: =Z52 -> G1.1.02 Addition / Subtraction | AE52: =K52 -> M1NS-IIg-32.1 | AF52: =M52 -> M1NS-IIg-32.1: Visualizes, represents, and subtracts one-digit numbers with minuends through 18 (basic facts). | AG52: =N52 -> 1.030 Visualizes, represents, and subtracts one-digit numbers with minuends through 18 M1NS-IIg-32.1 | AH52: 4 | AI52: PH_G1_C04_P3.1.1 PH_G1_C04_P3.1.2 | AJ52: To use the ‘counting backwards’ method to subtract 1, 2 or 3 from a number within 10 To use the 'counting on' method to subtract from a number within 10 | AP52: Published | AQ52: =IF($AP52="Raw Manuscript created","Editor to review",IF($AP52="Manuscript reviewed by Editor","Author to revise",IF($AP52="Manuscript revised by Author","Editor to review",IF($AP52="Manuscript finalised by Editor","Evonne to PFP",IF($AP52="Manuscript approved by Evonne","Evelyn to upload to Learnosity",IF($AP52="Manuscript uploaded to Learnosity","Prepress to create Activity",IF($AP52="Ready practice on Learnosity","Prepress to create Activity",IF($AP52="Activity created","Editor to conduct Learnosity review",IF($AP52="Published","Completed",""))))))))) -> Completed
C53: 3.2 Subtracting from 10 | D53: PINE_G1_C04_P3.3.1 | E53: Ch 4 Practice 3.2.1: Subtracting from 10 | F53: To subtract a number from 10 | G53: 11 10 | H53: 17 (Rev1) | J53: 1.050 To subtract a number from 10 M1NS-IIg-32.1 | K53: M1NS-IIg-32.1 | L53: Visualizes, represents, and subtracts one-digit numbers with minuends through 18 (basic facts) | M53: M1NS-IIg-32.1: Visualizes, represents, and subtracts one-digit numbers with minuends through 18 (basic facts). | N53: 1.030 Visualizes, represents, and subtracts one-digit numbers with minuends through 18 M1NS-IIg-32.1 | O53: P1/P2/A1/A2 | P53: PH_G1_C04_P3.2.1 | Q53: =E53 -> Ch 4 Practice 3.2.1: Subtracting from 10 | R53: PH, PR1MEPH | S53: Practice | T53: MATHPRO | U53: Grade 1 | V53: Chapter 4 Subtraction | W53: 9789814969369 | X53: 63 | Y53: 1. Numbers and Number Sense | Z53: G1.1.02 Addition / Subtraction | AA53: Other Methods of Subtraction | AB53: =J53 -> 1.050 To subtract a number from 10 M1NS-IIg-32.1 | AC53: =Y53 -> 1. Numbers and Number Sense | AD53: =Z53 -> G1.1.02 Addition / Subtraction | AE53: =K53 -> M1NS-IIg-32.1 | AF53: =M53 -> M1NS-IIg-32.1: Visualizes, represents, and subtracts one-digit numbers with minuends through 18 (basic facts). | AG53: =N53 -> 1.030 Visualizes, represents, and subtracts one-digit numbers with minuends through 18 M1NS-IIg-32.1 | AH53: 4 | AI53: PH_G1_C04_P3.1.2 | AJ53: To use the 'counting on' method to subtract from a number within 10 | AP53: Published | AQ53: =IF($AP53="Raw Manuscript created","Editor to review",IF($AP53="Manuscript reviewed by Editor","Author to revise",IF($AP53="Manuscript revised by Author","Editor to review",IF($AP53="Manuscript finalised by Editor","Evonne to PFP",IF($AP53="Manuscript approved by Evonne","Evelyn to upload to Learnosity",IF($AP53="Manuscript uploaded to Learnosity","Prepress to create Activity",IF($AP53="Ready practice on Learnosity","Prepress to create Activity",IF($AP53="Activity created","Editor to conduct Learnosity review",IF($AP53="Published","Completed",""))))))))) -> Completed
D54: PINE_G1_C04_P3.4.1 | E54: Ch 4 Practice 3.2.2: Completing addition and subtraction sentences | F54: To use '+', '-' or '=' correctly to complete mathematical sentences | G54: 12 11 | H54: 2 (Rev3) | I54: B_03 | J54: 1.051 To use '+', '-' or '=' correctly to complete mathematical sentences M1NS-Ih-12.1 | K54: M1NS-Ih-12.1 | L54: Visualizes, represents, and compares numbers up to 100 using relation symbols | M54: M1NS-Ih-12.1: Visualizes, represents, and compares numbers up to 100 using relation symbols. | N54: 1.012 Visualizes, represents, and compares numbers up to 100 M1NS-Ih-12.1 | O54: P1/P2/A1/A2 | P54: PH_G1_C04_P3.2.2 | Q54: =E54 -> Ch 4 Practice 3.2.2: Completing addition and subtraction sentences | R54: PH, PR1MEPH | S54: Practice | T54: MATHPRO | U54: Grade 1 | V54: Chapter 4 Subtraction | W54: 9789814969369 | X54: 63 | Y54: 1. Numbers and Number Sense | Z54: G1.1.02 Addition / Subtraction | AA54: Other Methods of Subtraction | AB54: =J54 -> 1.051 To use '+', '-' or '=' correctly to complete mathematical sentences M1NS-Ih-12.1 | AC54: =Y54 -> 1. Numbers and Number Sense | AD54: =Z54 -> G1.1.02 Addition / Subtraction | AE54: =K54 -> M1NS-Ih-12.1 | AF54: =M54 -> M1NS-Ih-12.1: Visualizes, represents, and compares numbers up to 100 using relation symbols. | AG54: =N54 -> 1.012 Visualizes, represents, and compares numbers up to 100 M1NS-Ih-12.1 | AH54: 4 | AI54: PH_G1_C04_P2.2.1 | AJ54: To write a family of four addition and subtraction facts for a given number bond | AP54: Published | AQ54: =IF($AP54="Raw Manuscript created","Editor to review",IF($AP54="Manuscript reviewed by Editor","Author to revise",IF($AP54="Manuscript revised by Author","Editor to review",IF($AP54="Manuscript finalised by Editor","Evonne to PFP",IF($AP54="Manuscript approved by Evonne","Evelyn to upload to Learnosity",IF($AP54="Manuscript uploaded to Learnosity","Prepress to create Activity",IF($AP54="Ready practice on Learnosity","Prepress to create Activity",IF($AP54="Activity created","Editor to conduct Learnosity review",IF($AP54="Published","Completed",""))))))))) -> Completed | AR54: remove row as objective is not in SOW
D55: PH_G1_C04_P3.2.3 | E55: Ch 4 Practice 3.2.3: Solve a 1-step picture problem by subtraction | F55: Solve a 1-step picture problem by subtraction | G55: 13 12 | H55: 2 (Rev2) | J55: 1.051a Solve a 1-step picture problem by subtraction M1NS-IIi-34.1 | K55: M1NS-IIi-34.1 | L55: Visualizes, represents, and solves routine and non-routine problems involving subtraction of whole numbers including money with minuends up to 99 with and without regrouping using appropriate problem solving strategies and tools | M55: M1NS-IIi-34.1: Visualizes, represents, and solves routine and non-routine problems involving subtraction of whole numbers including money with minuends up to 99 with and without regrouping using appropriate problem solving strategies and tools. | N55: 1.035 Visualizes, represents, and solves routine and non-routine problems involving subtraction of whole numbers including money with minuends up to 99 with and without regrouping 1NS-IIi-34.1 | O55: P1/P2/A1/A2 | P55: PH_G1_C04_P3.2.3 | Q55: =E55 -> Ch 4 Practice 3.2.3: Solve a 1-step picture problem by subtraction | R55: PH, PR1MEPH | S55: Practice | T55: MATHPRO | U55: Grade 1 | V55: Chapter 4 Subtraction | W55: 9789814969369 | X55: 63 | Y55: 1. Numbers and Number Sense | Z55: G1.1.02 Addition / Subtraction | AA55: Other Methods of Subtraction | AB55: =J55 -> 1.051a Solve a 1-step picture problem by subtraction M1NS-IIi-34.1 | AC55: =Y55 -> 1. Numbers and Number Sense | AD55: =Z55 -> G1.1.02 Addition / Subtraction | AE55: =K55 -> M1NS-IIi-34.1 | AF55: =M55 -> M1NS-IIi-34.1: Visualizes, represents, and solves routine and non-routine problems involving subtraction of whole numbers including money with minuends up to 99 with and without regrouping using appropriate problem solving strategies and tools. | AG55: =N55 -> 1.035 Visualizes, represents, and solves routine and non-routine problems involving subtraction of whole numbers including money with minuends up to 99 with and without regrouping 1NS-IIi-34.1 | AH55: 4 | AI55: PH_G1_C04_P2.2.1 | AJ55: To write a family of four addition and subtraction facts for a given number bond | AP55: Published | AQ55: =IF($AP55="Raw Manuscript created","Editor to review",IF($AP55="Manuscript reviewed by Editor","Author to revise",IF($AP55="Manuscript revised by Author","Editor to review",IF($AP55="Manuscript finalised by Editor","Evonne to PFP",IF($AP55="Manuscript approved by Evonne","Evelyn to upload to Learnosity",IF($AP55="Manuscript uploaded to Learnosity","Prepress to create Activity",IF($AP55="Ready practice on Learnosity","Prepress to create Activity",IF($AP55="Activity created","Editor to conduct Learnosity review",IF($AP55="Published","Completed",""))))))))) -> Completed
A56: Chapter 5: Ordinal Numbers and Positions | B56: Unit 1: Naming Positions | C56: 1.1 Knowing position words | D56: PINE_G1_C05_P1.1.1 | E56: Ch 5 Practice 1.1.1: Describing positions | F56: To use the words ‘left’, ‘right’, 'next to' and 'between' to describe the positions of objects | G56: 1, 2 | H56: 18 (Rev1) | J56: 1.052 To use the words ‘left’, ‘right’, 'next to' and 'between' to describe the positions of objects M1NS-Ii-16.1 | K56: M1NS-Ii-16.1 | L56: Identifies the 1st , 2nd, 3rd, up to 10th object in a given set from a given point of reference | M56: M1NS-Ii-16.1: Identifies the 1st, 2nd, 3rd, up to 10th object in a given set from a given point of reference. | N56: 1.014 Identifies the 1st, 2nd, 3rd, up to 10th object in a given set from a given point of reference M1NS-Ii-16.1 | O56: P1/P2/A1/A2 | P56: PH_G1_C05_P1.1.1 | Q56: =E56 -> Ch 5 Practice 1.1.1: Describing positions | R56: PH, PR1MEPH | S56: Practice | T56: MATHPRO | U56: Grade 1 | V56: Chapter 5 Ordinal Numbers and Positions | W56: 9789814969369 | X56: 65 | Y56: 1. Numbers and Number Sense | Z56: G1.1.01 Whole Numbers / Place Value | AA56: Naming Positions | AB56: =J56 -> 1.052 To use the words ‘left’, ‘right’, 'next to' and 'between' to describe the positions of objects M1NS-Ii-16.1 | AC56: =Y56 -> 1. Numbers and Number Sense | AD56: =Z56 -> G1.1.01 Whole Numbers / Place Value | AE56: =K56 -> M1NS-Ii-16.1 | AF56: =M56 -> M1NS-Ii-16.1: Identifies the 1st, 2nd, 3rd, up to 10th object in a given set from a given point of reference. | AG56: =N56 -> 1.014 Identifies the 1st, 2nd, 3rd, up to 10th object in a given set from a given point of reference M1NS-Ii-16.1 | AH56: 5 | AI56: n.a. | AJ56: n.a. | AP56: Published | AQ56: =IF($AP56="Raw Manuscript created","Editor to review",IF($AP56="Manuscript reviewed by Editor","Author to revise",IF($AP56="Manuscript revised by Author","Editor to review",IF($AP56="Manuscript finalised by Editor","Evonne to PFP",IF($AP56="Manuscript approved by Evonne","Evelyn to upload to Learnosity",IF($AP56="Manuscript uploaded to Learnosity","Prepress to create Activity",IF($AP56="Ready practice on Learnosity","Prepress to create Activity",IF($AP56="Activity created","Editor to conduct Learnosity review",IF($AP56="Published","Completed",""))))))))) -> Completed
C57: 1.2 Knowing 1st to 10th | D57: PINE_G1_C05_P1.2.1 | E57: Ch 5 Practice 1.2.1: Knowing 1st to 10th | F57: To name a position using an ordinal number from 1st to 10th | G57: 3 | H57: 19 (Rev1) | J57: 1.053 To name a position using an ordinal number from 1st to 10th M1NS-Ii-16.1 | K57: M1NS-Ii-16.1 | L57: Identifies the 1st , 2nd, 3rd, up to 10th object in a given set from a given point of reference | M57: M1NS-Ii-16.1: Identifies the 1st, 2nd, 3rd, up to 10th object in a given set from a given point of reference. | N57: 1.014 Identifies the 1st, 2nd, 3rd, up to 10th object in a given set from a given point of reference M1NS-Ii-16.1 | O57: P1/P2/A1/A2 | P57: PH_G1_C05_P1.2.1 | Q57: =E57 -> Ch 5 Practice 1.2.1: Knowing 1st to 10th | R57: PH, PR1MEPH | S57: Practice | T57: MATHPRO | U57: Grade 1 | V57: Chapter 5 Ordinal Numbers and Positions | W57: 9789814969369 | X57: 69 | Y57: 1. Numbers and Number Sense | Z57: G1.1.01 Whole Numbers / Place Value | AA57: Naming Positions | AB57: =J57 -> 1.053 To name a position using an ordinal number from 1st to 10th M1NS-Ii-16.1 | AC57: =Y57 -> 1. Numbers and Number Sense | AD57: =Z57 -> G1.1.01 Whole Numbers / Place Value | AE57: =K57 -> M1NS-Ii-16.1 | AF57: =M57 -> M1NS-Ii-16.1: Identifies the 1st, 2nd, 3rd, up to 10th object in a given set from a given point of reference. | AG57: =N57 -> 1.014 Identifies the 1st, 2nd, 3rd, up to 10th object in a given set from a given point of reference M1NS-Ii-16.1 | AH57: 5 | AI57: PH_G1_C01_P1.1.1 | AJ57: To count within 10 (including the use of zero to denote an empty set) | AP57: Published | AQ57: =IF($AP57="Raw Manuscript created","Editor to review",IF($AP57="Manuscript reviewed by Editor","Author to revise",IF($AP57="Manuscript revised by Author","Editor to review",IF($AP57="Manuscript finalised by Editor","Evonne to PFP",IF($AP57="Manuscript approved by Evonne","Evelyn to upload to Learnosity",IF($AP57="Manuscript uploaded to Learnosity","Prepress to create Activity",IF($AP57="Ready practice on Learnosity","Prepress to create Activity",IF($AP57="Activity created","Editor to conduct Learnosity review",IF($AP57="Published","Completed",""))))))))) -> Completed
D58: PINE_G1_C05_P1.2.2 | E58: Ch 5 Practice 1.2.2: More on describing positions | F58: To name a position using the phrases ‘behind’, ‘in front of', ‘last’, | G58: 4 | H58: 20 (Rev1) | J58: 1.054 To name a position using the phrases ‘behind’, ‘in front of', ‘last’ M1NS-Ii-16.1 | K58: M1NS-Ii-16.1 | L58: Identifies the 1st , 2nd, 3rd, up to 10th object in a given set from a given point of reference | M58: M1NS-Ii-16.1: Identifies the 1st, 2nd, 3rd, up to 10th object in a given set from a given point of reference. | N58: 1.014 Identifies the 1st, 2nd, 3rd, up to 10th object in a given set from a given point of reference M1NS-Ii-16.1 | O58: P1/P2/A1/A2 | P58: PH_G1_C05_P1.2.2 | Q58: =E58 -> Ch 5 Practice 1.2.2: More on describing positions | R58: PH, PR1MEPH | S58: Practice | T58: MATHPRO | U58: Grade 1 | V58: Chapter 5 Ordinal Numbers and Positions | W58: 9789814969369 | X58: 69 | Y58: 1. Numbers and Number Sense | Z58: G1.1.01 Whole Numbers / Place Value | AA58: Naming Positions | AB58: =J58 -> 1.054 To name a position using the phrases ‘behind’, ‘in front of', ‘last’ M1NS-Ii-16.1 | AC58: =Y58 -> 1. Numbers and Number Sense | AD58: =Z58 -> G1.1.01 Whole Numbers / Place Value | AE58: =K58 -> M1NS-Ii-16.1 | AF58: =M58 -> M1NS-Ii-16.1: Identifies the 1st, 2nd, 3rd, up to 10th object in a given set from a given point of reference. | AG58: =N58 -> 1.014 Identifies the 1st, 2nd, 3rd, up to 10th object in a given set from a given point of reference M1NS-Ii-16.1 | AH58: 5 | AI58: PH_G1_C05_P1.2.1 | AJ58: To name a position using an ordinal number from 1st to 10th | AP58: Published | AQ58: =IF($AP58="Raw Manuscript created","Editor to review",IF($AP58="Manuscript reviewed by Editor","Author to revise",IF($AP58="Manuscript revised by Author","Editor to review",IF($AP58="Manuscript finalised by Editor","Evonne to PFP",IF($AP58="Manuscript approved by Evonne","Evelyn to upload to Learnosity",IF($AP58="Manuscript uploaded to Learnosity","Prepress to create Activity",IF($AP58="Ready practice on Learnosity","Prepress to create Activity",IF($AP58="Activity created","Editor to conduct Learnosity review",IF($AP58="Published","Completed",""))))))))) -> Completed
C59: 1.3 Naming positions from the left or right | D59: PINE_G1_C05_P1.3.1 | E59: Ch 5 Practice 1.3.1: Naming positions from the left or right | F59: To name a position using an ordinal number from 1st to 10th To name a position using the words ‘left’ and ‘right’ | G59: 5 | H59: 3 (Rev2) | I59: A_05 | J59: 1.055 To name a position using an ordinal number from 1st to 10th M1NS-Ii-17.1 | K59: M1NS-Ii-17.1 | L59: Reads and writes ordinal numbers: 1st, 2nd, 3rd up to 10th | M59: M1NS-Ii-17.1: Reads and writes ordinal numbers: 1st, 2nd, 3rd up to 10th. | N59: 1.015 Reads and writes ordinal numbers M1NS-Ii-17.1 | O59: P1/P2/A1/A2 | P59: PH_G1_C05_P1.3.1 | Q59: =E59 -> Ch 5 Practice 1.3.1: Naming positions from the left or right | R59: PH, PR1MEPH | S59: Practice | T59: MATHPRO | U59: Grade 1 | V59: Chapter 5 Ordinal Numbers and Positions | W59: 9789814969369 | X59: 70 | Y59: 1. Numbers and Number Sense | Z59: G1.1.01 Whole Numbers / Place Value | AA59: Naming Positions | AB59: =J59 -> 1.055 To name a position using an ordinal number from 1st to 10th M1NS-Ii-17.1 | AC59: =Y59 -> 1. Numbers and Number Sense | AD59: =Z59 -> G1.1.01 Whole Numbers / Place Value | AE59: =K59 -> M1NS-Ii-17.1 | AF59: =M59 -> M1NS-Ii-17.1: Reads and writes ordinal numbers: 1st, 2nd, 3rd up to 10th. | AG59: =N59 -> 1.015 Reads and writes ordinal numbers M1NS-Ii-17.1 | AH59: 5 | AI59: PH_G1_C05_P1.2.1 | AJ59: To name a position using an ordinal number from 1st to 10th | AP59: Published | AQ59: =IF($AP59="Raw Manuscript created","Editor to review",IF($AP59="Manuscript reviewed by Editor","Author to revise",IF($AP59="Manuscript revised by Author","Editor to review",IF($AP59="Manuscript finalised by Editor","Evonne to PFP",IF($AP59="Manuscript approved by Evonne","Evelyn to upload to Learnosity",IF($AP59="Manuscript uploaded to Learnosity","Prepress to create Activity",IF($AP59="Ready practice on Learnosity","Prepress to create Activity",IF($AP59="Activity created","Editor to conduct Learnosity review",IF($AP59="Published","Completed",""))))))))) -> Completed
A60: Chapter 6: Numbers 0 to 20 | B60: Unit 1: Counting and Comparing | C60: 1.1 Counting, reading and writing numbers | D60: PINE_G1_C06_P1.1.1 | E60: Ch 6 Practice 1.1.1: Counting, reading and writing numbers | F60: To read and write a number from 11 to 20 — the numeral and the corresponding number word | G60: 1 | H60: 4 (Rev2) | J60: 1.056 To read and write a number from 11 to 20 M1NS-If-9.1 | K60: M1NS-If-9.1 | L60: Reads and writes numbers up to 100 in symbols and in words | M60: M1NS-If-9.1: Reads and writes numbers up to 100 in symbols and in words. | N60: 1.009 Reads and writes numbers up to 100 in symbols and in words M1NS-If-9.1 | O60: P1/P2/A1/A2 | P60: PH_G1_C06_P1.1.1 | Q60: =E60 -> Ch 6 Practice 1.1.1: Counting, reading and writing numbers | R60: PH, PR1MEPH | S60: Practice | T60: MATHPRO | U60: Grade 1 | V60: Chapter 6 Numbers 0 to 20 | W60: 9789814969369 | X60: 75 | Y60: 1. Numbers and Number Sense | Z60: G1.1.01 Whole Numbers / Place Value | AA60: Counting and Comparing | AB60: =J60 -> 1.056 To read and write a number from 11 to 20 M1NS-If-9.1 | AC60: =Y60 -> 1. Numbers and Number Sense | AD60: =Z60 -> G1.1.01 Whole Numbers / Place Value | AE60: =K60 -> M1NS-If-9.1 | AF60: =M60 -> M1NS-If-9.1: Reads and writes numbers up to 100 in symbols and in words. | AG60: =N60 -> 1.009 Reads and writes numbers up to 100 in symbols and in words M1NS-If-9.1 | AH60: 6 | AI60: PH_G1_C01_P1.1.2 | AJ60: To read and write a number from 0 to 10 — the numeral and the corresponding number word | AP60: Published | AQ60: =IF($AP60="Raw Manuscript created","Editor to review",IF($AP60="Manuscript reviewed by Editor","Author to revise",IF($AP60="Manuscript revised by Author","Editor to review",IF($AP60="Manuscript finalised by Editor","Evonne to PFP",IF($AP60="Manuscript approved by Evonne","Evelyn to upload to Learnosity",IF($AP60="Manuscript uploaded to Learnosity","Prepress to create Activity",IF($AP60="Ready practice on Learnosity","Prepress to create Activity",IF($AP60="Activity created","Editor to conduct Learnosity review",IF($AP60="Published","Completed",""))))))))) -> Completed
C61: 1.2 Understanding 2-digit numbers | D61: PINE_G1_C06_P1.2.1 | E61: Ch 6 Practice 1.2.1: Understanding 2-digit numbers | F61: To count within 20 by making a 10 first | G61: 2 | J61: 1.057 To count within 20 by making a 10 first M1NS-Ie-8.1 | K61: M1NS-Ie-8.1 | L61: Visualizes and counts by 2s, 5s and 10s through 100 | M61: M1NS-Ie-8.1: Visualizes and counts by 2s, 5s and 10s through 100. | N61: 1.008 Visualizes and counts by 2s, 5s and 10s through 100 M1NS-Ie-8.1 | O61: P1/P2/A1/A2 | P61: PH_G1_C06_P1.2.1 | Q61: =E61 -> Ch 6 Practice 1.2.1: Understanding 2-digit numbers | R61: PH, PR1MEPH | S61: Practice | T61: MATHPRO | U61: Grade 1 | V61: Chapter 6 Numbers 0 to 20 | W61: 9789814969369 | X61: 75 | Y61: 1. Numbers and Number Sense | Z61: G1.1.01 Whole Numbers / Place Value | AA61: Counting and Comparing | AB61: =J61 -> 1.057 To count within 20 by making a 10 first M1NS-Ie-8.1 | AC61: =Y61 -> 1. Numbers and Number Sense | AD61: =Z61 -> G1.1.01 Whole Numbers / Place Value | AE61: =K61 -> M1NS-Ie-8.1 | AF61: =M61 -> M1NS-Ie-8.1: Visualizes and counts by 2s, 5s and 10s through 100. | AG61: =N61 -> 1.008 Visualizes and counts by 2s, 5s and 10s through 100 M1NS-Ie-8.1 | AH61: 6 | AI61: PH_G1_C03_P3.4.1 | AJ61: To make 10 | AP61: Published | AQ61: =IF($AP61="Raw Manuscript created","Editor to review",IF($AP61="Manuscript reviewed by Editor","Author to revise",IF($AP61="Manuscript revised by Author","Editor to review",IF($AP61="Manuscript finalised by Editor","Evonne to PFP",IF($AP61="Manuscript approved by Evonne","Evelyn to upload to Learnosity",IF($AP61="Manuscript uploaded to Learnosity","Prepress to create Activity",IF($AP61="Ready practice on Learnosity","Prepress to create Activity",IF($AP61="Activity created","Editor to conduct Learnosity review",IF($AP61="Published","Completed",""))))))))) -> Completed
C62: 1.3 Counting on and backwards | D62: PINE_G1_C06_P1.3.1 | E62: Ch 6 Practice 1.3.1: Counting on and backwards | F62: To count on and backwards by 1 or 2 within 20 | G62: 3 | H62: 5 (Rev2) | J62: 1.058 To count on and backwards by 1 or 2 within 20 M1NS-Ie-8.1 | K62: M1NS-Ie-8.1 | L62: Visualizes and counts by 2s, 5s and 10s through 100 | M62: M1NS-Ie-8.1: Visualizes and counts by 2s, 5s and 10s through 100. | N62: 1.008 Visualizes and counts by 2s, 5s and 10s through 100 M1NS-Ie-8.1 | O62: P1/P2/A1/A2 | P62: PH_G1_C06_P1.3.1 | Q62: =E62 -> Ch 6 Practice 1.3.1: Counting on and backwards | R62: PH, PR1MEPH | S62: Practice | T62: MATHPRO | U62: Grade 1 | V62: Chapter 6 Numbers 0 to 20 | W62: 9789814969369 | X62: 76 | Y62: 1. Numbers and Number Sense | Z62: G1.1.01 Whole Numbers / Place Value | AA62: Counting and Comparing | AB62: =J62 -> 1.058 To count on and backwards by 1 or 2 within 20 M1NS-Ie-8.1 | AC62: =Y62 -> 1. Numbers and Number Sense | AD62: =Z62 -> G1.1.01 Whole Numbers / Place Value | AE62: =K62 -> M1NS-Ie-8.1 | AF62: =M62 -> M1NS-Ie-8.1: Visualizes and counts by 2s, 5s and 10s through 100. | AG62: =N62 -> 1.008 Visualizes and counts by 2s, 5s and 10s through 100 M1NS-Ie-8.1 | AH62: 6 | AI62: PH_G1_C01_P1.4.1 | AJ62: To count on and backwards within 10 | AP62: Published | AQ62: =IF($AP62="Raw Manuscript created","Editor to review",IF($AP62="Manuscript reviewed by Editor","Author to revise",IF($AP62="Manuscript revised by Author","Editor to review",IF($AP62="Manuscript finalised by Editor","Evonne to PFP",IF($AP62="Manuscript approved by Evonne","Evelyn to upload to Learnosity",IF($AP62="Manuscript uploaded to Learnosity","Prepress to create Activity",IF($AP62="Ready practice on Learnosity","Prepress to create Activity",IF($AP62="Activity created","Editor to conduct Learnosity review",IF($AP62="Published","Completed",""))))))))) -> Completed
D63: PINE_G1_C06_P1.3.2 | E63: Ch 6 Practice 1.3.2: Finding the number that comes before, after or between | F63: To give a number between two numbers within 20 | G63: 4 | J63: 1.059 To give a number between two numbers within 20 M1NS-Ib-3 | K63: M1NS-Ib-3 | L63: Identifies the number that is one more or one less from a given number | M63: M1NS-Ib-3: Identifies the number that is one more or one less from a given number. | N63: 1.003 Identifies the number that is one more or one less from a given number M1NS-Ib-3 | O63: P1/P2/A1/A2 | P63: PH_G1_C06_P1.3.2 | Q63: =E63 -> Ch 6 Practice 1.3.2: Finding the number that comes before, after or between | R63: PH, PR1MEPH | S63: Practice | T63: MATHPRO | U63: Grade 1 | V63: Chapter 6 Numbers 0 to 20 | W63: 9789814969369 | X63: 76 | Y63: 1. Numbers and Number Sense | Z63: G1.1.01 Whole Numbers / Place Value | AA63: Counting and Comparing | AB63: =J63 -> 1.059 To give a number between two numbers within 20 M1NS-Ib-3 | AC63: =Y63 -> 1. Numbers and Number Sense | AD63: =Z63 -> G1.1.01 Whole Numbers / Place Value | AE63: =K63 -> M1NS-Ib-3 | AF63: =M63 -> M1NS-Ib-3: Identifies the number that is one more or one less from a given number. | AG63: =N63 -> 1.003 Identifies the number that is one more or one less from a given number M1NS-Ib-3 | AH63: 6 | AI63: PH_G1_C06_P1.3.1 | AJ63: To count on and backwards by 1 or 2 within 20 | AP63: Published | AQ63: =IF($AP63="Raw Manuscript created","Editor to review",IF($AP63="Manuscript reviewed by Editor","Author to revise",IF($AP63="Manuscript revised by Author","Editor to review",IF($AP63="Manuscript finalised by Editor","Evonne to PFP",IF($AP63="Manuscript approved by Evonne","Evelyn to upload to Learnosity",IF($AP63="Manuscript uploaded to Learnosity","Prepress to create Activity",IF($AP63="Ready practice on Learnosity","Prepress to create Activity",IF($AP63="Activity created","Editor to conduct Learnosity review",IF($AP63="Published","Completed",""))))))))) -> Completed | AR63: remove row as objective is not in SOW
C64: 1.4 Comparing numbers | D64: PINE_G1_C06_P1.4.1 | E64: Ch 6 Practice 1.4.1: Comparing numbers | F64: To compare two numbers within 20 | G64: 5 | H64: 3 (Rev3) | I64: A_06 | J64: 1.060 To compare two numbers within 20 M1NS-Id-6 | K64: M1NS-Id-6 | L64: Visualizes, represents, and compares two sets using the expressions “less than,” “more than,” and “as many as” | M64: M1NS-Id-6: Visualizes, represents, and compares two sets using the expressions “less than”, “more than”, and “as many as”. | N64: 1.006 Visualizes, represents, and compares two sets M1NS-Id-6 | O64: P1/P2/A1/A2 | P64: PH_G1_C06_P1.4.1 | Q64: =E64 -> Ch 6 Practice 1.4.1: Comparing numbers | R64: PH, PR1MEPH | S64: Practice | T64: MATHPRO | U64: Grade 1 | V64: Chapter 6 Numbers 0 to 20 | W64: 9789814969369 | X64: 80 | Y64: 1. Numbers and Number Sense | Z64: G1.1.01 Whole Numbers / Place Value | AA64: Counting and Comparing | AB64: =J64 -> 1.060 To compare two numbers within 20 M1NS-Id-6 | AC64: =Y64 -> 1. Numbers and Number Sense | AD64: =Z64 -> G1.1.01 Whole Numbers / Place Value | AE64: =K64 -> M1NS-Id-6 | AF64: =M64 -> M1NS-Id-6: Visualizes, represents, and compares two sets using the expressions “less than”, “more than”, and “as many as”. | AG64: =N64 -> 1.006 Visualizes, represents, and compares two sets M1NS-Id-6 | AH64: 6 | AI64: PH_G1_C01_P1.3.2 | AJ64: To compare two numbers within 10 | AP64: Published | AQ64: =IF($AP64="Raw Manuscript created","Editor to review",IF($AP64="Manuscript reviewed by Editor","Author to revise",IF($AP64="Manuscript revised by Author","Editor to review",IF($AP64="Manuscript finalised by Editor","Evonne to PFP",IF($AP64="Manuscript approved by Evonne","Evelyn to upload to Learnosity",IF($AP64="Manuscript uploaded to Learnosity","Prepress to create Activity",IF($AP64="Ready practice on Learnosity","Prepress to create Activity",IF($AP64="Activity created","Editor to conduct Learnosity review",IF($AP64="Published","Completed",""))))))))) -> Completed
C65: 1.5 Comparing and ordering numbers | D65: PINE_G1_C06_P1.5.1 | E65: Ch 6 Practice 1.5.1: Comparing and ordering numbers | F65: To compare and order numbers within 20 | G65: 6 | H65: 6 (Rev2) | I65: B_04 | J65: 1.061 To compare and order numbers within 20 M1NS-Ie-7 | K65: M1NS-Ie-7 | L65: Visualizes, represents, and orders sets from least to greatest and vice versa | M65: M1NS-Ie-7: Visualizes, represents, and orders sets from least to greatest and vice versa. | N65: 1.007 Visualizes, represents, and orders sets from least to greatest and vice versa M1NS-Ie-7 | O65: P1/P2/A1/A2 | P65: PH_G1_C06_P1.5.1 | Q65: =E65 -> Ch 6 Practice 1.5.1: Comparing and ordering numbers | R65: PH, PR1MEPH | S65: Practice | T65: MATHPRO | U65: Grade 1 | V65: Chapter 6 Numbers 0 to 20 | W65: 9789814969369 | X65: 80 | Y65: 1. Numbers and Number Sense | Z65: G1.1.01 Whole Numbers / Place Value | AA65: Counting and Comparing | AB65: =J65 -> 1.061 To compare and order numbers within 20 M1NS-Ie-7 | AC65: =Y65 -> 1. Numbers and Number Sense | AD65: =Z65 -> G1.1.01 Whole Numbers / Place Value | AE65: =K65 -> M1NS-Ie-7 | AF65: =M65 -> M1NS-Ie-7: Visualizes, represents, and orders sets from least to greatest and vice versa. | AG65: =N65 -> 1.007 Visualizes, represents, and orders sets from least to greatest and vice versa M1NS-Ie-7 | AH65: 6 | AI65: PH_G1_C01_P1.4.2 | AJ65: To compare and order numbers within 10 | AP65: Published | AQ65: =IF($AP65="Raw Manuscript created","Editor to review",IF($AP65="Manuscript reviewed by Editor","Author to revise",IF($AP65="Manuscript revised by Author","Editor to review",IF($AP65="Manuscript finalised by Editor","Evonne to PFP",IF($AP65="Manuscript approved by Evonne","Evelyn to upload to Learnosity",IF($AP65="Manuscript uploaded to Learnosity","Prepress to create Activity",IF($AP65="Ready practice on Learnosity","Prepress to create Activity",IF($AP65="Activity created","Editor to conduct Learnosity review",IF($AP65="Published","Completed",""))))))))) -> Completed
A66: Chapter 7: Addition and Subtraction Within 20 | B66: Unit 1: Addition Within 20 | C66: 1.1 Adding two 1-digit numbers by making 10 | D66: PINE_G1_C07_P1.1.1 | E66: Ch 7 Practice 1.1.1: Adding two 1-digit numbers by making 10 | F66: To add two 1-digit numbers with regrouping using the ‘make 10’ method | G66: 1 | H66: 7 (Rev2) | J66: 1.062 To add two 1-digit numbers with regrouping using the ‘make 10’ method M1NS-IIa-26.1 | K66: M1NS-IIa-26.1 | L66: Visualizes and adds two one-digit numbers with sums up to 18 using the order and zero properties of addition | M66: M1NS-IIa-26.1: Visualizes and adds two one-digit numbers with sums up to 18 using the order and zero properties of addition. | N66: 1.018 Visualizes and adds two one-digit numbers with sums up to 18 M1NS-IIa-26.1 | O66: P1/P2/A1/A2 | P66: PH_G1_C07_P1.1.1 | Q66: =E66 -> Ch 7 Practice 1.1.1: Adding two 1-digit numbers by making 10 | R66: PH, PR1MEPH | S66: Practice | T66: MATHPRO | U66: Grade 1 | V66: Chapter 7 Addition and Subtraction Within 20 | W66: 9789814969369 | X66: 83 | Y66: 1. Numbers and Number Sense | Z66: G1.1.02 Addition / Subtraction | AA66: Addition Within 20 | AB66: =J66 -> 1.062 To add two 1-digit numbers with regrouping using the ‘make 10’ method M1NS-IIa-26.1 | AC66: =Y66 -> 1. Numbers and Number Sense | AD66: =Z66 -> G1.1.02 Addition / Subtraction | AE66: =K66 -> M1NS-IIa-26.1 | AF66: =M66 -> M1NS-IIa-26.1: Visualizes and adds two one-digit numbers with sums up to 18 using the order and zero properties of addition. | AG66: =N66 -> 1.018 Visualizes and adds two one-digit numbers with sums up to 18 M1NS-IIa-26.1 | AH66: 7 | AI66: PH_G1_C06_P1.2.1 | AJ66: To count within 20 by making a 10 first | AP66: Published | AQ66: =IF($AP66="Raw Manuscript created","Editor to review",IF($AP66="Manuscript reviewed by Editor","Author to revise",IF($AP66="Manuscript revised by Author","Editor to review",IF($AP66="Manuscript finalised by Editor","Evonne to PFP",IF($AP66="Manuscript approved by Evonne","Evelyn to upload to Learnosity",IF($AP66="Manuscript uploaded to Learnosity","Prepress to create Activity",IF($AP66="Ready practice on Learnosity","Prepress to create Activity",IF($AP66="Activity created","Editor to conduct Learnosity review",IF($AP66="Published","Completed",""))))))))) -> Completed
C67: 1.2 Adding a 1-digit and a 2-digit number | D67: PINE_G1_C07_P1.2.1 | E67: Ch 7 Practice 1.2.1: Adding a 1-digit and a 2-digit number | F67: To add a 1-digit number and a 2-digit number within 20 | G67: 2 | H67: 4 (Rev3) | J67: 1.063 To add a 1-digit number and a 2-digit number within 20 M1NS-IIa-26.1 | K67: M1NS-IIa-26.1 | L67: Visualizes and adds two one-digit numbers with sums up to 18 using the order and zero properties of addition | M67: M1NS-IIa-26.1: Visualizes and adds two one-digit numbers with sums up to 18 using the order and zero properties of addition. | N67: 1.018 Visualizes and adds two one-digit numbers with sums up to 18 M1NS-IIa-26.1 | O67: P1/P2/A1/A2 | P67: PH_G1_C07_P1.2.1 | Q67: =E67 -> Ch 7 Practice 1.2.1: Adding a 1-digit and a 2-digit number | R67: PH, PR1MEPH | S67: Practice | T67: MATHPRO | U67: Grade 1 | V67: Chapter 7 Addition and Subtraction Within 20 | W67: 9789814969369 | X67: 85 | Y67: 1. Numbers and Number Sense | Z67: G1.1.02 Addition / Subtraction | AA67: Addition Within 20 | AB67: =J67 -> 1.063 To add a 1-digit number and a 2-digit number within 20 M1NS-IIa-26.1 | AC67: =Y67 -> 1. Numbers and Number Sense | AD67: =Z67 -> G1.1.02 Addition / Subtraction | AE67: =K67 -> M1NS-IIa-26.1 | AF67: =M67 -> M1NS-IIa-26.1: Visualizes and adds two one-digit numbers with sums up to 18 using the order and zero properties of addition. | AG67: =N67 -> 1.018 Visualizes and adds two one-digit numbers with sums up to 18 M1NS-IIa-26.1 | AH67: 7 | AI67: PH_G1_C07_P1.1.1 | AJ67: To add two 1-digit numbers with regrouping using the ‘make 10’ method | AP67: Published | AQ67: =IF($AP67="Raw Manuscript created","Editor to review",IF($AP67="Manuscript reviewed by Editor","Author to revise",IF($AP67="Manuscript revised by Author","Editor to review",IF($AP67="Manuscript finalised by Editor","Evonne to PFP",IF($AP67="Manuscript approved by Evonne","Evelyn to upload to Learnosity",IF($AP67="Manuscript uploaded to Learnosity","Prepress to create Activity",IF($AP67="Ready practice on Learnosity","Prepress to create Activity",IF($AP67="Activity created","Editor to conduct Learnosity review",IF($AP67="Published","Completed",""))))))))) -> Completed
C68: 1.3 Adding by counting on | D68: PINE_G1_C07_P1.3.1 | E68: Ch 7 Practice 1.3.1: Adding by counting on | F68: To add two numbers, one of which is 1, 2 or 3, within 20 using the ‘counting on’ method | G68: 3 | J68: 1.064 To add two numbers within 20 using the ‘counting on’ method M1NS-IIa-26.1 | K68: M1NS-IIa-26.1 | L68: Visualizes and adds two one-digit numbers with sums up to 18 using the order and zero properties of addition | M68: M1NS-IIa-26.1: Visualizes and adds two one-digit numbers with sums up to 18 using the order and zero properties of addition. | N68: 1.018 Visualizes and adds two one-digit numbers with sums up to 18 M1NS-IIa-26.1 | O68: P1/P2/A1/A2 | P68: PH_G1_C07_P1.3.1 | Q68: =E68 -> Ch 7 Practice 1.3.1: Adding by counting on | R68: PH, PR1MEPH | S68: Practice | T68: MATHPRO | U68: Grade 1 | V68: Chapter 7 Addition and Subtraction Within 20 | W68: 9789814969369 | X68: 86 | Y68: 1. Numbers and Number Sense | Z68: G1.1.02 Addition / Subtraction | AA68: Addition Within 20 | AB68: =J68 -> 1.064 To add two numbers within 20 using the ‘counting on’ method M1NS-IIa-26.1 | AC68: =Y68 -> 1. Numbers and Number Sense | AD68: =Z68 -> G1.1.02 Addition / Subtraction | AE68: =K68 -> M1NS-IIa-26.1 | AF68: =M68 -> M1NS-IIa-26.1: Visualizes and adds two one-digit numbers with sums up to 18 using the order and zero properties of addition. | AG68: =N68 -> 1.018 Visualizes and adds two one-digit numbers with sums up to 18 M1NS-IIa-26.1 | AH68: 7 | AI68: PH_G1_C06_P1.3.1 | AJ68: To count on and backwards by 1 or 2 within 20 | AP68: Published | AQ68: =IF($AP68="Raw Manuscript created","Editor to review",IF($AP68="Manuscript reviewed by Editor","Author to revise",IF($AP68="Manuscript revised by Author","Editor to review",IF($AP68="Manuscript finalised by Editor","Evonne to PFP",IF($AP68="Manuscript approved by Evonne","Evelyn to upload to Learnosity",IF($AP68="Manuscript uploaded to Learnosity","Prepress to create Activity",IF($AP68="Ready practice on Learnosity","Prepress to create Activity",IF($AP68="Activity created","Editor to conduct Learnosity review",IF($AP68="Published","Completed",""))))))))) -> Completed
C69: 1.4 Doubles facts to 20 | D69: PINE_G1_C07_P1.4.1 | E69: Ch 7 Practice 1.4.1: Identifying doubles facts to 20 | F69: To identify a doubles fact | G69: 4 | I69: EOY_5 | J69: 1.065 To identify a doubles fact M1NS-IIa-28.1a | K69: M1NS-IIa-28.1a | L69: Adds two one-digit numbers using appropriate mental techniques eg adding doubles and/or near-doubles | M69: M1NS-IIa-28.1a: Adds two one-digit numbers using appropriate mental techniques. | N69: 1.019 Adds two one-digit numbers M1NS-IIa-28.1a | O69: P1/P2/A1/A2 | P69: PH_G1_C07_P1.4.1 | Q69: =E69 -> Ch 7 Practice 1.4.1: Identifying doubles facts to 20 | R69: PH, PR1MEPH | S69: Practice | T69: MATHPRO | U69: Grade 1 | V69: Chapter 7 Addition and Subtraction Within 20 | W69: 9789814969369 | X69: 88 | Y69: 1. Numbers and Number Sense | Z69: G1.1.02 Addition / Subtraction | AA69: Addition Within 20 | AB69: =J69 -> 1.065 To identify a doubles fact M1NS-IIa-28.1a | AC69: =Y69 -> 1. Numbers and Number Sense | AD69: =Z69 -> G1.1.02 Addition / Subtraction | AE69: =K69 -> M1NS-IIa-28.1a | AF69: =M69 -> M1NS-IIa-28.1a: Adds two one-digit numbers using appropriate mental techniques. | AG69: =N69 -> 1.019 Adds two one-digit numbers M1NS-IIa-28.1a | AH69: 7 | AI69: PH_G1_C03_P3.3.1 | AJ69: To recall an addition fact within 10 | AP69: Published | AQ69: =IF($AP69="Raw Manuscript created","Editor to review",IF($AP69="Manuscript reviewed by Editor","Author to revise",IF($AP69="Manuscript revised by Author","Editor to review",IF($AP69="Manuscript finalised by Editor","Evonne to PFP",IF($AP69="Manuscript approved by Evonne","Evelyn to upload to Learnosity",IF($AP69="Manuscript uploaded to Learnosity","Prepress to create Activity",IF($AP69="Ready practice on Learnosity","Prepress to create Activity",IF($AP69="Activity created","Editor to conduct Learnosity review",IF($AP69="Published","Completed",""))))))))) -> Completed
D70: PINE_G1_C07_P1.4.2 | E70: Ch 7 Practice 1.4.2: Adding a number to itself | F70: To add two 1-digit numbers which are the same | G70: 5 | J70: 1.066 To add two 1-digit numbers which are the same M1NS-IIa-28.1a | K70: M1NS-IIa-28.1a | L70: Adds two one-digit numbers using appropriate mental techniques eg adding doubles and/or near-doubles | M70: M1NS-IIa-28.1a: Adds two one-digit numbers using appropriate mental techniques. | N70: 1.019 Adds two one-digit numbers M1NS-IIa-28.1a | O70: P1/P2/A1/A2 | P70: PH_G1_C07_P1.4.2 | Q70: =E70 -> Ch 7 Practice 1.4.2: Adding a number to itself | R70: PH, PR1MEPH | S70: Practice | T70: MATHPRO | U70: Grade 1 | V70: Chapter 7 Addition and Subtraction Within 20 | W70: 9789814969369 | X70: 88 | Y70: 1. Numbers and Number Sense | Z70: G1.1.02 Addition / Subtraction | AA70: Addition Within 20 | AB70: =J70 -> 1.066 To add two 1-digit numbers which are the same M1NS-IIa-28.1a | AC70: =Y70 -> 1. Numbers and Number Sense | AD70: =Z70 -> G1.1.02 Addition / Subtraction | AE70: =K70 -> M1NS-IIa-28.1a | AF70: =M70 -> M1NS-IIa-28.1a: Adds two one-digit numbers using appropriate mental techniques. | AG70: =N70 -> 1.019 Adds two one-digit numbers M1NS-IIa-28.1a | AH70: 7 | AI70: PH_G1_C03_P3.3.2 | AJ70: To add two numbers which are the same | AP70: Published | AQ70: =IF($AP70="Raw Manuscript created","Editor to review",IF($AP70="Manuscript reviewed by Editor","Author to revise",IF($AP70="Manuscript revised by Author","Editor to review",IF($AP70="Manuscript finalised by Editor","Evonne to PFP",IF($AP70="Manuscript approved by Evonne","Evelyn to upload to Learnosity",IF($AP70="Manuscript uploaded to Learnosity","Prepress to create Activity",IF($AP70="Ready practice on Learnosity","Prepress to create Activity",IF($AP70="Activity created","Editor to conduct Learnosity review",IF($AP70="Published","Completed",""))))))))) -> Completed
C71: 1.5 Using doubles facts to add | D71: PINE_G1_C07_P1.5.1 | E71: Ch 7 Practice 1.5.1: Using doubles facts to add | F71: To add two 1-digit numbers using the ‘doubles plus 1’ method To determine if equations involving addition are true or false | G71: 6 | J71: 1.067 To add two 1-digit numbers using the ‘doubles plus 1’ method M1NS-IIa-28.1a | K71: M1NS-IIa-28.1a | L71: Adds two one-digit numbers using appropriate mental techniques eg adding doubles and/or near-doubles | M71: M1NS-IIa-28.1a: Adds two one-digit numbers using appropriate mental techniques. | N71: 1.019 Adds two one-digit numbers M1NS-IIa-28.1a | O71: P1/P2/A1/A2 | P71: PH_G1_C07_P1.5.1 | Q71: =E71 -> Ch 7 Practice 1.5.1: Using doubles facts to add | R71: PH, PR1MEPH | S71: Practice | T71: MATHPRO | U71: Grade 1 | V71: Chapter 7 Addition and Subtraction Within 20 | W71: 9789814969369 | X71: 89 | Y71: 1. Numbers and Number Sense | Z71: G1.1.02 Addition / Subtraction | AA71: Addition Within 20 | AB71: =J71 -> 1.067 To add two 1-digit numbers using the ‘doubles plus 1’ method M1NS-IIa-28.1a | AC71: =Y71 -> 1. Numbers and Number Sense | AD71: =Z71 -> G1.1.02 Addition / Subtraction | AE71: =K71 -> M1NS-IIa-28.1a | AF71: =M71 -> M1NS-IIa-28.1a: Adds two one-digit numbers using appropriate mental techniques. | AG71: =N71 -> 1.019 Adds two one-digit numbers M1NS-IIa-28.1a | AH71: 7 | AI71: PH_G1_C07_P1.4.2 | AJ71: To add two 1-digit numbers which are the same | AP71: Published | AQ71: =IF($AP71="Raw Manuscript created","Editor to review",IF($AP71="Manuscript reviewed by Editor","Author to revise",IF($AP71="Manuscript revised by Author","Editor to review",IF($AP71="Manuscript finalised by Editor","Evonne to PFP",IF($AP71="Manuscript approved by Evonne","Evelyn to upload to Learnosity",IF($AP71="Manuscript uploaded to Learnosity","Prepress to create Activity",IF($AP71="Ready practice on Learnosity","Prepress to create Activity",IF($AP71="Activity created","Editor to conduct Learnosity review",IF($AP71="Published","Completed",""))))))))) -> Completed
C72: 1.6 Finding the missing number in an addition sentence | D72: PINE_G1_C07_P3.1.1 | E72: Ch 7 Practice 1.6.1: Finding the missing part in an addition sentence | F72: To find the missing part in an addition sentence | G72: 7 | H72: 8 (Rev2) | J72: 1.068 To find the missing part in an addition sentence M1AL-IIIj-10 | K72: M1AL-IIIj-10 | L72: Visualizes and finds the missing number in an addition or subtraction sentence using a variety of ways eg n + 2 = 5 5 – n = 3 | M72: M1AL-IIIj-10: Visualizes and finds the missing number in an addition or subtraction sentence using a variety of ways. | N72: 1.052 Visualizes and finds the missing number in an addition or subtraction sentence M1AL-IIIj-10 | O72: P1/P2/A1/A2 | P72: PH_G1_C07_P1.6.1 | Q72: =E72 -> Ch 7 Practice 1.6.1: Finding the missing part in an addition sentence | R72: PH, PR1MEPH | S72: Practice | T72: MATHPRO | U72: Grade 1 | V72: Chapter 7 Addition and Subtraction Within 20 | W72: 9789814969369 | X72: 93 | Y72: 5. Patterns and Algebra | Z72: G1.1.02 Addition / Subtraction | AA72: Addition Within 20 | AB72: =J72 -> 1.068 To find the missing part in an addition sentence M1AL-IIIj-10 | AC72: =Y72 -> 5. Patterns and Algebra | AD72: =Z72 -> G1.1.02 Addition / Subtraction | AE72: =K72 -> M1AL-IIIj-10 | AF72: =M72 -> M1AL-IIIj-10: Visualizes and finds the missing number in an addition or subtraction sentence using a variety of ways. | AG72: =N72 -> 1.052 Visualizes and finds the missing number in an addition or subtraction sentence M1AL-IIIj-10 | AH72: 7 | AI72: PH_G1_C02_P1.7.1 PH_G1_C07_P1.3.1 | AJ72: To name the missing part or whole in a number bond To add two numbers, one of which is 1, 2 or 3, within 20 using the ‘counting on’ method | AP72: Published | AQ72: =IF($AP72="Raw Manuscript created","Editor to review",IF($AP72="Manuscript reviewed by Editor","Author to revise",IF($AP72="Manuscript revised by Author","Editor to review",IF($AP72="Manuscript finalised by Editor","Evonne to PFP",IF($AP72="Manuscript approved by Evonne","Evelyn to upload to Learnosity",IF($AP72="Manuscript uploaded to Learnosity","Prepress to create Activity",IF($AP72="Ready practice on Learnosity","Prepress to create Activity",IF($AP72="Activity created","Editor to conduct Learnosity review",IF($AP72="Published","Completed",""))))))))) -> Completed
B73: Unit 2: Subtraction Within 20 | C73: 2.1 Subtracting a 1-digit number from a 2-digit number | D73: PINE_G1_C07_P2.1.1 | E73: Ch 7 Practice 2.1.1: Subtracting a 1-digit number from a 2-digit number | F73: To subtract a 1-digit number from a 2-digit number within 20 without regrouping | G73: 8 | H73: 9 (Rev2) | J73: 1.069 To subtract a 1-digit number from a 2-digit number within 20 without regrouping M1NS-IIi-33.1 | K73: M1NS-IIi-33.1 | L73: Subtracts mentally one-digit numbers from two-digit minuends without regrouping using appropriate strategies | M73: M1NS-IIi-33.1: Subtracts mentally one-digit numbers from two-digit minuends without regrouping using appropriate strategies. | N73: 1.034 Subtracts mentally one-digit numbers from two-digit minuends without regrouping M1NS-IIi-33.1 | O73: P1/P2/A1/A2 | P73: PH_G1_C07_P2.1.1 | Q73: =E73 -> Ch 7 Practice 2.1.1: Subtracting a 1-digit number from a 2-digit number | R73: PH, PR1MEPH | S73: Practice | T73: MATHPRO | U73: Grade 1 | V73: Chapter 7 Addition and Subtraction Within 20 | W73: 9789814969369 | X73: 96 | Y73: 1. Numbers and Number Sense | Z73: G1.1.02 Addition / Subtraction | AA73: Subtraction Within 20 | AB73: =J73 -> 1.069 To subtract a 1-digit number from a 2-digit number within 20 without regrouping M1NS-IIi-33.1 | AC73: =Y73 -> 1. Numbers and Number Sense | AD73: =Z73 -> G1.1.02 Addition / Subtraction | AE73: =K73 -> M1NS-IIi-33.1 | AF73: =M73 -> M1NS-IIi-33.1: Subtracts mentally one-digit numbers from two-digit minuends without regrouping using appropriate strategies. | AG73: =N73 -> 1.034 Subtracts mentally one-digit numbers from two-digit minuends without regrouping M1NS-IIi-33.1 | AH73: 7 | AI73: PH_G1_C04_P2.1.2 | AJ73: To work out a subtraction fact within 10 by recalling the related number bond | AP73: Published | AQ73: =IF($AP73="Raw Manuscript created","Editor to review",IF($AP73="Manuscript reviewed by Editor","Author to revise",IF($AP73="Manuscript revised by Author","Editor to review",IF($AP73="Manuscript finalised by Editor","Evonne to PFP",IF($AP73="Manuscript approved by Evonne","Evelyn to upload to Learnosity",IF($AP73="Manuscript uploaded to Learnosity","Prepress to create Activity",IF($AP73="Ready practice on Learnosity","Prepress to create Activity",IF($AP73="Activity created","Editor to conduct Learnosity review",IF($AP73="Published","Completed",""))))))))) -> Completed
D74: PINE_G1_C07_P2.1A.1 | E74: Ch 7 Practice 2.1.2: Subtracting a 1-digit number from a 2-digit number using the ‘leading to 10’ method | F74: To subtract a 1-digit number from a 2-digit number within 20 with regrouping using the ‘leading to 10’ method | G74: 9 | J74: 1.070 To subtract a 1-digit number from a 2-digit number within 20 with regrouping using the ‘leading to 10’ method M1NS-IIh-32.4 | K74: M1NS-IIh-32.4 | L74: Visualizes, represents, and subtracts one- to two-digit numbers with minuends up to 99 with regrouping | M74: M1NS-IIh-32.4: Visualizes, represents, and subtracts one- to two-digit numbers with minuends up to 99 with regrouping. | N74: 1.033 Visualizes, represents, and subtracts one- to two-digit numbers with minuends up to 99 with regrouping M1NS-IIh-32.4 | O74: P1/P2/A1/A2 | P74: PH_G1_C07_P2.1.2 | Q74: =E74 -> Ch 7 Practice 2.1.2: Subtracting a 1-digit number from a 2-digit number using the ‘leading to 10’ method | R74: PH, PR1MEPH | S74: Practice | T74: MATHPRO | U74: Grade 1 | V74: Chapter 7 Addition and Subtraction Within 20 | W74: 9789814969369 | X74: 96 | Y74: 1. Numbers and Number Sense | Z74: G1.1.02 Addition / Subtraction | AA74: Subtraction Within 20 | AB74: =J74 -> 1.070 To subtract a 1-digit number from a 2-digit number within 20 with regrouping using the ‘leading to 10’ method M1NS-IIh-32.4 | AC74: =Y74 -> 1. Numbers and Number Sense | AD74: =Z74 -> G1.1.02 Addition / Subtraction | AE74: =K74 -> M1NS-IIh-32.4 | AF74: =M74 -> M1NS-IIh-32.4: Visualizes, represents, and subtracts one- to two-digit numbers with minuends up to 99 with regrouping. | AG74: =N74 -> 1.033 Visualizes, represents, and subtracts one- to two-digit numbers with minuends up to 99 with regrouping M1NS-IIh-32.4 | AH74: 7 | AI74: PH_G1_C07_P2.1.1 | AJ74: To subtract a 1-digit number from a 2-digit number within 20 without regrouping | AP74: Published | AQ74: =IF($AP74="Raw Manuscript created","Editor to review",IF($AP74="Manuscript reviewed by Editor","Author to revise",IF($AP74="Manuscript revised by Author","Editor to review",IF($AP74="Manuscript finalised by Editor","Evonne to PFP",IF($AP74="Manuscript approved by Evonne","Evelyn to upload to Learnosity",IF($AP74="Manuscript uploaded to Learnosity","Prepress to create Activity",IF($AP74="Ready practice on Learnosity","Prepress to create Activity",IF($AP74="Activity created","Editor to conduct Learnosity review",IF($AP74="Published","Completed",""))))))))) -> Completed
C75: 2.2 Subtracting a 1-digit number from a 2-digit number using the ‘subtract from 10’ method | D75: PINE_G1_C07_P2.2.1 | E75: Ch 7 Practice 2.2.1: Subtracting a 1-digit number from a 2-digit number using the ‘subtract from 10’ method | F75: To subtract a 1-digit number from a 2-digit number within 20 with regrouping using the ‘subtract from 10’ method | G75: 10 | J75: 1.071 To subtract a 1-digit number from a 2-digit number within 20 with regrouping using the ‘subtract from 10’ method M1NS-IIh-32.4 | K75: M1NS-IIh-32.4 | L75: Visualizes, represents, and subtracts one- to two-digit numbers with minuends up to 99 with regrouping | M75: M1NS-IIh-32.4: Visualizes, represents, and subtracts one- to two-digit numbers with minuends up to 99 with regrouping. | N75: 1.033 Visualizes, represents, and subtracts one- to two-digit numbers with minuends up to 99 with regrouping M1NS-IIh-32.4 | O75: P1/P2/A1/A2 | P75: PH_G1_C07_P2.2.1 | Q75: =E75 -> Ch 7 Practice 2.2.1: Subtracting a 1-digit number from a 2-digit number using the ‘subtract from 10’ method | R75: PH, PR1MEPH | S75: Practice | T75: MATHPRO | U75: Grade 1 | V75: Chapter 7 Addition and Subtraction Within 20 | W75: 9789814969369 | X75: 99 | Y75: 1. Numbers and Number Sense | Z75: G1.1.02 Addition / Subtraction | AA75: Subtraction Within 20 | AB75: =J75 -> 1.071 To subtract a 1-digit number from a 2-digit number within 20 with regrouping using the ‘subtract from 10’ method M1NS-IIh-32.4 | AC75: =Y75 -> 1. Numbers and Number Sense | AD75: =Z75 -> G1.1.02 Addition / Subtraction | AE75: =K75 -> M1NS-IIh-32.4 | AF75: =M75 -> M1NS-IIh-32.4: Visualizes, represents, and subtracts one- to two-digit numbers with minuends up to 99 with regrouping. | AG75: =N75 -> 1.033 Visualizes, represents, and subtracts one- to two-digit numbers with minuends up to 99 with regrouping M1NS-IIh-32.4 | AH75: 7 | AI75: PH_G1_C04_P3.2.1 | AJ75: To subtract a number from 10 | AP75: Published | AQ75: =IF($AP75="Raw Manuscript created","Editor to review",IF($AP75="Manuscript reviewed by Editor","Author to revise",IF($AP75="Manuscript revised by Author","Editor to review",IF($AP75="Manuscript finalised by Editor","Evonne to PFP",IF($AP75="Manuscript approved by Evonne","Evelyn to upload to Learnosity",IF($AP75="Manuscript uploaded to Learnosity","Prepress to create Activity",IF($AP75="Ready practice on Learnosity","Prepress to create Activity",IF($AP75="Activity created","Editor to conduct Learnosity review",IF($AP75="Published","Completed",""))))))))) -> Completed
C76: 2.3 Subtracting by counting backwards | D76: PINE_G1_C07_P2.3.1 | E76: Ch 7 Practice 2.3.1: Subtracting by counting backwards | F76: To subtract 1, 2 or 3 from a number within 20 using the ‘counting backwards’ method | G76: 11 | J76: 1.072 To subtract 1, 2 or 3 from a number within 20 using the ‘counting backwards’ method M1NS-IIg-32.1 | K76: M1NS-IIg-32.1 | L76: Visualizes, represents, and subtracts one-digit numbers with minuends through 18 (basic facts) | M76: M1NS-IIg-32.1: Visualizes, represents, and subtracts one-digit numbers with minuends through 18 (basic facts). | N76: 1.030 Visualizes, represents, and subtracts one-digit numbers with minuends through 18 M1NS-IIg-32.1 | O76: P1/P2/A1/A2 | P76: PH_G1_C07_P2.3.1 | Q76: =E76 -> Ch 7 Practice 2.3.1: Subtracting by counting backwards | R76: PH, PR1MEPH | S76: Practice | T76: MATHPRO | U76: Grade 1 | V76: Chapter 7 Addition and Subtraction Within 20 | W76: 9789814969369 | X76: 102 | Y76: 1. Numbers and Number Sense | Z76: G1.1.02 Addition / Subtraction | AA76: Subtraction Within 20 | AB76: =J76 -> 1.072 To subtract 1, 2 or 3 from a number within 20 using the ‘counting backwards’ method M1NS-IIg-32.1 | AC76: =Y76 -> 1. Numbers and Number Sense | AD76: =Z76 -> G1.1.02 Addition / Subtraction | AE76: =K76 -> M1NS-IIg-32.1 | AF76: =M76 -> M1NS-IIg-32.1: Visualizes, represents, and subtracts one-digit numbers with minuends through 18 (basic facts). | AG76: =N76 -> 1.030 Visualizes, represents, and subtracts one-digit numbers with minuends through 18 M1NS-IIg-32.1 | AH76: 7 | AI76: PH_G1_C06_P1.3.1 | AJ76: To count on and backwards by 1 or 2 within 20 | AP76: Published | AQ76: =IF($AP76="Raw Manuscript created","Editor to review",IF($AP76="Manuscript reviewed by Editor","Author to revise",IF($AP76="Manuscript revised by Author","Editor to review",IF($AP76="Manuscript finalised by Editor","Evonne to PFP",IF($AP76="Manuscript approved by Evonne","Evelyn to upload to Learnosity",IF($AP76="Manuscript uploaded to Learnosity","Prepress to create Activity",IF($AP76="Ready practice on Learnosity","Prepress to create Activity",IF($AP76="Activity created","Editor to conduct Learnosity review",IF($AP76="Published","Completed",""))))))))) -> Completed
C77: 2.4 Subtracting by counting on | D77: PINE_G1_C07_P2.4.1 | E77: Ch 7 Practice 2.4.1: Subtracting by counting on | F77: To use the 'counting on' method to subtract from a number within 20 To determine if equations involving addition are true or false | G77: 12 | J77: 1.073 To use the 'counting on' method to subtract from a number within 20 M1NS-IIg-32.1 | K77: M1NS-IIg-32.1 | L77: Visualizes, represents, and subtracts one-digit numbers with minuends through 18 (basic facts) | M77: M1NS-IIg-32.1: Visualizes, represents, and subtracts one-digit numbers with minuends through 18 (basic facts). | N77: 1.030 Visualizes, represents, and subtracts one-digit numbers with minuends through 18 M1NS-IIg-32.1 | O77: P1/P2/A1/A2 | P77: PH_G1_C07_P2.4.1 | Q77: =E77 -> Ch 7 Practice 2.4.1: Subtracting by counting on | R77: PH, PR1MEPH | S77: Practice | T77: MATHPRO | U77: Grade 1 | V77: Chapter 7 Addition and Subtraction Within 20 | W77: 9789814969369 | X77: 103 | Y77: 1. Numbers and Number Sense | Z77: G1.1.02 Addition / Subtraction | AA77: Subtraction Within 20 | AB77: =J77 -> 1.073 To use the 'counting on' method to subtract from a number within 20 M1NS-IIg-32.1 | AC77: =Y77 -> 1. Numbers and Number Sense | AD77: =Z77 -> G1.1.02 Addition / Subtraction | AE77: =K77 -> M1NS-IIg-32.1 | AF77: =M77 -> M1NS-IIg-32.1: Visualizes, represents, and subtracts one-digit numbers with minuends through 18 (basic facts). | AG77: =N77 -> 1.030 Visualizes, represents, and subtracts one-digit numbers with minuends through 18 M1NS-IIg-32.1 | AH77: 7 | AI77: PH_G1_C07_P2.3.1 | AJ77: To subtract 1, 2 or 3 from a number within 20 using the ‘counting backwards’ method | AP77: Published | AQ77: =IF($AP77="Raw Manuscript created","Editor to review",IF($AP77="Manuscript reviewed by Editor","Author to revise",IF($AP77="Manuscript revised by Author","Editor to review",IF($AP77="Manuscript finalised by Editor","Evonne to PFP",IF($AP77="Manuscript approved by Evonne","Evelyn to upload to Learnosity",IF($AP77="Manuscript uploaded to Learnosity","Prepress to create Activity",IF($AP77="Ready practice on Learnosity","Prepress to create Activity",IF($AP77="Activity created","Editor to conduct Learnosity review",IF($AP77="Published","Completed",""))))))))) -> Completed
D78: PINE_G1_C07_P2.4A.1 | E78: Ch 7 Practice 2.4.2: Completing addition and subtraction sentences | F78: To use '+' or '-' correctly to complete mathematical sentences | G78: 13 | J78: 1.074 To use '+' or '-' correctly to complete mathematical sentences M1NS-Ih-12.1 | K78: M1NS-Ih-12.1 | L78: Visualizes, represents, and compares numbers up to 100 using relation symbols | M78: M1NS-Ih-12.1: Visualizes, represents, and compares numbers up to 100 using relation symbols. | N78: 1.012 Visualizes, represents, and compares numbers up to 100 M1NS-Ih-12.1 | O78: P1/P2/A1/A2 | P78: PH_G1_C07_P2.4.2 | Q78: =E78 -> Ch 7 Practice 2.4.2: Completing addition and subtraction sentences | R78: PH, PR1MEPH | S78: Practice | T78: MATHPRO | U78: Grade 1 | V78: Chapter 7 Addition and Subtraction Within 20 | W78: 9789814969369 | X78: 103 | Y78: 1. Numbers and Number Sense | Z78: G1.1.02 Addition / Subtraction | AA78: Subtraction Within 20 | AB78: =J78 -> 1.074 To use '+' or '-' correctly to complete mathematical sentences M1NS-Ih-12.1 | AC78: =Y78 -> 1. Numbers and Number Sense | AD78: =Z78 -> G1.1.02 Addition / Subtraction | AE78: =K78 -> M1NS-Ih-12.1 | AF78: =M78 -> M1NS-Ih-12.1: Visualizes, represents, and compares numbers up to 100 using relation symbols. | AG78: =N78 -> 1.012 Visualizes, represents, and compares numbers up to 100 M1NS-Ih-12.1 | AH78: 7 | AI78: PH_G1_C04_P3.2.2 | AJ78: To use '+', '-' or '=' correctly to complete mathematical sentences | AP78: Published | AQ78: =IF($AP78="Raw Manuscript created","Editor to review",IF($AP78="Manuscript reviewed by Editor","Author to revise",IF($AP78="Manuscript revised by Author","Editor to review",IF($AP78="Manuscript finalised by Editor","Evonne to PFP",IF($AP78="Manuscript approved by Evonne","Evelyn to upload to Learnosity",IF($AP78="Manuscript uploaded to Learnosity","Prepress to create Activity",IF($AP78="Ready practice on Learnosity","Prepress to create Activity",IF($AP78="Activity created","Editor to conduct Learnosity review",IF($AP78="Published","Completed",""))))))))) -> Completed
C79: 2.5 Finding the missing number in an subtraction sentence | D79: PINE_G1_C07_P3.1.2 | E79: Ch 7 Practice 2.5.1: Finding the missing part in a subtraction sentence | F79: To find the missing part in a subtraction sentence | H79: 10 (Rev2) | J79: 1.075 To find the missing part in a subtraction sentence M1AL-IIIj-10 | K79: M1AL-IIIj-10 | L79: Visualizes and finds the missing number in an addition or subtraction sentence using a variety of ways eg n + 2 = 5 5 – n = 3 | M79: M1AL-IIIj-10: Visualizes and finds the missing number in an addition or subtraction sentence using a variety of ways. | N79: 1.052 Visualizes and finds the missing number in an addition or subtraction sentence M1AL-IIIj-10 | O79: P1/P2/A1/A2 | P79: PH_G1_C07_P2.5.1 | Q79: =E79 -> Ch 7 Practice 2.5.1: Finding the missing part in a subtraction sentence | R79: PH, PR1MEPH | S79: Practice | T79: MATHPRO | U79: Grade 1 | V79: Chapter 7 Addition and Subtraction Within 20 | W79: 9789814969369 | X79: 106 | Y79: 5. Patterns and Algebra | Z79: G1.1.02 Addition / Subtraction | AA79: Subtraction Within 20 | AB79: =J79 -> 1.075 To find the missing part in a subtraction sentence M1AL-IIIj-10 | AC79: =Y79 -> 5. Patterns and Algebra | AD79: =Z79 -> G1.1.02 Addition / Subtraction | AE79: =K79 -> M1AL-IIIj-10 | AF79: =M79 -> M1AL-IIIj-10: Visualizes and finds the missing number in an addition or subtraction sentence using a variety of ways. | AG79: =N79 -> 1.052 Visualizes and finds the missing number in an addition or subtraction sentence M1AL-IIIj-10 | AH79: 7 | AI79: PH_G1_C02_P1.7.1 | AJ79: To name the missing part or whole in a number bond | AP79: Published | AQ79: =IF($AP79="Raw Manuscript created","Editor to review",IF($AP79="Manuscript reviewed by Editor","Author to revise",IF($AP79="Manuscript revised by Author","Editor to review",IF($AP79="Manuscript finalised by Editor","Evonne to PFP",IF($AP79="Manuscript approved by Evonne","Evelyn to upload to Learnosity",IF($AP79="Manuscript uploaded to Learnosity","Prepress to create Activity",IF($AP79="Ready practice on Learnosity","Prepress to create Activity",IF($AP79="Activity created","Editor to conduct Learnosity review",IF($AP79="Published","Completed",""))))))))) -> Completed
D80: PINE_G1_C07_P3.2.1 | E80: Ch 7 Practice 2.5.2: Finding the missing whole in a subtraction sentence | F80: To find the missing whole in a subtraction sentence | I80: A_07 | J80: 1.076 To find the missing whole in a subtraction sentence M1NS-IIh-32.4 | K80: M1NS-IIh-32.4 | L80: Visualizes, represents, and subtracts one- to two-digit numbers with minuends up to 99 with regrouping | M80: M1NS-IIh-32.4: Visualizes, represents, and subtracts one- to two-digit numbers with minuends up to 99 with regrouping. | N80: 1.033 Visualizes, represents, and subtracts one- to two-digit numbers with minuends up to 99 with regrouping M1NS-IIh-32.4 | O80: P1/P2/A1/A2 | P80: PH_G1_C07_P2.5.2 | Q80: =E80 -> Ch 7 Practice 2.5.2: Finding the missing whole in a subtraction sentence | R80: PH, PR1MEPH | S80: Practice | T80: MATHPRO | U80: Grade 1 | V80: Chapter 7 Addition and Subtraction Within 20 | W80: 9789814969369 | X80: 106 | Y80: 1. Numbers and Number Sense | Z80: G1.1.02 Addition / Subtraction | AA80: Subtraction Within 20 | AB80: =J80 -> 1.076 To find the missing whole in a subtraction sentence M1NS-IIh-32.4 | AC80: =Y80 -> 1. Numbers and Number Sense | AD80: =Z80 -> G1.1.02 Addition / Subtraction | AE80: =K80 -> M1NS-IIh-32.4 | AF80: =M182 -> M1NS-IIh-32.4: Visualizes, represents, and subtracts one- to two-digit numbers with minuends up to 99 with regrouping. | AG80: =N182 -> 1.033 Visualizes, represents, and subtracts one- to two-digit numbers with minuends up to 99 with regrouping M1NS-IIh-32.4 | AH80: 7 | AI80: PH_G1_C02_P1.7.1 | AJ80: To name the missing part or whole in a number bond | AP80: Published | AQ80: =IF($AP80="Raw Manuscript created","Editor to review",IF($AP80="Manuscript reviewed by Editor","Author to revise",IF($AP80="Manuscript revised by Author","Editor to review",IF($AP80="Manuscript finalised by Editor","Evonne to PFP",IF($AP80="Manuscript approved by Evonne","Evelyn to upload to Learnosity",IF($AP80="Manuscript uploaded to Learnosity","Prepress to create Activity",IF($AP80="Ready practice on Learnosity","Prepress to create Activity",IF($AP80="Activity created","Editor to conduct Learnosity review",IF($AP80="Published","Completed",""))))))))) -> Completed
B81: Unit 3: Problem Solving | C81: 3.1 Word problems | D81: PINE_G1_C07_P4.1.1 | E81: Ch 7 Practice 3.1.1: Word problems | F81: To solve 1-step word problems involving addition or subtraction of numbers within 20 | H81: 19, 20 (Rev2) | J81: 1.077 To solve 1-step word problems involving addition or subtraction of numbers within 20 M1NS-IIi-34.1 | K81: M1NS-IIi-34.1 | L81: Visualizes, represents, and solves routine and non-routine problems involving subtraction of whole numbers including money with minuends up to 99 with and without regrouping using appropriate problem solving strategies and tools | M81: M1NS-IIi-34.1: Visualizes, represents, and solves routine and non-routine problems involving subtraction of whole numbers including money with minuends up to 99 with and without regrouping using appropriate problem solving strategies and tools. | N81: 1.035 Visualizes, represents, and solves routine and non-routine problems involving subtraction of whole numbers including money with minuends up to 99 with and without regrouping 1NS-IIi-34.1 | O81: P1/P2/A1/A2 | P81: PH_G1_C07_P3.1.1 | Q81: =E81 -> Ch 7 Practice 3.1.1: Word problems | R81: PH, PR1MEPH | S81: Practice | T81: MATHPRO | U81: Grade 1 | V81: Chapter 7 Addition and Subtraction Within 20 | W81: 9789814969369 | X81: 111 | Y81: 1. Numbers and Number Sense | Z81: G1.1.02 Addition / Subtraction | AA81: Problem Solving | AB81: =J81 -> 1.077 To solve 1-step word problems involving addition or subtraction of numbers within 20 M1NS-IIi-34.1 | AC81: =Y81 -> 1. Numbers and Number Sense | AD81: =Z81 -> G1.1.02 Addition / Subtraction | AE81: =K81 -> M1NS-IIi-34.1 | AF81: =M81 -> M1NS-IIi-34.1: Visualizes, represents, and solves routine and non-routine problems involving subtraction of whole numbers including money with minuends up to 99 with and without regrouping using appropriate problem solving strategies and tools. | AG81: =N81 -> 1.035 Visualizes, represents, and solves routine and non-routine problems involving subtraction of whole numbers including money with minuends up to 99 with and without regrouping 1NS-IIi-34.1 | AH81: 7 | AI81: PH_G1_C07_P1.3.1 PH_G1_C07_P2.2.1 | AJ81: To add two numbers, one of which is 1, 2 or 3, within 20 using the ‘counting on’ method To subtract a 1-digit number from a 2-digit number within 20 with regrouping using the ‘subtract from 10’ method | AP81: Published | AQ81: =IF($AP81="Raw Manuscript created","Editor to review",IF($AP81="Manuscript reviewed by Editor","Author to revise",IF($AP81="Manuscript revised by Author","Editor to review",IF($AP81="Manuscript finalised by Editor","Evonne to PFP",IF($AP81="Manuscript approved by Evonne","Evelyn to upload to Learnosity",IF($AP81="Manuscript uploaded to Learnosity","Prepress to create Activity",IF($AP81="Ready practice on Learnosity","Prepress to create Activity",IF($AP81="Activity created","Editor to conduct Learnosity review",IF($AP81="Published","Completed",""))))))))) -> Completed
D82: PINE_G1_C07_P4.1.2 | E82: Ch 7 Practice 3.1.2: Checking answers | F82: To check the answer to an addition by adding the numbers in a different order To check the answer to a subtraction by adding the answer to the smaller number in the question To check reasonableness of answers | J82: 1.078 To check reasonableness of answers M1NS-IIe-29.1 | K82: M1NS-IIe-29.1 | L82: Visualizes and solves one-step routine and non-routine problems involving addition of whole numbers including money with sums up to 99 using appropriate problem solving strategies | M82: M1NS-IIe-29.1: Visualizes and solves one-step routine and non-routine problems involving addition of whole numbers including money with sums up to 99 using appropriate problem solving strategies. | N82: 1.026 Visualizes and solves one-step routine and non-routine problems involving addition of whole numbers including money with sums up to 99 M1NS-IIe- 29.1 | O82: P1/P2/A1/A2 | P82: PH_G1_C07_P3.1.2 | Q82: =E82 -> Ch 7 Practice 3.1.2: Checking answers | R82: PH, PR1MEPH | S82: Practice | T82: MATHPRO | U82: Grade 1 | V82: Chapter 7 Addition and Subtraction Within 20 | W82: 9789814969369 | X82: 111 | Y82: 1. Numbers and Number Sense | Z82: G1.1.02 Addition / Subtraction | AA82: Problem Solving | AB82: =J82 -> 1.078 To check reasonableness of answers M1NS-IIe-29.1 | AC82: =Y82 -> 1. Numbers and Number Sense | AD82: =Z82 -> G1.1.02 Addition / Subtraction | AE82: =K82 -> M1NS-IIe-29.1 | AF82: =M82 -> M1NS-IIe-29.1: Visualizes and solves one-step routine and non-routine problems involving addition of whole numbers including money with sums up to 99 using appropriate problem solving strategies. | AG82: =N82 -> 1.026 Visualizes and solves one-step routine and non-routine problems involving addition of whole numbers including money with sums up to 99 M1NS-IIe- 29.1 | AH82: 7 | AI82: PH_G1_C07_P3.1.1 | AJ82: To solve 1-step word problems involving addition or subtraction of numbers within 20 | AP82: Published | AQ82: =IF($AP82="Raw Manuscript created","Editor to review",IF($AP82="Manuscript reviewed by Editor","Author to revise",IF($AP82="Manuscript revised by Author","Editor to review",IF($AP82="Manuscript finalised by Editor","Evonne to PFP",IF($AP82="Manuscript approved by Evonne","Evelyn to upload to Learnosity",IF($AP82="Manuscript uploaded to Learnosity","Prepress to create Activity",IF($AP82="Ready practice on Learnosity","Prepress to create Activity",IF($AP82="Activity created","Editor to conduct Learnosity review",IF($AP82="Published","Completed",""))))))))) -> Completed | AR82: Unpublished these practices as they are not part of Prime PH curriculum
D83: PINE_G1_C07_P4.2B.1 | E83: Ch 7 Practice 3.1.3: More word problems (1) | F83: To solve 1-step word problems involving addition or subtraction of numbers within 20 by drawing a picture | G83: 14 | J83: 1.079 To solve 1-step word problems within 20 M1NS-IIi-34.1 | K83: M1NS-IIi-34.1 | L83: Visualizes, represents, and solves routine and non-routine problems involving subtraction of whole numbers including money with minuends up to 99 with and without regrouping using appropriate problem solving strategies and tools | M83: M1NS-IIi-34.1: Visualizes, represents, and solves routine and non-routine problems involving subtraction of whole numbers including money with minuends up to 99 with and without regrouping using appropriate problem solving strategies and tools. | N83: 1.035 Visualizes, represents, and solves routine and non-routine problems involving subtraction of whole numbers including money with minuends up to 99 with and without regrouping 1NS-IIi-34.1 | O83: P1/P2/A1/A2 | P83: PH_G1_C07_P3.1.3 | Q83: =E83 -> Ch 7 Practice 3.1.3: More word problems (1) | R83: PH, PR1MEPH | S83: Practice | T83: MATHPRO | U83: Grade 1 | V83: Chapter 7 Addition and Subtraction Within 20 | W83: 9789814969369 | X83: 111 | Y83: 1. Numbers and Number Sense | Z83: G1.1.02 Addition / Subtraction | AA83: Problem Solving | AB83: =J83 -> 1.079 To solve 1-step word problems within 20 M1NS-IIi-34.1 | AC83: =Y83 -> 1. Numbers and Number Sense | AD83: =Z83 -> G1.1.02 Addition / Subtraction | AE83: =K83 -> M1NS-IIi-34.1 | AF83: =M83 -> M1NS-IIi-34.1: Visualizes, represents, and solves routine and non-routine problems involving subtraction of whole numbers including money with minuends up to 99 with and without regrouping using appropriate problem solving strategies and tools. | AG83: =N83 -> 1.035 Visualizes, represents, and solves routine and non-routine problems involving subtraction of whole numbers including money with minuends up to 99 with and without regrouping 1NS-IIi-34.1 | AH83: 7 | AI83: PH_G1_C07_P3.1.1 | AJ83: To solve 1-step word problems involving addition or subtraction of numbers within 20 | AP83: Published | AQ83: =IF($AP83="Raw Manuscript created","Editor to review",IF($AP83="Manuscript reviewed by Editor","Author to revise",IF($AP83="Manuscript revised by Author","Editor to review",IF($AP83="Manuscript finalised by Editor","Evonne to PFP",IF($AP83="Manuscript approved by Evonne","Evelyn to upload to Learnosity",IF($AP83="Manuscript uploaded to Learnosity","Prepress to create Activity",IF($AP83="Ready practice on Learnosity","Prepress to create Activity",IF($AP83="Activity created","Editor to conduct Learnosity review",IF($AP83="Published","Completed",""))))))))) -> Completed
D84: PINE_G1_C07_P4.2B.2 | E84: Ch 7 Practice 3.1.4: More word problems (2) | F84: To solve 1-step word problems involving addition or subtraction of numbers within 20 by finding missing numbers in addition or subtraction sentences. | G84: 15 | I84: B_09 | J84: 1.080 To solve 1-step word problems within 20 M1NS-IIi-34.1 | K84: M1NS-IIi-34.1 | L84: Visualizes, represents, and solves routine and non-routine problems involving subtraction of whole numbers including money with minuends up to 99 with and without regrouping using appropriate problem solving strategies and tools | M84: M1NS-IIi-34.1: Visualizes, represents, and solves routine and non-routine problems involving subtraction of whole numbers including money with minuends up to 99 with and without regrouping using appropriate problem solving strategies and tools. | N84: 1.035 Visualizes, represents, and solves routine and non-routine problems involving subtraction of whole numbers including money with minuends up to 99 with and without regrouping 1NS-IIi-34.1 | O84: P1/P2/A1/A2 | P84: PH_G1_C07_P3.1.4 | Q84: =E84 -> Ch 7 Practice 3.1.4: More word problems (2) | R84: PH, PR1MEPH | S84: Practice | T84: MATHPRO | U84: Grade 1 | V84: Chapter 7 Addition and Subtraction Within 20 | W84: 9789814969369 | X84: 111 | Y84: 1. Numbers and Number Sense | Z84: G1.1.02 Addition / Subtraction | AA84: Problem Solving | AB84: =J84 -> 1.080 To solve 1-step word problems within 20 M1NS-IIi-34.1 | AC84: =Y84 -> 1. Numbers and Number Sense | AD84: =Z84 -> G1.1.02 Addition / Subtraction | AE84: =K84 -> M1NS-IIi-34.1 | AF84: =M84 -> M1NS-IIi-34.1: Visualizes, represents, and solves routine and non-routine problems involving subtraction of whole numbers including money with minuends up to 99 with and without regrouping using appropriate problem solving strategies and tools. | AG84: =N84 -> 1.035 Visualizes, represents, and solves routine and non-routine problems involving subtraction of whole numbers including money with minuends up to 99 with and without regrouping 1NS-IIi-34.1 | AH84: 7 | AI84: PH_G1_C07_P1.6.1 PH_G1_C07_P2.5.1 PH_G1_C07_P2.5.2 | AJ84: To find the missing part in an addition sentence To find the missing part in a subtraction sentence To find the missing whole in a subtraction sentence | AP84: Published | AQ84: =IF($AP84="Raw Manuscript created","Editor to review",IF($AP84="Manuscript reviewed by Editor","Author to revise",IF($AP84="Manuscript revised by Author","Editor to review",IF($AP84="Manuscript finalised by Editor","Evonne to PFP",IF($AP84="Manuscript approved by Evonne","Evelyn to upload to Learnosity",IF($AP84="Manuscript uploaded to Learnosity","Prepress to create Activity",IF($AP84="Ready practice on Learnosity","Prepress to create Activity",IF($AP84="Activity created","Editor to conduct Learnosity review",IF($AP84="Published","Completed",""))))))))) -> Completed
D85: PINE_G1_C07_P4.2B.3 | E85: Ch 7 Practice 3.1.5: Checking answers | F85: To check the answer to an addition by adding the numbers in a different order To check the answer to a subtraction by adding the answer to the smaller number in the question To check reasonableness of answers | J85: 1.081 To check reasonableness of answers M1NS-IIi-34.1 | K85: M1NS-IIi-34.1 | L85: Visualizes, represents, and solves routine and non-routine problems involving subtraction of whole numbers including money with minuends up to 99 with and without regrouping using appropriate problem solving strategies and tools | M85: M1NS-IIi-34.1: Visualizes, represents, and solves routine and non-routine problems involving subtraction of whole numbers including money with minuends up to 99 with and without regrouping using appropriate problem solving strategies and tools. | N85: 1.035 Visualizes, represents, and solves routine and non-routine problems involving subtraction of whole numbers including money with minuends up to 99 with and without regrouping 1NS-IIi-34.1 | O85: P1/P2/A1/A2 | P85: PH_G1_C07_P3.1.5 | Q85: =E85 -> Ch 7 Practice 3.1.5: Checking answers | R85: PH, PR1MEPH | S85: Practice | T85: MATHPRO | U85: Grade 1 | V85: Chapter 7 Addition and Subtraction Within 20 | W85: 9789814969369 | X85: 111 | Y85: 1. Numbers and Number Sense | Z85: G1.1.02 Addition / Subtraction | AA85: Problem Solving | AB85: =J85 -> 1.081 To check reasonableness of answers M1NS-IIi-34.1 | AC85: =Y85 -> 1. Numbers and Number Sense | AD85: =Z85 -> G1.1.02 Addition / Subtraction | AE85: =K85 -> M1NS-IIi-34.1 | AF85: =M85 -> M1NS-IIi-34.1: Visualizes, represents, and solves routine and non-routine problems involving subtraction of whole numbers including money with minuends up to 99 with and without regrouping using appropriate problem solving strategies and tools. | AG85: =N85 -> 1.035 Visualizes, represents, and solves routine and non-routine problems involving subtraction of whole numbers including money with minuends up to 99 with and without regrouping 1NS-IIi-34.1 | AH85: 7 | AI85: PH_G1_C07_P3.1.4 | AJ85: To solve 1-step word problems involving addition or subtraction of numbers within 20 by finding missing numbers in addition or subtraction sentences. | AP85: Published | AQ85: =IF($AP85="Raw Manuscript created","Editor to review",IF($AP85="Manuscript reviewed by Editor","Author to revise",IF($AP85="Manuscript revised by Author","Editor to review",IF($AP85="Manuscript finalised by Editor","Evonne to PFP",IF($AP85="Manuscript approved by Evonne","Evelyn to upload to Learnosity",IF($AP85="Manuscript uploaded to Learnosity","Prepress to create Activity",IF($AP85="Ready practice on Learnosity","Prepress to create Activity",IF($AP85="Activity created","Editor to conduct Learnosity review",IF($AP85="Published","Completed",""))))))))) -> Completed
